Workbook

Sheet Corpus
A1: # | B1: Domain — Category | C1: Part | D1: Semantic | E1: English | F1: Character | G1: Mode | H1: Russian | I1: Kazakh
A2: SHAME DOMAIN
A3: 1 | B3: Shame — Moral shame | C3: P1 | D3: caused moral shame, tears as physical manifestation; Ellen (external moral standard, parental authority) | E3: At sixteen, thanks to Mammy and Ellen, she looked sweet, charming and giddy, but she was, in reality, self-willed, vain and obstinate. She had the easily stirred passions of her Irish father and nothing except the thinnest veneer of her mother's unselfish and forbearing nature. Ellen never fully realized that it was only a veneer, for Scarlett always showed her best face to her mother, concealing her escapades, curbing her temper and appearing as sweet-natured as she could in Ellen's presence, for her mother could shame her to tears with a reproachful glance. | F3: Scarlett | G3: felt | H3: TERM: pristydit' (пристыдить) — to put to shame, to shame (someone) [ORD] PASSAGE: ибо одного укоряющего взгляда матери было достаточно, чтобы пристыдить ее до слез. TRANS: ibo odnogo ukoryayushchego vzglyada materi bylo dostatochno, chtoby pristydit' ee do slez. TRANSLATION: for a single reproachful glance from her mother was enough to shame her to tears. | I3: TERM: ŪİALTU (ҰЯЛТУ) — to make (someone) feel ashamed; to disconcert; to embarrass (causative) [KED, SZK] PASSAGE: Өзін момын етіп көрсетудің жолын білді, анасының сөге қараған жалғыз көзқарасы оны ұялтып, жылатуға жеткілікті болатын TRANS: Özın momyn etıp körsetudıñ jolyn bıldı, anasynyñ söge qarağan jalğyz közqarasy ony ūialtyp, jylatuğa jetkılıktı bolatyn TRANSLATION: She knew how to put on an air of meekness; her mother's single reproachful glance was enough to shame her into tears.
A4: 2 | B4: Shame — Moral shame | C4: P1 | D4: mild moral shame, inner accusation; no physical manifestation; Ellen (internalized moral standard) | E4: To Scarlett, the very idea of saying such things to her own mother was almost sacrilegious. And yet—and yet—there was something very pleasant about the Tarleton girls' relations with their mother, and they adored her for all that they criticized and scolded and teased her. Not, Scarlett loyally hastened to tell herself, that she would prefer a mother like Mrs. Tarleton to Ellen, but still it would be fun to romp with a mother. She knew that even that thought was disrespectful to Ellen and felt ashamed of it. | F4: Scarlett | G4: felt | H4: TERM: ustydilas' (устыдилась) — felt ashamed (pf., past fem.) [ORD] (lemma: устыдиться) PASSAGE: Но она устыдилась такой мысли, почувствовав даже в этом какое-то неуважение к Эллин TRANS: No ona ustydilas' takoy mysli, pochuvstvovav dazhe v etom kakoe-to neuvazhenie k Ellin TRANSLATION: But she felt ashamed at such a thought, sensing in it a kind of disrespect toward Ellen | I4: TERM: ŪİALU (ҰЯЛУ) — to feel ashamed; to feel shy; to be embarrassed [KED, SZK] PASSAGE: Әйтсе де мұндай ойдың өзі Эллинге деген құрметсіздік сияқты сезіліп, ұялып қалды. TRANS: Äitse de mūndai oidyñ özı Elinge degen qūrmetsızdık siaqty sezılıp, ūialyp qaldy. TRANSLATION: And yet such a thought itself felt like disrespect toward Ellen, and she felt ashamed.
A5: 3 | B5: Shame — Moral shame | C5: P3 | D5: shame at openly violating social-moral duty; mild; no physical manifestation | E5: She went hastily up the two short blocks to Peachtree Street, breathing the unfouled air in as deep gulps as her tightly laced corset would permit. She was standing on the corner, uncertain as to what she would do next, ashamed to go home to Aunt Pitty's but determined not to go back to the hospital, when Rhett Butler drove by. | F5: Scarlett | G5: felt | H5: TERM: stydno (стыдно) — it is shameful; (one) feels ashamed (impersonal predicate) [ORD] PASSAGE: ей стыдно было возвратиться к тете Питти, TRANS: ey stydno bylo vozvratit'sya k tete Pitti, TRANSLATION: she was ashamed to return to Aunt Pitty, | I5: TERM: ŪİALU (ҰЯЛУ) — to feel ashamed; to feel shy; to be embarrassed [KED, SZK] PASSAGE: Бұрышқа жеткенде әрі қарай қалай жүрерін білмей тұрып қалды; Ол Питти тәтейге баруға ұялды TRANS: Būryşqa jetkende ärı qarai qalai jürerın bılmei tūryp qaldy; Ol Pitti täteige baruğa ūialdy TRANSLATION: When she reached the corner she stood still, not knowing what to do next; she was too ashamed to go to Aunt Pitty.
A6: 4 | B6: Shame — Moral shame | C6: P3 | D6: mild moral shame about angry outburst towards a servant; inner accusation; no physical manifestation; no specific witness | E6: A sullen "Yas'm" drifted up to her and she drew a deep breath, feeling suddenly ashamed of herself. | F6: Scarlett | G6: felt | H6: TERM: ustydyas' (устыдясь) — having felt ashamed (gerund) [ORD] (lemma: устыдиться) PASSAGE: и Скарлетт глубоко вздохнула, устыдясь своей внезапной вспышки TRANS: i Skarlett gluboko vzdokhnula, ustydyas' svoey vnezapnoy vspyshki TRANSLATION: and Scarlett took a deep breath, ashamed of her sudden outburst | I6: TERM: ūialyp (ұялып) — feeling ashamed; embarrassed [KED, SZK] (lemma: ūialu / ұялу — to feel ashamed; to feel shy; to be embarrassed) PASSAGE: Скарлетт өзінің кенеттен тұтанып кеткеніне ұялып, терең күрсінді. TRANS: Skarlett özınıñ kenetten tūtanyp ketkenıne ūialyp, tereñ kürsındı. TRANSLATION: Scarlett, ashamed of her sudden outburst, sighed deeply.
A7: 5 | B7: Shame — Moral shame | C7: P3 | D7: shame about own cowardice, inadvertently exposed by Melanie; no physical manifestation | E7: What Melanie said was no more than Scarlett had been thinking but hearing it put into words infuriated her, shamed her as if her secret cowardice was written plainly in her face. | F7: Scarlett | G7: felt | H7: TERM: stydno (стыдно) — it is shameful; (one) feels ashamed (impersonal predicate) [ORD] PASSAGE: ей было стыдно, словно Мелани прочла трусливые мысли на ее лице. TRANS: ey bylo stydno, slovno Melani prochla truslivye mysli na ee litse. TRANSLATION: she felt ashamed, as if Melanie had read her cowardly thoughts on her face. | I7: TERM: ŪİALU (ҰЯЛУ) — to feel ashamed; to feel shy; to be embarrassed [KED, SZK] PASSAGE: Мелани тек Скарлеттің өзі ойлағанын дауыстап айтқан еді, бірақ Скарлетт, Мелани оның қорқынышын бетінен оқып қойғандай, ұялғаннан ашуланды. TRANS: Melani tek Skarlettıñ özı oilağanyn dauystap aitqan edı, bıraq Skarlett, Melani onyñ qorqynyşyn betınen oqyp qoiğandai, ūialğannan aşulandy. TRANSLATION: Melanie had only said aloud what Scarlett herself had been thinking, but Scarlett, as if Melanie had read her fear on her face, became angry from shame.
A8: 6 | B8: Shame — Moral shame | C8: P3 | D8: shame about unfair inner judgment; no physical manifestation; no audience | E8: By a series of limping jerks, she pulled the body down the hall toward the back porch and, pausing to wipe her forehead with the back of her hand, glanced back toward Melanie, sitting against the wall hugging her thin knees to her bare breasts. How silly of Melanie to be bothering about modesty at a time like this, Scarlett thought irritably. It was just part of her nicey-nice way of acting which had always made Scarlett despise her. Then shame rose in her. After all—after all, Melanie had dragged herself from bed so soon after having a baby and had come to her aid with a weapon too heavy even for her to lift. That had taken courage, the kind of courage Scarlett honestly knew she herself did not possess, the thin-steel, spun-silk courage which had characterized Melanie on the terrible night Atlanta fell and on the long trip home. It was the same intangible, unspectacular courage that all the Wilkeses possessed, a quality which Scarlett did not understand but to which she gave grudging tribute. | F8: Scarlett | G8: felt | H8: TERM: stydno (стыдно) — it is shameful; (one) feels ashamed (impersonal predicate) [ORD] PASSAGE: И тут ей неожиданно стало стыдно. TRANS: I tut ey neozhidanno stalo stydno. TRANSLATION: And then suddenly she felt ashamed. | I8: PASSAGE: Бірақ ол көп ұзамай ұялыс тапты. TRANS: Bıraq ol köp ūzamai ūialys tapty. TRANSLATION: But before long she felt embarrassment / a sense of shame.
A9: 7 | B9: Shame — Moral shame | C9: P4 | D9: shame ascribed to another — performative speech act (verdict / directive) | E9: "She didn't write you? Oh, I guess she was too ashamed to write you. She should be ashamed! Oh, to have such a mean sister!" | F9: Scarlett | G9: ascribed | H9: TERM: stydno (стыдно) — it is shameful; (one) feels ashamed (impersonal predicate) [ORD] PASSAGE: Ах, наверное, ей было слишком стыдно. TRANS: Akh, navernoe, ey bylo slishkom stydno. TRANSLATION: Ah, she must have been too ashamed. | I9: TERM: ŪİAT (ҰЯТ) — shame; disgrace; sense of decency (also: that which is improper) [KED, SZK] PASSAGE: Сірә, ұяты жібермеген шығар. TRANS: Sırä, ūiaty jıbermegen şyğar. TRANSLATION: Most likely shame did not let her [write].
A10: 8 | B10: Shame — Moral shame | C10: P4 | D10: mild shame about being thought better than she is; no physical manifestation; community / diffuse audience | E10: She felt puzzled and a little ashamed, as always when people attributed to her emotions and motives they possessed and thought she shared. | F10: Scarlett | G10: felt | H10: TERM: pristyzhennoy (пристыженной) — shamed, abashed (past pass. participle) [ORD] (lemma: пристыженный) PASSAGE: Скарлетт была озадачена и чувствовала себя немного пристыженной TRANS: Skarlett byla ozadachena i chuvstvovala sebya nemnogo pristyzhennoy TRANSLATION: Scarlett was puzzled and felt herself a bit shamed | I10: TERM: QOLAİSYZ (ҚОЛАЙСЫЗ) — inappropriate; inconvenient; awkward [KED, SZK] PASSAGE: Скарлеттің көңілі алаңдап, өзін қолайсыз сезініп тұр, әйтеуір, адамдар ылғи да бұған өзінің ойлары мен сезімдерін таңады да жүреді, мұның ортақтаспайтынымен шаруалары жоқ. TRANS: Skarlettıñ köñılı alañdap, özın qolaisyz sezınıp tūr, äiteuır, adamdar ylği da būğan özınıñ oilary men sezımderın tañady da jüredı, mūnyñ ortaqtaspaitynymen şarualary joq. TRANSLATION: Scarlett was confused and felt awkward — people always ascribe to her their own thoughts and feelings, with no regard for whether she shares them.
A11: 9 | B11: Shame — Moral shame | C11: P4 | D11: Ashley’s self-directed moral shame about causing another to sacrifice | E11: "You ashamed? Why should you be ashamed? I'm the one to feel shame and I do. If it hadn't been for my stupidity you wouldn't be in this fix. You'd never have married Frank. I should never have let you leave Tara last winter. Oh, fool that I was! I should have known you—known you were desperate, so desperate that you'd— I should have—I should have—" His face went haggard. | F11: Scarlett | G11: ascribed | H11: TERM: stydno (стыдно) — it is shameful; (one) feels ashamed (impersonal predicate) [ORD] PASSAGE: Вам было стыдно? TRANS: Vam bylo stydno? TRANSLATION: You were ashamed? | I11: TERM: ŪİALU (ҰЯЛУ) — to feel ashamed; to feel shy; to be embarrassed [KED, SZK] PASSAGE: Ұялдым дейсіз бе? TRANS: Ūialdym deisız be? TRANSLATION: You say you were ashamed?
A12: 10 | B12: Shame — Moral shame | C12: P4 | D12: moral shame, Ashley’s self-accusation and pain as stimulus; physical manifestation – facial expression (eyes); Ashley as stimulus and witness | E12: The edge in his voice spoke of a raw, unhealed wound that ached within him and his words brought shame to her eyes. He was swift to see it and his face changed to gentleness. | F12: Scarlett | G12: felt | H12: TERM: slezy styda (слезы стыда) — tears of shame [ORD] (lemma: слеза) PASSAGE: Раздражение, звучавшее в его голосе, говорило о незаживающей ране, которая болела, и от его слов слезы стыда выступили у нее на глазах. TRANS: Razdrazhenie, zvuchavshee v ego golose, govorilo o nezazhivayushchey rane, kotoraya bolela, i ot ego slov slezy styda vystupili u nee na glazakh. TRANSLATION: The irritation that sounded in his voice spoke of an unhealing wound that hurt, and at his words tears of shame welled up in her eyes. | I12: PASSAGE: Эшлидің үнінде бір наланың белгісі бар секілді, жазылмаған жараның қазір де жанына батып тұрғаны байқалғанда, Скарлеттің көзінен жас тамшылары ытқып шығып, кеудесіне тырс-тырс тамды. TRANS: Eşlidıñ ünınde bır nalanyñ belgısı bar sekıldı, jazylmağan jaranyñ qazır de janyna batyp tūrğany baiqalğanda, Skarlettıñ közınen jas tamşylary ytqyp şyğyp, keudesıne tyrs-tyrs tamdy. TRANSLATION: In Ashley's voice there was, as it were, a sign of grievance — it could be felt that the unhealed wound was hurting his soul even now — and tears of shame burst from Scarlett's eyes and dripped onto her chest.
A13: 11 | B13: Shame — Moral shame | C13: P4 | D13: moral shame, inner accusation; no physical manifestation; not understanding Melanie as stimulus and moral mirror; Melanie ascribing noble motives to Scarlett when she had ulterior motives | E13: Her eyes blazed with enthusiasm and happiness and the two stared at her, Ashley with a queer stunned look, Scarlett with surprise mingled with shame. It had never occurred to her that Melanie missed Atlanta so much and longed to be back, longed for a home of her own. She had seemed so contented at Tara it came to Scarlett as a shock that she was homesick. | F13: Scarlett | G13: felt | H13: TERM: styda (стыда) — shame (genitive) [ORD] (lemma: стыд) PASSAGE: Скарлетт — со смесью удивления и стыда. TRANS: Skarlett — so smes'yu udivleniya i styda. TRANSLATION: Scarlett — with a mix of surprise and shame. | I13: TERM: ŪİAT(ҰЯТ) — shame; disgrace; sense of decency (also: that which is improper) [KED, SZK] PASSAGE: Эшли дағдарып, есін жия алмаса, Скарлетт ұяттан өртеніп әрі таңырқап тұр. TRANS: Eşli dağdaryp, esın jia almasa, Skarlett ūiattan örtenıp ärı tañyrqap tūr. TRANSLATION: While Ashley was confused and could not collect himself, Scarlett stood burning with shame and astonished.
A14: 12 | B14: Shame — Moral shame | C14: P4 | D14: moral shame, inner accusation; no physical manifestation; Melanie as moral mirror; Melanie and Ashley audience | E14: As usual when confronted by Melanie's habit of attributing worthy motives where no worth existed, Scarlett was ashamed and irritated, and suddenly she could not meet either Ashley's or Melanie's eyes. | F14: Scarlett | G14: felt | H14: TERM: styda (стыда) — shame (genitive) [ORD] (lemma: стыд) PASSAGE: И Скарлетт, столкнувшись с этим умением Мелани приписывать людям благородные поступки там, где благородством и не пахло, почувствовала, по обыкновению, прилив стыда и раздражения TRANS: I Skarlett, stolknuvshis' s etim umeniem Melani pripisyvat' lyudyam blagorodnye postupki tam, gde blagorodstvom i ne pakhlo, pochuvstvovala, po obyknoveniyu, priliv styda i razdrazheniya TRANSLATION: And Scarlett, faced with this skill of Melanie's for ascribing noble motives to people where no nobility was to be found, felt her customary surge of shame and irritation | I14: TERM: ŪİAT (ҰЯТ) — shame; disgrace; sense of decency (also: that which is improper) [KED, SZK] PASSAGE: Өзінің көрген, маңдайына бұйырған әр жақсылығын қашан да біреудің арқасында болды деп ойлайтын Меланидің мына қуанышты күйі Скарлеттің бетінен отын шығарып, ұяттан жерге кірердей болды. TRANS: Özınıñ körgen, mañdaiyna būiyrğan är jaqsylyğyn qaşan da bıreudıñ arqasynda boldy dep oilaityn Melanidıñ myna quanyşty küiı Skarlettıñ betınen otyn şyğaryp, ūiattan jerge kırerdei boldy. TRANSLATION: Melanie's joyous mood — always thinking that every good thing she had received in life had come because of someone else — made Scarlett's face burn and want to sink into the ground from shame.
... A24: 22 | B24: Shame — Moral shame | C24: P4 | D24: Moral shame observed by Scarlett | E24: Ashley was doing little better with convicts than he had done with free labor, although why, he was unable to tell. Moreover, he looked as if he were ashamed to be working convicts and he had little to say to her these days. | F24: Ashley | G24: felt | H24: TERM: stydilsya (стыдился) — felt ashamed (3sg masc. past, impf.) [ORD] (lemma: стыдиться) PASSAGE: К тому же он, казалось, стыдился того, что у него работают каторжники, и почти не общался со Скарлетт. TRANS: K tomu zhe on, kazalos', stydilsya togo, chto u nego rabotayut katorzhniki, i pochti ne obshchalsya so Skarlett. TRANSLATION: Moreover, he seemed to be ashamed that convicts were working for him, and he hardly communicated with Scarlett at all. | I24: TERM: QYSYLU (ҚЫСЫЛУ) — to feel embarrassed; to feel constrained; to be in difficulty [KED, SZK] PASSAGE: Сотталғандармен жұмыс істеп жүргеніне қысылатын да сияқты ма, Скарлеттпен де көп кездеспей жүр. TRANS: Sottalğandarmen jūmys ıstep jürgenıne qysylatyn da siaqty ma, Skarlettpen de köp kezdespei jür. TRANSLATION: It seems he is also embarrassed at working with convicts; he no longer often meets with Scarlett either.
A25: 23 | B25: Shame — Moral shame | C25: P5 | E25: And, for the first time, some of the bright glow which had enveloped him since the first day she fell in love with him began to fade imperceptibly. The tarnish of shame and guilt that enveloped her spread to him as well. Resolutely she tried to fight off this thought but it only made her cry harder. | F25: Scarlett-Ashley | G25: felt | H25: TERM: pozor (позор) — disgrace; shame; ignominy [ORD] PASSAGE: Черное пятно позора и вины, лежавшее на ней, переползло и на него. TRANS: Černoe pjatno pozora i viny, ležavšee na nej, perepolzlo i na nego. TRANSLATION: The black stain of disgrace and guilt that lay upon her spread to him as well. | I25: TERM: kınä men künä (кінә мен күнә) — guilt and sin (set phrase combining secular and religious registers) [KED, SZK] (lemma: кінә) PASSAGE: Осы уақытқа дейін өз арқасына басқан кінә мен күнәнің қап-қара нүктесі жылыстап, Эшлиге қарай ауып бара жатты. TRANS: Osy uaqytqa deiın öz arqasyna basqan kınä men künänıñ qap-qara nüktesı jylystap, Eşlige qarai auyp bara jatty. TRANSLATION: Up till now, the pitch-black mark of guilt and sin she had borne on her own back was sliding off and shifting toward Ashley.
A26: 24 | B26: Shame — Moral shame | C26: P3 | D26: Shame about being caught in a lie about knowing midwifery | E26: "Fo' Gawd, Miss Scarlett—" Fright and shame were in her rolling eyes. | F26: Prissy | G26: felt | H26: TERM: styd (стыд) — shame; the feeling of having transgressed a moral or social norm [ORD] PASSAGE: Растерянность и стыд были в ее вытаращенных от страха глазах. TRANS: Rasteryannost' i styd byli v ee vytarashchennykh ot strakha glazakh. TRANSLATION: Bewilderment and shame were in her eyes bulging with terror. | I26: TERM: ŪİALU (ҰЯЛУ) — to feel ashamed; to feel shy; to be embarrassed [KED, SZK] PASSAGE: Оның жүзінен абыржу мен ұялғандықты анық бауқауға болатын еді. TRANS: Onyñ jüzınen abyrju men ūialğandyqty anyq bauqauğa bolatyn edı. TRANSLATION: Bewilderment and shame could be clearly seen on her face.
A27: 25 | B27: Shame — Moral shame | C27: P3 | D27: Potential moral shame about spending money when he could steal | E27: She had a shrewd suspicion that the reason he had so much money left over was that he had not bought the fowls or most of the food. Pork would have taken shame to himself had he spent her money when there were unguarded hen coops along the road and smokehouses handy. | F27: Pork | G27: felt | H27: TERM: posramil by samogo sebya (посрамил бы самого себя) — would have brought shame on himself [ORD] (lemma: посрамить) PASSAGE: Порк посрамил бы самого себя, если бы потратил ее деньги TRANS: Pork posramil by samogo sebya, esli by potratil ee den'gi TRANSLATION: Pork would have shamed himself if he had spent her money | I27: PASSAGE: Скарлетт берген ақшаны жұмсаса, Порк өзін-өзі кешірмес еді. TRANS: Skarlett bergen aqşany jūmsasa, Pork özın-özı keşırmes edı. TRANSLATION: If he had spent the money Scarlett gave him, Pork would not forgive himself.
A28: 26 | B28: Shame — Absent moral shame | C28: P2 | D28: moral conventions breached — manipulation, lies; shame ABSENT | E28: Scarlett turned and tiptoed through the silent hall into the dining room to get the brandy bottle that she and Melly privately called the "swoon bottle" because Pittypat always took a sip from it when her fluttering heart made her faint—or seem to faint. Triumph was written on her face and no trace of shame for her unfilial treatment of Gerald. Now Ellen would be soothed with lies if any other busybody wrote her. Now she could stay in Atlanta. Now she could do almost as she pleased, Pittypat being the weak vessel that she was. She unlocked the cellaret and stood for a moment with the bottle and glass pressed to her bosom. | F28: Scarlett | G28: felt | H28: TERM: nikakikh ugryzeniy sovesti (никаких угрызений совести) — no pangs of conscience whatsoever [ORD] (lemma: угрызение) PASSAGE: Лицо Скарлетт выражало торжество — никаких угрызений совести она не испытывала, хотя и поступила с Джералдом отнюдь не как любящая, преданная дочь. TRANS: Litso Skarlett vyrazhalo torzhestvo — nikakikh ugryzeniy sovesti ona ne ispytyvala, khotya i postupila s Dzheraldom otnyud' ne kak lyubyashchaya, predannaya doch'. TRANSLATION: Scarlett's face wore a triumphant expression — she felt no pangs of conscience whatsoever, although she had not behaved like a loving, devoted daughter toward Gerald. | I28: TERM: QYMSYNU (ҚЫМСЫНУ) — to feel awkward; to feel embarrassed [KED, SZK] PASSAGE: Скарлеттің бет-әлпетінде жеңіске жеткен түр байқалады, ол Джералдқа әкесін жақсы көретін адал қызы емес, бөтен біреудей қулық жасағанына еш қымсынған жоқ. TRANS: Skarlettıñ bet-älpetınde jeñıske jetken tür baiqalady, ol Jeraldqa äkesın jaqsy köretın adal qyzy emes, böten bıreudei qulyq jasağanyna eş qymsynğan joq. TRANSLATION: Scarlett's face showed a victorious expression; she felt no embarrassment at all that she had played a trick on Gerald like a stranger rather than as a loving, faithful daughter.
A29: 27 | B29: Shame — Absent moral shame | C29: P4 | D29: moral and social conventions breached — shame ABSENT; Ashley as witness | E29: She was still clutching the ball of red clay when she went up the front steps. She had carefully avoided the back entrance, for Mammy's sharp eyes would certainly have seen that something was greatly amiss. Scarlett did not want to see Mammy or anyone else. She did not feel that she could endure seeing anyone or talking to anyone again. She had no feeling of shame or disappointment or bitterness now, only a weakness of the knees and a great emptiness of heart. She squeezed the clay so tightly it ran out from her clenched fist and she said over and over, parrot-like: "I've still got this. Yes, I've still got this." | F29: Scarlett | G29: felt | H29: TERM: styd (стыд) — shame; the feeling of having transgressed a moral or social norm [ORD] PASSAGE: Ее уже не мучил стыд, разочарование или горечь — лишь была какая-то слабость в коленях да огромная пустота в душе. TRANS: Ee uzhe ne muchil styd, razocharovanie ili gorech' — lish' byla kakaya-to slabost' v kolenyakh da ogromnaya pustota v dushe. TRANSLATION: She was no longer tormented by shame, disappointment, or bitterness — only a kind of weakness in her knees and a vast emptiness in her soul. | I29: TERM: ŪİAT (ҰЯТ) — shame; disgrace; sense of decency (also: that which is improper) [KED, SZK] PASSAGE: Қалған көңіл де, қысқан ұят та бір шетке ысырылып, жан дүниесі босап, буын-буынынан әл кетіпті. TRANS: Qalğan köñıl de, qysqan ūiat ta bır şetke ysyrylyp, jan düniesı bosap, buyn-buynynan äl ketıptı. TRANSLATION: Both her remaining feelings and her gripping shame had been pushed aside; her inner being was emptied, and the strength had left her every joint.
A30: 28 | B30: Shame — Absent moral shame | C30: P5 | D30: Immoral behavior impossible with Rhett as specific witness | E30: Already she was regretting the hasty words. Had they been spoken to anyone save Rhett she would have shamelessly retracted them. Why had she burst out like that? She looked at Rhett with an angry frown and saw that he was watching her with his old keen, cat-at-a- mouse-hole look. When he saw her frown, he laughed suddenly, his white teeth flashing. Scarlett had an uncertain feeling that he had jockeyed her into this position. | F30: Scarlett | G30: felt | H30: TERM: stesneniya (стеснения) — awkwardness; constraint (gen.) [ORD] (lemma: стеснение) PASSAGE: Скажи она их кому угодно, кроме Ретта, она бы без всякого стеснения взяла их назад. TRANS: Skazhi ona ikh komu ugodno, krome Retta, ona by bez vsyakogo stesneniya vzyala ikh nazad. TRANSLATION: Had she said it to anyone but Rhett, she would have taken it back without any embarrassment. | I30: PASSAGE: Мұның бәрін кімге айтқан болса да, кейін қайтарып ала салар еді, айтқанынан қайта танар еді, тек Реттің алдында емес. TRANS: Mūnyñ bärın kımge aitqan bolsa da, keiın qaitaryp ala salar edı, aitqanynan qaita tanar edı, tek Rettıñ aldynda emes. TRANSLATION: Whoever she had said all this to, she would have taken it back, would have recanted — except in front of Rhett.
A31: 29 | B31: Shame — Absent social shame (about the body) | C31: P1 | D31: body confidence: NO shame about body as social object | E31: Of course, her brooch could be pinned over the spot, but perhaps Melanie had sharp eyes. There remained varicolored cotton dresses which Scarlett felt were not festive enough for the occasion, ball dresses and the green sprigged muslin she had worn yesterday. But it was an afternoon dress. It was not suitable for a barbecue, for it had only tiny puffed sleeves and the neck was low enough for a dancing dress. But there was nothing else to do but wear it. After all she was not ashamed of her neck and arms and bosom, even if it was not correct to show them in the morning. | F31: Scarlett | G31: felt | H31: TERM: stydit'sya (стыдиться) — to feel ashamed (imperfective); pf. постыдиться/устыдиться [ORD] PASSAGE: ей не приходится стыдиться TRANS: ey ne prikhoditsya stydit'sya TRANSLATION: she did not have to feel ashamed | I31: TERM: QYSYLU (ҚЫСЫЛУ) — to feel embarrassed; to feel constrained; to be in difficulty [KED, SZK] PASSAGE: Түптеп келгенде тіпті таңертеңнен мойнын, иығын, қолын жаңалаштау аса орынды болмаса да, сол үшін қысылуына тура келмейді. TRANS: Tüptep kelgende tıptı tañerteñnen moinyn, iyğyn, qolyn jañalaştau asa oryndy bolmasa da, sol üşın qysyluyna tura kelmeidı. TRANSLATION: After all, even though baring her neck, shoulders, and arms in the morning was not entirely proper, she did not have to feel embarrassed about it.
A32: 30 | B32: Shame — Absent social shame (about the body) | C32: P1 | D32: body confidence: NO shame about body as social object | E32: As she stood before the mirror and twisted herself about to get a side view, she thought that there was absolutely nothing about her figure to cause her shame. Her neck was short but rounded and her arms plump and enticing. Her breasts, pushed high by her stays, were very nice breasts. | F32: Scarlett | G32: felt | H32: TERM: iz"yana (изъяна) — defect; flaw (gen.) [ORD] (lemma: изъян) PASSAGE: не обнаружила в своей фигуре ни малейшего изъяна. TRANS: ne obnaruzhila v svoey figure ni maleyshego iz"yana. TRANSLATION: she found not the slightest flaw in her figure. | I32: TERM: KEMŞILIK (КЕМШІЛІК) — defect; failing; shortcoming [KED, SZK] PASSAGE: Айна алдында тұрып, ол өзін жанынан көру үшін белін майыстырып қарап, сымбатынан еш кемшілік таппады. comment: 'shame' is not directly translated. TRANS: Aina aldynda tūryp, ol özın janynan köru üşın belın maiystyryp qarap, symbatynan eş kemşılık tappady. comment: 'shame' is not directly translated. TRANSLATION: Standing before the mirror and turning sideways to view her profile, she found no flaw in her elegance.
A33: 31 | B33: Shame — Social shame | C33: P1 | D33: strong shame about social convention and exposure to societal judgment; internal burning | E33: She did not want to be fair, although she knew what he said was true. He had never once crossed the borders of friendliness with her and, when she thought of this fresh anger rose, the anger of hurt pride and feminine vanity. She had run after him and he would have none of her. He preferred a whey-faced little fool like Melanie to her. Oh, far better that she had followed Ellen and Mammy's precepts and never, never revealed that she even liked him—better anything than to be faced with this scorching shame! | F33: Scarlett | G33: felt | H33: TERM: sgorat' so styda (сгорать со стыда) — to burn up with shame (idiom) [ORD] (lemma: сгорать) PASSAGE: Пусть бы он никогда-никогда не узнал об этом — все лучше, чем так сгорать со стыда TRANS: Pust' by on nikogda-nikogda ne uznal ob etom — vse luchshe, chem tak sgorat' so styda TRANSLATION: Let him never, never know about it — anything would be better than burning up with shame so | I33: TERM: ŪİAT (ҰЯТ) — shame; disgrace; sense of decency (also: that which is improper) [KED, SZK] PASSAGE: Ах, ол неге Эллин мен Үлкен шешейдің нұсқауын тыңдамады! Эшли мұның сезімінен күдіктенбеуі керек еді! Бұлай ұяттан өртенгенше, оның бұл туралы ешқашан, еш уақытта білмегені жақсы еді! TRANS: Ah, ol nege Elin men Ülken şeşeidıñ nūsqauyn tyñdamady! Eşli mūnyñ sezımınen küdıktenbeuı kerek edı! Būlai ūiattan örtengenşe, onyñ būl turaly eşqaşan, eş uaqytta bılmegenı jaqsy edı! TRANSLATION: Ah, why had she not heeded Ellen's and Mammy's instructions! Ashley should not have suspected her feelings! Better that he should never, ever know about this than to burn up like this with shame!
A34: 32 | B34: Shame — Social shame (somatic expression) | C34: P2 | D34: strong shame about breaking social conventions and Ashley’s rejection, social exposure, physical manifestations – face crimson; Rhett witness | E34: She looked up at him imploringly, her face crimson with the shame of their last meeting, and met two of the blackest eyes she had ever seen, dancing in merciless merriment. Of all the people in the world to turn up here, this terrible person who had witnessed that scene with Ashley which still gave her nightmares; this odious wretch who ruined girls and was not received by nice people; this despicable man who had said, and with good cause, that she was not a lady. | F34: Scarlett | G34: felt | H34: TERM: Zardevshis' ot smushcheniya, (Зардевшись от смущения,) = flushing; having blushed PASSAGE: Зардевшись от смущения, она с мольбой подняла на него глаза TRANS: Zardevshis' ot smushcheniya, ona s mol'boy podnyala na nego glaza TRANSLATION: Burning crimson with embarrassment, she raised her eyes pleadingly to him | I34: TERM: ŪİALU (ҰЯЛУ) — to feel ashamed; to feel shy; to be embarrassed [KED, SZK] PASSAGE: Ұяла қысылған Скарлетт оған басын көтеріп қарады, ... TRANS: Ūiala qysylğan Skarlett oğan basyn köterıp qarady, ... TRANSLATION: Scarlett, flushed with embarrassment, raised her head and looked at him,...
A35: 33 | B35: Shame — Social shame | C35: P2 | D35: shame at absence of social tokens of pride (comparison) | E35: She flipped back the edges of the letters, looking at the dates, remembering their contents. In them there were no fine descriptive pages of bivouacs and charges such as Darcy Meade wrote his parents or poor Dallas McLure had written his old-maid sisters, Misses Faith and Hope. The Meades and McLures proudly read these letters all over the neighborhood, and Scarlett had frequently felt a secret shame that Melanie had no such letters from Ashley to read aloud at sewing circles. | F35: Scarlett | G35: felt | H35: TERM: styd (стыд) — shame; the feeling of having transgressed a moral or social norm [ORD] PASSAGE: Скарлетт не раз испытывала втайне стыд, что Эшли не пишет Мелани таких писем, которые интересно было бы почитать в швейном кружке вслух. TRANS: Skarlett ne raz ispytyvala vtayne styd, chto Eshli ne pishet Melani takikh pisem, kotorye interesno bylo by pochitat' v shveynom kruzhke vslukh. TRANSLATION: Scarlett had more than once felt secret shame that Ashley did not write Melanie letters of the kind that would be interesting to read aloud in the sewing circle. | I35: TERM: ŪİALU (ҰЯЛУ) — to feel ashamed; to feel shy; to be embarrassed [KED, SZK] PASSAGE: ... ал Скарлетт Эшлидің Меланиге мұндай хаттарды жазбағанына бірнеше рет ішінен ұялған, ... TRANS: ... al Skarlett Eşlidıñ Melanige mūndai hattardy jazbağanyna bırneşe ret ışınen ūialğan, ... TRANSLATION: ...and Scarlett had felt ashamed inwardly several times that Ashley did not write Melanie such letters,...
A36: 34 | B36: Shame — Social shame (somatic expression) | C36: P3 | D36: strong shame about breaking social-moral conventions, social exposure, face crimson; Ellen (internalized moral standard); Rhett as witness | E36: Scarlett leaped to her feet, her face red with shame. How could she have said such a thing! How could she, Ellen's daughter, with her upbringing, have sat there and listened to such debasing words and then made such a shameless reply? She should have screamed. She should have fainted. She should have turned coldly away in silence and swept from the porch. Too late now! | F36: Scarlett | G36: felt | H36: TERM: sgoraya ot styda. (сгорая от стыда.) = burning with shame PASSAGE: Скарлетт вскочила с кресла, сгорая от стыда. TRANS: Skarlett vskochila s kresla, sgoraya ot styda. TRANSLATION: Scarlett leapt up from the chair, burning with shame. | I36: TERM: ŪİAT (ҰЯТ) — shame; disgrace; sense of decency (also: that which is improper) [KED, SZK] PASSAGE: Скарлетт ұяттан өртеніп креслодан атып тұрды. TRANS: Skarlett ūiattan örtenıp kreslodan atyp tūrdy. TRANSLATION: Scarlett, burning up with shame, sprang up from the armchair.
A37: 35 | B37: Shame — Social shame | C37: P4 | D37: Deferred shame from self-humiliation through social-moral transgression; Rhett witness | E37: When he had hurried away to bring her a glass of wine and a paper thin slice of cake, Scarlett sat down in the alcove at the end of the drawing room and carefully arranged her skirts so that the worst spots would not show. The humiliating events of the morning with Rhett were pushed from her mind by the excitement of seeing so many people and hearing music again. Tomorrow she would think of Rhett's conduct and her shame and they would make her writhe again. Tomorrow she would wonder if she had made any impression on Frank's hurt and bewildered heart. But not tonight. Tonight she was alive to her finger tips, every sense alert with hope, her eyes sparkling. | F37: Scarlett | G37: felt | H37: TERM: unizhenii (унижении) — humiliation (prep.) [ORD] (lemma: унижение) PASSAGE: Завтра она снова будет думать о поведении Ретта, о своем унижении и снова будет кипеть от гнева. TRANS: Zavtra ona snova budet dumat' o povedenii Retta, o svoem unizhenii i snova budet kipet' ot gneva. TRANSLATION: Tomorrow she would once again be thinking of Rhett's behavior, of her humiliation, and would once again be seething with anger. | I37: TERM: QYSAS (ҚЫСАС) — malice; revenge; spite [KED, SZK] PASSAGE: Ертең Реттің қылығын қайтадан еске түсіріп, өзіне жасаған қысастығына күйініп, тағы да ашудан қызынатын шығар. TRANS: Erteñ Rettıñ qylyğyn qaitadan eske tüsırıp, özıne jasağan qysastyğyna küiınıp, tağy da aşudan qyzynatyn şyğar. TRANSLATION: Tomorrow she would probably again recall Rhett's behavior, again be wounded by the wrong he had done her, and again burn with anger.
... A106: 104 | B106: Shame — Performed / ironic shame | C106: P5 | D106: shame PERFORMED — not genuinely felt | E106: "Somehow," said Mrs. Elsing uncertainly, "somehow, I don't think he's so bad. A man who fought for the Confederacy can't be all bad. It's Scarlett who is the bad one. Do you know, Dolly, I really believe that he—well, he's ashamed of Scarlett but is too much of a gentleman to let on." | F106: Rhett | G106: ascribed | H106: TERM: styditsya (стыдится) — feels ashamed (3sg) [ORD] (lemma: стыдиться) PASSAGE: Знаете, Долли, мне в самом деле кажется, что он… ну, словом, что он стыдится Скарлетт, но, будучи джентльменом, не показывает этого. TRANS: Znaete, Dolli, mne v samom dele kazhetsya, chto on… nu, slovom, chto on styditsya Skarlett, no, buduchi dzhentl'menom, ne pokazyvaet etogo. TRANSLATION: You know, Dolly, it really seems to me that he... well, that he is ashamed of Scarlett, but being a gentleman, he does not show it. | I106: TERM: ŪİALU (ҰЯЛУ) — to feel ashamed; to feel shy; to be embarrassed [KED, SZK] PASSAGE: Байқайсыз ба, Долли, сірә, ол Скарлетт үшін ұялатын тәрізді ме, қалай? Тек онысын байқатпайтын сияқты. Қанша дегенмен мырза емес пе? TRANS: Baiqaisyz ba, Dolli, sırä, ol Skarlett üşın ūialatyn tärızdı me, qalai? Tek onysyn baiqatpaityn siaqty. Qanşa degenmen myrza emes pe? TRANSLATION: Don't you notice, Dolly — it seems perhaps he is ashamed for Scarlett's sake, no? But he doesn't let it show. After all, isn't he a gentleman?
A107: GUILT DOMAIN
A108: 105 | B108: Guilt — Felt guilt | C108: P1 | D108: strong felt guilt; inner moral accusation; presence of the person wronged actualizes felt guilt | E108: Since the day of the speaking, Stuart had been uncomfortable in India's presence. Not that India ever reproached him or even indicated by look or gesture that she was aware of his abruptly changed allegiance. She was too much of a lady. But Stuart felt guilty and ill at ease with her. He knew he had made India love him and he knew that she still loved him and, deep in his heart, he had the feeling that he had not played the gentleman. | F108: Stuart Tarleton | G108: felt | H108: TERM: chuvstva viny (чувства вины) — feeling of guilt (gen.) [ORD] (lemma: вина) PASSAGE: Но Стюарт не мог избавиться от чувства вины и испытывал поэтому неловкость. TRANS: No Styuart ne mog izbavit'sya ot chuvstva viny i ispytyval poetomu nelovkost'. TRANSLATION: But Stuart could not rid himself of the feeling of guilt and as a result felt awkward. | I108: TERM: KİNÄLY (КІНӘЛЫ) — guilty; at fault [KED, SZK] (lemma: кінәлі) PASSAGE: Бірақ Стюарт оның алдында өзін кінәлі сезінгендіктен ыңғайсыздықтан арыла алмады. TRANS: Biraq Styuart onyñ aldynda özin kinäli sezingendikten yñğaysyzdyqtan aryla almady. TRANSLATION: But Stuart could not rid himself of the awkwardness of feeling guilty before her.
A109: 106 | B109: Guilt — Felt guilt (guilty pleasure) | C109: P1 | D109: mild guilty pleasure — impropriety felt as pleasurable; no moral weight; Ellen as superego | E109: Scarlett had no awe of her father and felt him more her contemporary than her sisters, for jumping fences and keeping it a secret from his wife gave him a boyish pride and guilty glee that matched her own pleasure in outwitting Mammy. She rose from her seat to watch him. | F109: Gerald O’Hara | G109: felt | H109: PASSAGE: Он был как бы ее сверстником — даже больше, чем сестры, — ведь Джералд, словно мальчишка, любил втайне от жены скакать по полям напрямик, а Скарлетт — тоже большая охотница до всяких эскапад — была его верной союзницей против Мамушки. TRANS: On byl kak by ee sverstnikom — dazhe bol'she, chem sestry, — ved' Dzherald, slovno mal'chishka, lyubil vtayne ot zheny skakat' po polyam napryamik, a Skarlett — tozhe bol'shaya okhotnitsa do vsyakikh eskapad — byla ego vernoy soyuznitsey protiv Mamushki. TRANSLATION: He was, as it were, her contemporary — even more so than her sisters — for Gerald, like a boy, loved to gallop straight across the fields out of his wife's sight, and Scarlett — herself a great enthusiast of escapades — was his loyal ally against Mammy. | I109: PASSAGE: - TRANS: - TRANSLATION: -
A110: 107 | B110: Guilt — Felt guilt | C110: P1 | D110: strong felt guilt; inner moral accusation; Ellen (internalized superego) | E110: "Ah-ah-hum," said Gerald, suddenly and guiltily aware that the conversation, a most interesting and entirely proper one to him, would seem quite otherwise to Ellen. In fact, he knew she would never recover should she learn that her daughters had been exposed to so frank a conversation. But Mrs. Tarleton was, as usual, deaf to all other ideas when pursuing her favorite topic, breeding, whether it be horses or humans. | F110: Gerald O’Hara | G110: felt | H110: TERM: smushchenno (смущенно) — in embarrassment; awkwardly (adv.) [ORD] PASSAGE: — Хм, да, да, — смущенно пробормотал Джералд, до сознания которого вдруг дошло, что этот чрезвычайно интересный и вполне, на его взгляд, приличный разговор, вероятно, показался бы совсем неуместным его жене TRANS: — Khm, da, da, — smushchenno probormotal Dzherald, do soznaniya kotorogo vdrug doshlo, chto etot chrezvychayno interesnyy i vpolne, na ego vzglyad, prilichnyy razgovor, veroyatno, pokazalsya by sovsem neumestnym ego zhene TRANSLATION: "Hm, yes, yes," Gerald muttered in embarrassment, suddenly realizing that this conversation, extremely interesting and, in his view, perfectly proper, would probably appear utterly inappropriate to his wife | I110: TERM: ŪİALU (ҰЯЛУ) — to feel ashamed; to feel shy; to be embarrassed [KED, SZK] PASSAGE: ... Джералд ұялғаннан күбірлеп, ол кенет өзінің ойынша өте қызықты әрі әжептәуір әңгіме әйеліме мүлдем орынсыз болып көрінер еді деп ойлады. TRANS: ... Jerald ūialğannan kübırlep, ol kenet özınıñ oiynşa öte qyzyqty ärı äjeptäuır äñgıme äielıme müldem orynsyz bolyp körıner edı dep oilady. TRANSLATION: ... Gerald murmured in embarrassment, suddenly thinking that the conversation he found very interesting and respectable would seem entirely improper to his wife.
A111: 108 | B111: Guilt — Felt guilt (guilty pleasure) | C111: P1 | D111: mild guilty pleasure — relief mixed with guilt about feeling relief at the absence of her moral superego (Ellen) and her social conscience (Mammy) | E111: As the carriage bore her down the red road toward the Wilkes plantation, Scarlett had a feeling of guilty pleasure that neither her mother nor Mammy was with the party. There would be no one at the barbecue who, by delicately lifted brows or out-thrust underlip, could interfere with her plan of action. | F111: Scarlett | G111: felt | H111: TERM: ne bez nekotorykh ugryzeniy sovesti (не без некоторых угрызений совести) — not without some pangs of conscience [ORD] (lemma: угрызение) PASSAGE: Пока коляска, поднимая красную пыль, катилась по дороге к Двенадцати Дубам, Скарлетт, не без некоторых угрызений совести, радовалась тому, что ни Эллин, ни Мамушка не будут присутствовать на барбекю. TRANS: Poka kolyaska, podnimaya krasnuyu pyl', katilas' po doroge k Dvenadtsati Dubam, Skarlett, ne bez nekotorykh ugryzeniy sovesti, radovalas' tomu, chto ni Ellin, ni Mamushka ne budut prisutstvovat' na barbekyu. TRANSLATION: As the carriage rolled along the road to Twelve Oaks raising red dust, Scarlett, not without some pangs of conscience, was glad that neither Ellen nor Mammy would be present at the barbecue. | I111: TERM: AR (АР) — honour; conscience; inalienable inner moral principle [KED, SZK] PASSAGE: Скарлетт аздап ары мазаласа да, барбекюде Эллиннің де, Үлкен шешейдің де болмайтынына қуанды. TRANS: Skarlett azdap ary mazalasa da, barbeküde Elinnıñ de, Ülken şeşeidıñ de bolmaitynyna quandy TRANSLATION: Although Scarlett's conscience troubled her a little, she rejoiced that neither Ellen nor Mammy would be at the barbecue.
A112: 109 | B112: Guilt — Guilt as tormentor | C112: P2 | D112: felt guilt; inner moral accusation; Ellen (internalized superego); guilt about Ellen’s pain, not about scandalous conduct | E112: A cold qualm of guilt assailed Scarlett at the thought of Ellen's consternation, should she ever learn of her daughter's scandalous conduct. But she took heart at the thought of the twenty-five miles between Atlanta and Tara. Miss Pitty certainly wouldn't tell Ellen. It would put her in such a bad light as a chaperon. And if Pitty didn't tattle, she was safe. | F112: Scarlett | G112: felt | H112: TERM: raskayanie (раскаяние) — repentance; remorse [ORD] PASSAGE: Скарлетт похолодела и в душе у нее пробудилось раскаяние. TRANS: Skarlett pokholodela i v dushe u nee probudilos' raskayanie. TRANSLATION: Scarlett went cold and remorse awakened in her soul. | I112: TERM: ÖKİNİSH (ӨКІНІШ) — regret; repentance [KED, SZK] PASSAGE: Скарлетт суып сала берді де, оның жан дүниесінде өкініш пайда болды. TRANS: Skarlett suyp sala berdı de, onyñ jan düniesınde ökınış paida boldy. TRANSLATION: Scarlett grew cold, and remorse arose in her inner being.
A113: 110 | B113: Guilt — Felt guilt | C113: P2 | D113: felt guilt; child-like emotion; Ellen (internalized superego) | E113: There was more in the same vein but Scarlett did not finish it. For once, she was thoroughly frightened. She did not feel reckless and defiant now. She felt as young and guilty as when she was ten and had thrown a buttered biscuit at Suellen at the table. To think of her gentle mother reproving her so harshly and her father coming to town to talk to Captain Butler. The real seriousness of the matter grew on her. Gerald was going to be severe. This was one time when she knew she couldn't wiggle out of her punishment by sitting on his knee and being sweet and pert. | F113: Scarlett | G113: felt | H113: TERM: provinivshiysya (провинившийся) — the one at fault; one who has done wrong (active part.) [ORD] (lemma: провиниться) PASSAGE: Она чувствовала себя словно провинившийся ребенок — совсем как в десять лет, когда как-то раз за столом запустила в Сьюлин печеньем. TRANS: Ona chuvstvovala sebya slovno provinivshiysya rebenok — sovsem kak v desyat' let, kogda kak-to raz za stolom zapustila v S'yulin pechen'em. TRANSLATION: She felt as though she were a guilty child — exactly as at age ten, when she once threw a cookie at Suellen at the table. | I113: TERM: JAZYQTY (ЖАЗЫҚТЫ) — at fault; guilty [KED, SZK] PASSAGE: Сьюлинге тоқаш лақтырған кездегі жазықты болған он жасар жасөспірім кезіндегідей сезінді. TRANS: S'iulinge toqaş laqtyrğan kezdegı jazyqty bolğan on jasar jasöspırım kezındegıdei sezındı. TRANSLATION: She felt as if she were a ten-year-old who had thrown a roll at Suellen — like a guilty youngster.
A114: 111 | B114: Guilt — Felt guilt | C114: P2 | D114: felt guilt mixed with panic; fear of discovery | E114: "Mother of God!" thought Scarlett, in a panic of guilt. "'Concealing his real thoughts.' Can Melly have read his mind? Or my mind? Does she suspect that he and I—" | F114: Scarlett | G114: felt | H114: TERM: sovest' (совесть) — conscience; the inner moral faculty [ORD] PASSAGE: в испуге подумала Скарлетт, так как, совесть ее, разумеется, была нечиста. TRANS: v ispuge podumala Skarlett, tak kak, sovest' ee, razumeetsya, byla nechista. TRANSLATION: Scarlett thought in fright, since her conscience was, of course, not clean. | I114: TERM: AR-OJDAN (АР-ОЖДАН) — conscience (compound from Arabic wijdān): the inalienable inner tribunal [KED, SZK] PASSAGE: ... осылай ойлаған Скарлетт шошып кетті, өйткені оның ар-ұжданы, әрине, таза емес еді. TRANS: ... osylai oilağan Skarlett şoşyp kettı, öitkenı onyñ ar-ūjdany, ärine, taza emes edı. TRANSLATION: ... thinking thus, Scarlett took fright, for her ar-ujdan [conscience] was, of course, not clean.
A115: 112 | B115: Guilt — Felt guilt | C115: P2 | D115: felt guilt; inner moral accusation; Ellen (internalized superego); pain at deceiving her mother and abusing her trust, not at the actual misdeeds | E115: "I'm always your little girl," Scarlett would say and bury her head upon Ellen's breast, her guilt rising up to accuse her. She did not tell her mother that it was the dancing and the beaux which drew her back to Atlanta and not the service of the Confederacy. There were many things she kept from her mother these days. But, most of all, she kept secret the fact that Rhett Butler called frequently at Aunt Pittypat's house. | F115: Scarlett | G115: felt | H115: TERM: ugryzeniya sovesti. (угрызения совести.) = pangs of conscience PASSAGE: — Я всегда, всегда буду вашей маленькой дочуркой, — говорила Скарлетт и прятала лицо на груди Эллин, чувствуя внезапно вспыхнувшие угрызения совести. TRANS: — Ya vsegda, vsegda budu vashey malen'koy dochurkoy, — govorila Skarlett i pryatala litso na grudi Ellin, chuvstvuya vnezapno vspykhnuvshie ugryzeniya sovesti. TRANSLATION: "I will always, always be your little daughter," said Scarlett, hiding her face on Ellen's breast, feeling suddenly flaring pangs of conscience. | I115: TERM: QYSYLU (ҚЫСЫЛУ) — to feel embarrassed; to feel constrained; to be in difficulty [KED, SZK] PASSAGE: - Мен әрқашан сенің кішкентай қызың боламын, - деді Скарлетт өзінің ұжданы алдында қысылған жүзін Эллиннің кеудесіне жасырып. TRANS: Men ärqaşan senıñ kışkentai qyzyñ bolamyn, - dedı Skarlett özınıñ ūjdany aldynda qysylğan jüzın Elinnıñ keudesıne jasyryp. TRANSLATION: "I will always be your little girl," said Scarlett, hiding her face — embarrassed before her own conscience [ūjdan] — on Ellen's breast.
A116: 113 | B116: Guilt — Felt guilt (guilty conscience) | C116: P2 | D116: guilty conscience — guilt and conscience fused | E116: Scarlett's guilty conscience stirred as she tried to recall what Ashley might have written that would lead Melanie to make such a statement, but most of the letters she had read had gone out of her head as soon as she finished reading them. She believed Melanie had simply taken leave of her senses. | F116: Scarlett | G116: felt | H116: TERM: sovesti (совести) — conscience (gen./dat./prep.) [ORD] (lemma: совесть) PASSAGE: Скарлетт, испытывая легкий укол совести, старалась вспомнить, что же было такого в письмах Эшли, что заставило Мелани сделать подобное заявление, но содержание писем почти мгновенно улетучивалось у нее из головы, как только она кончала читать. TRANS: Skarlett, ispytyvaya legkiy ukol sovesti, staralas' vspomnit', chto zhe bylo takogo v pis'makh Eshli, chto zastavilo Melani sdelat' podobnoe zayavlenie, no soderzhanie pisem pochti mgnovenno uletuchivalos' u nee iz golovy, kak tol'ko ona konchala chitat'. TRANSLATION: Scarlett, feeling a slight prick of conscience, tried to recall what was in Ashley's letters that would make Melanie make such a statement, but the contents of the letters almost instantly evaporated from her head as soon as she finished reading. | I116: TERM: ūial- (ұял-) — be ashamed (verbal stem) [KED, SZK] (lemma: ұялу) PASSAGE: Скарлетт аздап ұялыс сезініп, Эшлидің хаттарындағы Меланиді осындай мәлімдеме жасауға итермелеген жолдарды еске түсіруге тырысты, ... TRANS: Skarlett azdap ūialys sezınıp, Eşlidıñ hattaryndağy Melanidı osyndai mälımdeme jasauğa itermelegen joldardy eske tüsıruge tyrysty, .... TRANSLATION: Feeling a slight twinge of shame, Scarlett tried to recall the lines in Ashley's letters that had pushed Melanie to make such a statement,...
A117: 114 | B117: Guilt — Guilt as tormentor | C117: P2 | D117: overwhelming felt guilt; inner moral accusation; no specific audience | E117: "Jealous—of me?" cried Scarlett, stricken with guilt. | F117: Scarlett | G117: felt | H117: TERM: sovesti (совести) — conscience (gen./dat./prep.) [ORD] (lemma: совесть) PASSAGE: — Завидуешь мне? — воскликнула Скарлетт, чувствуя легкий укол совести. TRANS: — Zaviduesh' mne? — voskliknula Skarlett, chuvstvuya legkiy ukol sovesti. TRANSLATION: "You're jealous of me?" exclaimed Scarlett, feeling a slight prick of conscience. | I117: TERM: AR-OJDAN (АР-ОЖДАН) — conscience (compound from Arabic wijdān): the inalienable inner tribunal [KED, SZK] PASSAGE: - Сен менен қызғанасың ба? - деп айқайлады Скарлетт ар-ұжданы ептеп мазалап. TRANS: - Sen menen qyzğanasyñ ba? - dep aiqailady Skarlett ar-ūjdany eptep mazalap. TRANSLATION: "Are you jealous of me?" — Scarlett cried out, her ar-ujdan [conscience] slightly troubling her.
A118: 115 | B118: Guilt — Felt guilt | C118: P4 | D118: felt guilt at intended conduct – preventative function; activated by Mammy | E118: Mammy looked at her piercingly, just as she had done when Scarlett was small and had tried unsuccessfully to palm off plausible excuses for misdeeds. She seemed to be reading her mind and Scarlett dropped her eyes unwillingly, the first feeling of guilt at her intended conduct creeping over her. | F118: Scarlett | G118: felt | H118: TERM: sovesti (совести) — conscience (gen./dat./prep.) [ORD] (lemma: совесть) PASSAGE: Казалось, Мамушка без труда читала в ее мыслях, и Скарлетт невольно опустила глаза, впервые почувствовав укол совести из-за своей затеи. TRANS: Kazalos', Mamushka bez truda chitala v ee myslyakh, i Skarlett nevol'no opustila glaza, vpervye pochuvstvovav ukol sovesti iz-za svoey zatei. TRANSLATION: It seemed that Mammy could read her thoughts without difficulty, and Scarlett involuntarily lowered her eyes, for the first time feeling a prick of conscience because of her scheme. | I118: TERM: ŪİAT (ҰЯТ) — shame; disgrace; sense of decency (also: that which is improper) [KED, SZK] PASSAGE: Скарлетт ұяттың салмағынан ауыр тартқандай болған кірпіктерін төмен түсіре қойды. TRANS: Skarlett ūiattyñ salmağynan auyr tartqandai bolğan kırpıkterın tömen tüsıre qoidy. TRANSLATION: Scarlett, as though her eyelids had grown heavy from the weight of shame, lowered them.
A119: 116 | B119: Guilt — Felt guilt | C119: P4 | D119: Guilt not of the lie, but at the thought of Ellen; accompanied by discomfort | E119: The first time Scarlett lied in this fashion she felt disconcerted and guilty—disconcerted because the lie sprang so easily and naturally to her lips, guilty because the thought flashed into her mind: What would Mother say? | F119: Scarlett | G119: felt | H119: TERM: stydno (стыдно) — it is shameful; (one) feels ashamed (impersonal predicate) [ORD] PASSAGE: Когда Скарлетт впервые решилась на такую ложь, ей потом стало стыдно и очень не по себе — TRANS: Kogda Skarlett vpervye reshilas' na takuyu lozh', ey potom stalo stydno i ochen' ne po sebe — TRANSLATION: When Scarlett had first decided on such a lie, she afterward felt ashamed and very ill at ease — | I119: TERM: QYSYLU (ҚЫСЫЛУ) — to feel embarrassed; to feel constrained; to be in difficulty [KED, SZK] PASSAGE: Осы өтірік айтуға ең алғаш бел байлағанында, әрине, қысылған еді. TRANS: Osy ötırık aituğa eñ alğaş bel bailağanynda, ärine, qysylğan edı. TRANSLATION: When she first resolved to tell this lie, of course, she had been embarrassed.
... A138: 135 | B138: Guilt — Guilt as deed | C138: P2 | D138: Scarlett interprets Melanie’s look as one of a guilty child – after taking money for the cause from Belle | E138: As she struggled with her bushy, obstinate locks, perspiration beading her forehead, she heard light running feet in the downstairs hall and knew that Melanie was home from the hospital. As she heard her fly up the stairs, two at a time, she paused, hairpin in mid-air, realizing that something must be wrong, for Melanie always moved as decorously as a dowager. She went to the door and threw it open, and Melanie ran in, her face flushed and frightened, looking like a guilty child. | F138: Melanie | G138: ascribed | H138: TERM: nashkodivshego (нашкодившего) — the naughty/mischievous one (active part. masc. gen.) [ORD] (lemma: нашкодить) PASSAGE: Скарлетт поспешила к двери, распахнула ее, и Мелани, перепуганная, с пылающими щеками, вбежала в комнату, глядя на Скарлетт молящими глазами нашкодившего ребенка. TRANS: Skarlett pospeshila k dveri, raspakhnula ee, i Melani, perepugannaya, s pylayushchimi shchekami, vbezhala v komnatu, glyadya na Skarlett molyashchimi glazami nashkodivshego rebenka. TRANSLATION: Scarlett hurried to the door, flung it open, and Melanie, frightened, with burning cheeks, ran into the room, looking at Scarlett with the imploring eyes of a mischief-doing child. | I138: TERM: būzyq (бұзық) — naughty; mischievous; (of child) ill-behaved [KED, SZK] PASSAGE:бұзық баланың бірдеңе бүлдіргендегі жалынышты көзімен Скарлеттке қарады. TRANS:būzyq balanyñ bırdeñe büldırgendegı jalynyşty közımen Skarlettke qarady. TRANSLATION: she looked at Scarlett with the imploring eyes of a naughty child who had broken something.
A139: CONSCIENCE DOMAIN
A140: 136 | B140: Conscience — Internal authority (advisor / opponent) | C140: P5 | D140: Ellen as internalized conscience; Melanie as moral mirror; desire for penance and repair | E140: She was driven by a conscience which, though long suppressed, could still rise up, an active Catholic conscience. "Confess your sins and do penance for them in sorrow and contrition," Ellen had told her a hundred times and, in this crisis, Ellen's religious training came back and gripped her. She would confess—yes, everything, every look and word, those few caresses—and then God would ease her pain and give her peace. And, for her penance, there would be the dreadful sight of Melanie's face changing from fond love and trust to incredulous horror and repulsion. Oh, that was too hard a penance, she thought in anguish, to have to live out her life remembering Melanie's face, knowing that Melanie knew all the pettiness, the meanness, the two-faced disloyalty and the hypocrisy that were in her. | F140: Scarlett | G140: felt | H140: TERM: sovest' (совесть) — conscience; the inner moral faculty [ORD] PASSAGE: К такому шагу Скарлетт побуждала совесть, которая хоть и долго молчала, но все еще способна была поднять голос, — совесть истинно верующей католички. TRANS: K takomu shagu Skarlett pobuzhdala sovest', kotoraya khot' i dolgo molchala, no vse eshche sposobna byla podnyat' golos, — sovest' istinno veruyushchey katolichki. TRANSLATION: Scarlett was urged to such a step by a conscience that, although it had been silent for a long time, was still capable of raising its voice — the conscience of a true believing Catholic. | I140: TERM: AR-ŪİAT(АР-ҰЯТ) — conscience-shame (compound): the active inner moral faculty [KED, SZK] PASSAGE: Баяғыдан бері бұғып жатқанымен, ақыры өзінің бар екенін, бас көтеретін уақыты келгенін білдерген ар-ұяты Скарлетті осы қадамға жетелейтін. Жүрегінің түкпірінде шынайы католиктік сенімі: TRANS: Baiağydan berı būğyp jatqanymen, aqyry özınıñ bar ekenın, bas köteretın uaqyty kelgenın bıldergen ar-ūiaty Skarlettı osy qadamğa jeteleitın. Jüregınıñ tükpırınde şynaiy katoliktık senımı: TRANSLATION: Although it had been hiding for a long time, her conscience — finally signaling its existence and that the time to raise its head had come — was leading Scarlett to this step. In the depths of her heart, her sincere Catholic faith:
A141: 137 | B141: Conscience — Internal authority (advisor / opponent) | C141: P1 | D141: Inner moral advisor and judge | E141: Gerald shoved in all his chips and laid on top of them his wallet. If the money it contained happened to belong to the firm of O'Hara Brothers, Gerald's conscience was not sufficiently troubled to confess it before Mass the following morning. He knew what he wanted, and when Gerald wanted something he gained it by taking the most direct route. | F141: Gerald O’Hara | G141: felt | H141: TERM: sovest' (совесть) — conscience; the inner moral faculty [ORD] PASSAGE: Тот факт, что содержимое бумажника являлось собственностью фирмы братьев О'Хара, не слишком обременял совесть Джералда, и каяться в своем грехе завтра перед утренней мессой он не собирался. TRANS: Tot fakt, chto soderzhimoe bumazhnika yavlyalos' sobstvennost'yu firmy brat'ev O'Khara, ne slishkom obremenyal sovest' Dzheralda, i kayat'sya v svoem grekhe zavtra pered utrenney messoy on ne sobiralsya. TRANSLATION: The fact that the contents of the wallet were the property of the firm of the O'Hara brothers did not weigh too heavily on Gerald's conscience, and he was not planning to repent of his sin tomorrow before morning Mass. | I141: TERM: AR-ŪİAT (АР-ҰЯТ) — conscience-shame (compound): the active inner moral faculty [KED, SZK] PASSAGE: ... Джералдтың ар-ұятын мазаламады TRANS: ... Jeraldtyñ ar-ūiatyn mazalamady TRANSLATION: ... did not trouble Gerald's conscience.
A142: 138 | B142: Conscience — Internal authority (advisor / opponent) | C142: P2 | D142: conscience as internal debating partner — argued away (early arc) | E142: "Well, it's true," she argued with her conscience. "Everybody carries on like they were holy and they aren't anything but men, and mighty unattractive looking ones at that." | F142: Scarlett | G142: felt | H142: TERM: sovest'yu (совестью) — conscience (instrumental) [ORD] (lemma: совесть) PASSAGE: «Но ведь это же в самом деле так, — вступила она в спор с собственной совестью. TRANS: «No ved' eto zhe v samom dele tak, — vstupila ona v spor s sobstvennoy sovest'yu. TRANSLATION: "But it really is so," she entered into argument with her own conscience. | I142: TERM: AR-OJDAN (АР-ОЖДАН) — conscience (compound from Arabic wijdān): the inalienable inner tribunal [KED, SZK] PASSAGE: "Бірақ бұл шынымен де солай", - деді ол өз ар-ұжданымен дауласып. TRANS: "Bıraq būl şynymen de solai", - dedı ol öz ar-ūjdanymen daulasyp. TRANSLATION: "But this really is so," — she said, arguing with her own conscience.
A143: 139 | B143: Conscience — Internal authority (advisor / opponent) | C143: P4 | D143: conscience battles desire for money — equal contest; loses | E143: As she drove off down the path to the Decatur road her conscience battled with her desire for money. She knew she had no business exposing human lives to the hard little man's mercies. If he should cause the death of one of them she would be as guilty as he was, for she had kept him in charge after learning of his brutalities. But, on the other hand—well, on the other hand, men had no business getting to be convicts. If they broke laws and got caught, then they deserved what they got. This partly salved her conscience but as she drove down the road the dull thin faces of the convicts would keep coming back into her mind. | F143: Scarlett | G143: felt | H143: TERM: sovest' (совесть) — conscience; the inner moral faculty [ORD] PASSAGE: Она ехала по тропе, выходившей на Декейтерскую дорогу, а в душе у нее совесть боролась с жаждой наживы. TRANS: Ona ekhala po trope, vykhodivshey na Dekeyterskuyu dorogu, a v dushe u nee sovest' borolas' s zhazhdoy nazhivy. TRANSLATION: She was riding along the path that led out to the Decatur road, and in her soul her conscience was struggling with greed. | I143: TERM: AR-ŪİAT(АР-ҰЯТ) — conscience-shame (compound): the active inner moral faculty [KED, SZK] PASSAGE: Ол Декейтер жолына шығатын соқпаққа түсіп алып, жүріп келеді, көкірегіндегі табысқа құмарлық мен ар-ұяты өзара алысуда. TRANS: Ol Dekeiter jolyna şyğatyn soqpaqqa tüsıp alyp, jürıp keledı, kökıregındegı tabysqa qūmarlyq men ar-ūiaty özara alysuda.. TRANSLATION: Heading down the path that comes out onto the Decatur road, she rides along; her thirst for profit and her conscience are wrestling with each other inside her.
A144: 140 | B144: Conscience — Internal authority (advisor / opponent) | C144: P4 | D144: Opponent, attacker, judge | E144: If only Melanie were with her, Melanie could calm her fears. But Melanie was at home, nursing Ashley. For a moment Scarlett thought of summoning Pittypat to stand between her and her conscience but she hesitated. Pitty would probably make matters worse, for she honestly mourned Frank. | F144: Scarlett | G144: felt | H144: TERM: sovesti (совести) — conscience (gen./dat./prep.) [ORD] (lemma: совесть) PASSAGE: На мгновение Скарлетт подумала было попросить Питтипэт подняться к ней — может, в ее присутствии умолкнет голос совести, — но не решилась. TRANS: Na mgnovenie Skarlett podumala bylo poprosit' Pittipet podnyat'sya k ney — mozhet, v ee prisutstvii umolknet golos sovesti, — no ne reshilas'. TRANSLATION: For a moment Scarlett thought to ask Pittypat to come up to her — perhaps in her presence the voice of conscience would fall silent — but she did not dare. | I144: TERM: ŪİAT (ҰЯТ) — shame; disgrace; sense of decency (also: that which is improper) [KED, SZK] PASSAGE: Бір сәтке Питтипэт тәтесін шақырғысы келіп те ойланды, ол мұның көңілін аулап, ойын бөлсе, ұятпен бетпе-бет жалғыз қалудан құтылар ма еді, дегенмен бата алмады. TRANS: Bır sätke Pittipet tätesın şaqyrğysy kelıp te oilandy, ol mūnyñ köñılın aulap, oiyn bölse, ūiatpen betpe-bet jalğyz qaludan qūtylar ma edı, degenmen bata almady. TRANSLATION: For a moment she even thought to call Aunt Pittypat — if she could distract her thoughts and entertain her, perhaps she could escape being left alone face-to-face with shame — but she did not dare.
A145: 141 | B145: Conscience — Internal authority (advisor / opponent) | C145: P4 | D145: Opponent, attacker, judge – about a particularly “indecent” deed | E145: "Oh, come! You are confessing and you might as well confess the truth as a decorous lie. Did your—er—conscience bother you much when you offered to—shall we say—part with that jewel which is dearer than life for three hundred dollars?" | F145: Scarlett | G145: spoken | H145: TERM: sovest' (совесть) — conscience; the inner moral faculty [ORD] PASSAGE: Ваша… м-м… совесть очень вас мучила, когда вы соглашались… скажем, так — расстаться с этим сокровищем, которое вам дороже жизни, за триста долларов? TRANS: Vasha… m-m… sovest' ochen' vas muchila, kogda vy soglashalis'… skazhem, tak — rasstat'sya s etim sokrovishchem, kotoroe vam dorozhe zhizni, za trista dollarov? TRANSLATION: Did your... mm... conscience torment you greatly when you agreed... shall we say — to part with this treasure that is dearer to you than life, for three hundred dollars? | I145: TERM: ŪİAT (ҰЯТ) — shame; disgrace; sense of decency (also: that which is improper) [KED, SZK] PASSAGE: Сіз үш жүз долларға бағалаған әшекейіңізбен қоштасарыңызда да ұятыңыз сізді қинады ма екен. TRANS:Sız üş jüz dollarğa bağalağan äşekeiıñızben qoştasaryñyzda da ūiatyñyz sızdı qinady ma eken. TRANSLATION: When you bid farewell to your jewel that you priced at three hundred dollars, did your shame trouble you?
A146: 142 | B146: Conscience — Internal authority (advisor / opponent) | C146: P5 | D146: Opponent, can kill | E146: "I can't tell her," she thought miserably. "Never, not even if my conscience kills me." She remembered irrelevantly Rhett's drunken remark: "She can't conceive of dishonor in anyone she loves...let that be your cross." | F146: Scarlett | G146: spoken | H146: TERM: sovest' (совесть) — conscience; the inner moral faculty [ORD] PASSAGE: Никогда не смогу, даже если совесть убьет меня». TRANS: Nikogda ne smogu, dazhe esli sovest' ub'et menya». TRANSLATION: Never, even if my conscience kills me. | I146: TERM: AR-ŪİAT (АР-ҰЯТ) — conscience-shame (compound): the active inner moral faculty [KED, SZK] PASSAGE: "Мұны айта алмайды екенмін, ар-ұятым тұншықтырып өлтірсе де айта алмаймын" деп тұнжырай ойлады Скарлетт. TRANS: "Mūny aita almaidy ekenmın, ar-ūiatym tūnşyqtyryp öltırse de aita almaimyn" dep tūnjyrai oilady Skarlett. TRANSLATION: "I cannot say it; even if my conscience should choke and kill me, I cannot say it," thought Scarlett gloomily.
A147: 143 | B147: Conscience — Internal authority (advisor / opponent) | C147: P2 | D147: Interlocutor, advisor – can make one doubt one’s course of action | E147: That morning Aunt Pitty had reached the regretful decision that she had better kill the patriarch before he died of old age and pining for his harem which had long since been eaten. For days he had drooped about the empty chicken run, too dispirited to crow. After Uncle Peter had wrung his neck, Aunt Pitty had been beset by conscience at the thought of enjoying him, en famille, when so many of her friends had not tasted chicken for weeks, so she suggested company for dinner. Melanie, who was now in her fifth month, had not been out in public or received guests for weeks, and she was appalled at the idea. But Aunt Pitty, for once, was firm. It would be selfish to eat the rooster alone, and if Melanie would only move her top hoop a little higher no one would notice anything and she was so flat in the bust anyway. | F147: Aunt Pitty | G147: felt | H147: TERM: somneniya (сомнения) — doubt; doubts [ORD] (lemma: сомнение) PASSAGE: Когда дядюшка Питер свернул ему шею, деликатную душу тетушки Питтипэт внезапно одолели сомнения: допустимо ли насладиться этой птицей в кругу семьи, в то время как многие из друзей неделями не могут отведать куриного мяса, и она решила пригласить гостей. TRANS: Kogda dyadyushka Piter svernul emu sheyu, delikatnuyu dushu tetushki Pittipet vnezapno odoleli somneniya: dopustimo li nasladit'sya etoy ptitsey v krugu sem'i, v to vremya kak mnogie iz druzey nedelyami ne mogut otvedat' kurinogo myasa, i ona reshila priglasit' gostey. TRANSLATION: When Uncle Peter wrung its neck, Aunt Pittypat's delicate soul was suddenly seized by doubts: was it permissible to enjoy this bird in the family circle while many of her friends could not have a taste of chicken meat for weeks, and she decided to invite guests. | I147: TERM: KÜMÄN (КҮМƏН) = doubt; uncertainty PASSAGE: Питтипэт тәтейдің нәзік жанында: "оның көптеген достары бірнеше апта бойы тауықтың дәмін тата алмай отырғанда, бұл құсты отбасымен бірге жеп рахаттануға бола ма, әлде қонақ шақыруға шешім қабылдауы дұрыс па?" деген күмән пайда болды. TRANS: Pittipet täteidıñ näzık janynda: "onyñ köptegen dostary bırneşe apta boiy tauyqtyñ dämın tata almai otyrğanda, būl qūsty otbasymen bırge jep rahattanuğa bola ma, älde qonaq şaqyruğa şeşım qabyldauy dūrys pa?" degen kümän paida boldy. TRANSLATION: In Aunt Pittypat's sensitive soul there arose the doubt: "While many of his friends have not been able to taste chicken for weeks, is it appropriate to enjoy eating this bird with the family — or would it be right to decide on inviting guests?"
A148: 144 | B148: Conscience — Internal authority (advisor / opponent) | C148: P4 | D148: Struggle with conscience | E148: "Of course," she said, wondering what the old fool had been talking about. Some struggle with his conscience. When a man got as old as Frank Kennedy he ought to have learned not to bother about things that didn't matter. But he always was so nervous and fussy and old maidish. | F148: Frank Kennedy | G148: felt | H148: TERM: sovesti (совести) — conscience (gen./dat./prep.) [ORD] (lemma: совесть) PASSAGE: Что-то насчет своей совести. TRANS: Chto-to naschet svoey sovesti. TRANSLATION: Something about his conscience. | I148: TERM: ŪİAT (ҰЯТ) — shame; disgrace; sense of decency (also: that which is improper) [KED, SZK] PASSAGE: Өз ұяты туралы ма, бірдеңе. TRANS: Öz ūiaty turaly ma, bırdeñe. TRANSLATION: Something about their own shame [conscience], or something like that.
A149: 145 | B149: Conscience — Absent reaction | C149: P4 | D149: ABSENT reaction of conscience due to personal loyalties | E149: The mottled wise old eyes saw deeply, saw clearly, with the directness of the savage and the child, undeterred by conscience when danger threatened her pet. Scarlett was her baby and what her baby wanted, even though it belonged to another, Mammy was willing to help her obtain. The rights of Suellen and Frank Kennedy did not even enter her mind, save to cause a grim inward chuckle. Scarlett was in trouble and doing the best she could, and Scarlett was Miss Ellen's child. | F149: Mammy | G149: felt | H149: TERM: soznanie (сознание) — consciousness; awareness (here: moral awareness) [ORD] PASSAGE: не затуманенные слишком развитым сознанием TRANS: ne zatumanennye slishkom razvitym soznaniem TRANSLATION: not clouded by an overdeveloped consciousness | I149: PASSAGE: Сүйікті қызының басына қиындық туған кезде, дақ түссе де мейірімді, дана көзі бәрін де қалт жібермей байқап, істің мән-жайына бойлай кірісті. Сәбидің жанарындай жәутеңдеген көзқарасы санасында не болып жатқанын жайып салып тұр. TRANS: Süiıktı qyzynyñ basyna qiyndyq tuğan kezde, daq tüsse de meiırımdı, dana közı bärın de qalt jıbermei baiqap, ıstıñ män-jaiyna boilai kırıstı. Säbidıñ janaryndai jäuteñdegen közqarasy sanasynda ne bolyp jatqanyn jaiyp salyp tūr. TRANSLATION: When difficulties came upon her beloved girl, [Mammy's] kind, wise eyes — even with stains — missed nothing and went deep into the heart of the matter. The flickering, baby-like glance laid bare what was happening in her mind.
A150: 146 | B150: Conscience — Dormant / waking creature | C150: P2 | D150: Being that can sleep and wake up | E150: Scarlett's guilty conscience stirred as she tried to recall what Ashley might have written that would lead Melanie to make such a statement, but most of the letters she had read had gone out of her head as soon as she finished reading them. She believed Melanie had simply taken leave of her senses. | F150: Scarlett | G150: felt | H150: TERM: sovesti (совести) — conscience (gen./dat./prep.) [ORD] (lemma: совесть) PASSAGE: Скарлетт, испытывая легкий укол совести, старалась вспомнить, что же было такого в письмах Эшли, что заставило Мелани сделать подобное заявление, но содержание писем почти мгновенно улетучивалось у нее из головы, как только она кончала читать. TRANS: Skarlett, ispytyvaya legkiy ukol sovesti, staralas' vspomnit', chto zhe bylo takogo v pis'makh Eshli, chto zastavilo Melani sdelat' podobnoe zayavlenie, no soderzhanie pisem pochti mgnovenno uletuchivalos' u nee iz golovy, kak tol'ko ona konchala chitat'. TRANSLATION: Scarlett, feeling a slight prick of conscience, tried to recall what was in Ashley's letters that would make Melanie make such a statement, but the contents of the letters almost instantly evaporated from her head as soon as she finished reading. | I150: TERM: ŪİALU (ҰЯЛУ) — to feel ashamed; to feel shy; to be embarrassed [KED, SZK] PASSAGE: Скарлетт аздап ұялыс сезініп, Эшлидің хаттарындағы Меланиді осындай мәлімдеме жасауға итермелеген жолдарды еске түсіруге тырысты, ... TRANS: Skarlett azdap ūialys sezınıp, Eşlidıñ hattaryndağy Melanidı osyndai mälımdeme jasauğa itermelegen joldardy eske tüsıruge tyrysty, ... TRANSLATION: Feeling a slight twinge of shame, Scarlett tried to recall the lines in Ashley's letters that had pushed Melanie to make such a statement,...
A151: 147 | B151: Conscience — General faculty | C151: P4 | D151: conscience as active inner faculty — inner moral judge | E151: No one intruded upon her, believing that she wished to be left alone with her grief, but to be left alone was the last thing Scarlett desired. Had it only been grief that companioned her, she could have borne it as she had borne other griefs. But, added to her stunned sense of loss at Frank's death, were fear and remorse and the torment of a suddenly awakened conscience. For the first time in her life she was regretting things she had done, regretting them with a sweeping superstitious fear that made her cast sidelong glances at the bed upon which she had lain with Frank. | F151: Scarlett | G151: felt | H151: TERM: sovesti (совести) — conscience (gen./dat./prep.) [ORD] (lemma: совесть) PASSAGE: Но помимо потрясения от потери мужа, она испытывала еще страх, и раскаяние, и муки внезапно проснувшейся совести. TRANS: No pomimo potryaseniya ot poteri muzha, ona ispytyvala eshche strakh, i raskayanie, i muki vnezapno prosnuvsheysya sovesti. TRANSLATION: But besides the shock of losing her husband, she also felt fear, and remorse, and the pangs of suddenly awakened conscience. | I151: TERM: ŪİAT (ҰЯТ) — shame; disgrace; sense of decency (also: that which is improper) [KED, SZK] PASSAGE: Бірақ күйеуінен айырылған қасіреті өз алдында, бойын билеген қорқыныш пен жанын жеген өкініш, бір бүйірден бас көтере қалған ұят қоса қысып барады. TRANS: Bıraq küieuınen aiyrylğan qasıretı öz aldynda, boiyn bilegen qorqynyş pen janyn jegen ökınış, bır büiırden bas kötere qalğan ūiat qosa qysyp barady. TRANSLATION: But the grief of losing her husband had its own place; the fear that filled her body, the regret that ate at her soul, and the shame that suddenly raised its head from one side, were all squeezing her along with it.
... A177: 173 | B177: Conscience — Absent reaction | C177: P4 | D177: conscience ABSENT reaction when reaction was expected | E177: "You misunderstand. I regret to say that my conscience has not troubled me at all about deserting you. But as for enlisting—when I think of joining the army in varnished boots and a white linen suit and armed with only a pair of dueling pistols— And those long cold miles in the snow after my boots wore out and I had no overcoat and nothing to eat...I cannot understand why I did not desert. It was all the purest insanity. But it's in one's blood. Southerners can never resist a losing cause. But never mind my reasons. It's enough that I'm forgiven." | F177: Rhett | G177: spoken | H177: TERM: sovest' (совесть) — conscience; the inner moral faculty [ORD] PASSAGE: К великому сожалению, я вынужден признать: совесть не мучила меня при мысли, что я вас бросил. TRANS: K velikomu sozhaleniyu, ya vynuzhden priznat': sovest' ne muchila menya pri mysli, chto ya vas brosil. TRANSLATION: To my great regret, I am forced to admit: my conscience did not torment me at the thought that I had abandoned you. | I177: TERM: AR (АР) — honour; conscience; inalienable inner moral principle [KED, SZK] PASSAGE: Өз арыңыз, ұятыңыз туралы ұмытыңыз, Скарлетт. TRANS: Öz aryñyz, ūiatyñyz turaly ūmytyñyz, Skarlett. TRANSLATION: Forget about your ar [conscience] and your shame, Scarlett.
A178: 174 | B178: Conscience — General faculty | C178: P4 | D178: Not specified, general moral faculty | E178: "To England and I may be gone for months. Forget your conscience, Scarlett. I have no intention of discussing your soul's welfare any further. Don't you want to hear my news?" | F178: Scarlett | G178: ascribed | H178: TERM: sovesti (совести) — conscience (gen./dat./prep.) [ORD] (lemma: совесть) PASSAGE: Забудьте о своей совести, Скарлетт. TRANS: Zabud'te o svoey sovesti, Skarlett. TRANSLATION: Forget about your conscience, Scarlett.
A179: HONOR DOMAIN
A180: 175 | B180: Honor — Moral code | C180: P4 | D180: honor as absolute inner principle — above life; not negotiable (Ashley) | E180: "Nothing," he said quietly, "nothing—except honor." | F180: Ashley | G180: spoken | H180: TERM: chesti (чести) — honour (gen./dat./prep.) [ORD] (lemma: честь) PASSAGE: Ничто, — ровным голосом повторил он, — ничто, кроме чести. TRANS: Nichto, — rovnym golosom povtoril on, — nichto, krome chesti. TRANSLATION: Nothing, — he repeated in an even voice, — nothing except honor. | I180: TERM: AR-ŪİAT (АР-ҰЯТ) — conscience-shame (compound): the active inner moral faculty [KED, SZK] PASSAGE: Ештеңе жоқ, - деп қайталады ол да, - ар-ұяттан басқа ештеңе жоқ. TRANS: Eşteñe joq, - dep qaitalady ol da, - ar-ūiattan basqa eşteñe joq. TRANSLATION: There is nothing, — he repeated, — nothing other than conscience/honor.
A181: 176 | B181: Honor — Moral code | C181: P4 | D181: honor as absolute inner principle — above life; not negotiable (Ashley) | E181: Scarlett writhed at his words. Of course, Ashley loved her for just these things. It was this knowledge that made life endurable, this knowledge that Ashley, bound by honor, loved her from afar for beautiful things deep buried in her that he alone could see. But they did not seem so beautiful when dragged to the light by Rhett, especially in that deceptively smooth voice that covered sarcasm. | F181: Ashley | G181: felt | H181: TERM: chesti (чести) — honour (gen./dat./prep.) [ORD] (lemma: честь) PASSAGE: Сознание того, что Эшли, связанный соображениями чести, любит ее на расстоянии за то прекрасное, что глубоко скрыто в ней и что один, только он видит, — это сознание как раз и позволяло ей жить. TRANS: Soznanie togo, chto Eshli, svyazannyy soobrazheniyami chesti, lyubit ee na rasstoyanii za to prekrasnoe, chto gluboko skryto v ney i chto odin, tol'ko on vidit, — eto soznanie kak raz i pozvolyalo ey zhit'. TRANSLATION: The awareness that Ashley, bound by considerations of honor, loves her from a distance for the beautiful that is deeply hidden in her, which only he sees — this awareness was precisely what allowed her to live. | I181: TERM: AR-OJDAN (АР-ОЖДАН) — conscience (compound from Arabic wijdān): the inalienable inner tribunal [KED, SZK] PASSAGE: Ар-ождан тазалығын бәрінен биік қойғандықтан да Эшли пәк сезімін ластамас үшін бойын аулақ сала ұстап, мұның тереңге жасырылған асып қасиеттеріне бола жақсы көреді. TRANS: Ar-ojdan tazalyğyn bärınen biık qoiğandyqtan da Eşli päk sezımın lastamas üşın boiyn aulaq sala ūstap, mūnyñ tereñge jasyrylğan asyp qasietterıne bola jaqsy köredı. TRANSLATION: Because he placed the purity of his conscience above all, Ashley keeps himself at a distance so as not to soil his pure feeling; he loves her for the noble qualities hidden deep within her.
A182: 177 | B182: Honor — Moral code | C182: P5 | D182: honor as absolute inner principle — above life; not negotiable (Ashley) | E182: Knowing how Ashley valued honor above his life, Scarlett knew he must be writhing. He, like Scarlett, was forced to shelter behind Melanie's skirts. While Scarlett realized the necessity for this and knew that the blame for his false position lay mostly at her own door, still—still— Womanlike she would have respected Ashley more, had he shot Archie and admitted everything to Melanie and the world. She knew she was being unfair but she was too miserable to care for such fine points. Some of Rhett's taunting words of contempt came back to her and she wondered if indeed Ashley had played the manly part in this mess. And, for the first time, some of the bright glow which had enveloped him since the first day she fell in love with him began to fade imperceptibly. | F182: Ashley | G182: felt | H182: TERM: chest' (честь) — honour; honor [ORD] PASSAGE: Зная, что Эшли ставит честь выше жизни, Скарлетт понимала, что он, должно быть, кипит от ярости. TRANS: Znaya, chto Eshli stavit chest' vyshe zhizni, Skarlett ponimala, chto on, dolzhno byt', kipit ot yarosti. TRANSLATION: Knowing that Ashley placed honor above life, Scarlett understood that he must be seething with rage. | I182: TERM: AR-NAMYS (АР-НАМЫС) — honour; observable behavioural code (compound) [KED, SZK] PASSAGE: Эшлидің ар-намысын өмірінен де жоғары қоятынын білген Скарлетт оның ыза мен өкініштен жарылардай боп жүргенін топшылайды. TRANS: Eşlidıñ ar-namysyn ömırınen de joğary qoiatynyn bılgen Skarlett onyñ yza men ökınışten jarylardai bop jürgenın topşylaidy. TRANSLATION: Knowing that Ashley places his honor-pride above his very life, Scarlett guesses that he is on the verge of bursting from anger and regret.
A183: 178 | B183: Honor — Nobility of character | C183: P5 | D183: dishonor / absent honor — violation or accusation; outside the code | E183: "Yes, you will listen. And I'll tell you this to ease your worry. Miss Melly is a fool but not the kind you think. It was obvious that someone had told her but she didn't believe it. Even if she saw, she wouldn't believe. There's too much honor in her to conceive of dishonor in anyone she loves. I don't know what lie Ashley Wilkes told her—but any clumsy one would do, for she loves Ashley and she loves you. I'm sure I can't see why she loves you but she does. Let that be one of your crosses." | F183: Melanie | G183: ascribed | H183: TERM: blagorodstvo (благородство) — nobility; nobleness of character [ORD] PASSAGE: otsutstvie blagorodstva (отсутствие благородства) = nobleness, absence of nobleness Слишком много в ней благородства, чтобы она могла поверить в отсутствие благородства у тех, кого любит. TRANS: otsutstvie blagorodstva (otsutstvie blagorodstva) = nobleness, absence of nobleness Slishkom mnogo v ney blagorodstva, chtoby ona mogla poverit' v otsutstvie blagorodstva u tekh, kogo lyubit. TRANSLATION: absence of nobility = There is too much nobility in her for her to be able to believe in the absence of nobility in those whom she loves. | I183: TERM: Janınıñ asıldığı, päktigi (Жанының асылдығы, пәктігі) = the nobility and purity of her soul PASSAGE: Жанының асылдығы, пәктігі сондай өзі аса қатты жақсы көретін адамының сатқын болуы мүмкін екеніне сене алмайды. TRANS: Janynyñ asyldyğy, päktıgı sondai özı asa qatty jaqsy köretın adamynyñ satqyn boluy mümkın ekenıne sene almaidy. TRANSLATION: The nobility, the purity of her soul is such that she cannot believe that the person she loves so very much could be a traitor.
A184: 179 | B184: Honor — Moral code | C184: P4 | D184: Scarlett sacrificed herself and did shameful things to prevent Ashley from doing dishonorable things | E184: "Yes, it's done now," he said with slow bitterness. "You wouldn't have let me do anything dishonorable but you would sell yourself to a man you didn't love—and bear his child, so that my family and I wouldn't starve. It was kind of you to shelter my helplessness." | F184: Ashley | G184: spoken | H184: TERM: beschestnyy (бесчестный) — dishonourable; ignoble [ORD] PASSAGE: Вы бы не допустили, чтобы я совершил бесчестный поступок, а сами продались человеку, которого не любили, и теперь носите под сердцем его ребенка, и все ради того, чтобы я и моя семья не умерли с голоду. TRANS: Vy by ne dopustili, chtoby ya sovershil beschestnyy postupok, a sami prodalis' cheloveku, kotorogo ne lyubili, i teper' nosite pod serdtsem ego rebenka, i vse radi togo, chtoby ya i moya sem'ya ne umerli s golodu. TRANSLATION: You would never have allowed me to commit a dishonorable deed, and yet you sold yourself to a man you did not love, and now bear his child beneath your heart, all so that I and my family would not die of starvation. | I184: TERM: ARSYZDYQ (АРСЫЗДЫҚ) - shamelessness PASSAGE: Мені арсыздыққа қайтсеңіз де жібермес едіңіз, бірақ өзіңізді еш сүймейтін адамға сатып жібердіңіз де, жүрегіңіздің астында соның баласын сақтап жүрсіз. TRANS: Menı arsyzdyqqa qaitseñız de jıbermes edıñız, bıraq özıñızdı eş süimeitın adamğa satyp jıberdıñız de, jüregıñızdıñ astynda sonyñ balasyn saqtap jürsız. TRANSLATION: You, no matter what, would not have let me act shamelessly, but you yourself sold yourself off to a man you did not love at all, and now you carry his child beneath your heart.
A185: 180 | B185: Honor — Moral code | C185: P2 | D185: Non-scrupulous | E185: When Scarlett first began secretly reading these letters, she had been so stricken of conscience and so fearful of discovery she could hardly open the envelopes for trembling. Now, her never- too-scrupulous sense of honor was dulled by repetition of the offense and even fear of discovery had subsided. Occasionally, she thought with a sinking heart, "What would Mother say if she knew?" She knew Ellen would rather see her dead than know her guilty of such dishonor. This had worried Scarlett at first, for she still wanted to be like her mother in every respect. But the temptation to read the letters was too great and she put the thought of Ellen out of her mind. She had become adept at putting unpleasant thoughts out of her mind these days. She had learned to say, "I won't think of this or that bothersome thought now. I'll think about it tomorrow." Generally when tomorrow came, the thought either did not occur at all or it was so attenuated by the delay it was not very troublesome. So the matter of Ashley's letters did not lie very heavily on her conscience. | F185: Scarlett | G185: felt | H185: TERM: poryadochnost' (порядочность) — decency; respectability; integrity [ORD] PASSAGE: По мало-помалу от частых повторений этой проделки ее не слишком остро развитое чувство порядочности и вовсе притупилось, да и страх сам собой исчез. TRANS: Po malo-pomalu ot chastykh povtoreniy etoy prodelki ee ne slishkom ostro razvitoe chuvstvo poryadochnosti i vovse pritupilos', da i strakh sam soboy ischez. TRANSLATION: But little by little, with frequent repetitions of this trick, her not very sharply developed sense of decency was completely dulled, and the fear itself disappeared. | I185: TERM:AR-ŪİAT(АР-ҰЯТ) — conscience-shame (compound): the active inner moral faculty [KED, SZK] PASSAGE: оның ар-ұят, әдептілік сезімі мүлдем өшіп, қорқынышы өзіненөзі жоғалып кетті TRANS: onyñ ar-ūiat, ädeptılık sezımı müldem öşıp, qorqynyşy özınenözı joğalyp kettı TRANSLATION: her sense of conscience-shame and propriety was extinguished entirely, and her fear too vanished of itself.
A186: 181 | B186: Honor — Moral code | C186: P3 | D186: Code of behavior | E186: Nothing her mother had taught her was of any value whatsoever now and Scarlett's heart was sore and puzzled. It did not occur to her that Ellen could not have foreseen the collapse of the civilization in which she raised her daughters, could not have anticipated the disappearings of the places in society for which she trained them so well. It did not occur to her that Ellen had looked down a vista of placid future years, all like the uneventful years of her own life, when she had taught her to be gentle and gracious, honorable and kind, modest and truthful. Life treated women well when they had learned those lessons, said Ellen. | F186: Scarlett | G186: felt | H186: TERM: , chestnoy, pravdivoy (, честной, правдивой) = honest PASSAGE: уча ее быть доброй, мягкой, уступчивой, честной, правдивой и скромной, TRANS: ucha ee byt' dobroy, myagkoy, ustupchivoy, chestnoy, pravdivoy i skromnoy, TRANSLATION: teaching her to be kind, gentle, yielding, honest, truthful, and modest, | I186: TERM: şynşyl, adal, adal (шыншыл, адал) = honest, loyal PASSAGE: Скарлетт Эллиннің мұны мейірімді, жұмсақ, мойынсұнғыш, шыншыл, адал және қарапайым болуға үйрете отырып, өзінің өлшенген өмірі сияқты алдағы өмірден бейбіт, өзгеріссіз жылдар тізбегін ғана көргенін түсінбеді. TRANS: Skarlett Elinnıñ mūny meiırımdı, jūmsaq, moiynsūnğyş, şynşyl, adal jäne qarapaiym boluğa üirete otyryp, özınıñ ölşengen ömırı siaqty aldağy ömırden beibıt, özgerıssız jyldar tızbegın ğana körgenın tüsınbedı. TRANSLATION: Scarlett, while Ellen was teaching her to be kind, gentle, submissive, truthful, honest, and modest, did not understand that, like Ellen's measured life, [Ellen] was seeing only a row of peaceful and unchanging years stretching ahead.
A187: 182 | B187: Honor — Moral code | C187: P4 | D187: Both social and moral honor | E187: There was no doubt what Ellen would say to a daughter who told lies and engaged in sharp practices. She would be stunned and incredulous and would speak gentle words that stung despite their gentleness, would talk of honor and honesty and truth and duty to one's neighbor. Momentarily, Scarlett cringed as she pictured the look on her mother's face. | F187: Ellen | G187: felt | H187: TERM: chesti (чести) — honour (gen./dat./prep.) [ORD] (lemma: честь) PASSAGE: Она была бы потрясена, она бы ушам своим не поверила и так и сказала бы Скарлетт — мягко, но слова ее жгли бы каленым железом, — сказала бы о чести, и о честности, и о правде, и о долге перед ближними. TRANS: Ona byla by potryasena, ona by usham svoim ne poverila i tak i skazala by Skarlett — myagko, no slova ee zhgli by kalenym zhelezom, — skazala by o chesti, i o chestnosti, i o pravde, i o dolge pered blizhnimi. TRANSLATION: She would be shocked, she would not believe her ears and would say so to Scarlett — gently, but her words would burn like a red-hot iron — would speak of honor, and of honesty, and of truth, and of duty toward one's neighbors. | I187: TERM: AR-OJDAN (АР-ОЖДАН) — conscience (compound from Arabic wijdān): the inalienable inner tribunal [KED, SZK] PASSAGE: Алдымен өз құлағына өзі сенбей, көзі шарасынан шыға таңданар еді де, соншалық бәсең, бірақ намысыңа тигенде темірмен етіңді тіліп түскендей үнмен "Скарлетт" дер еді де, ар-ождан туралы, адалдық, шындық, туыс-бауыр алдындағы міндеті туралы айтар еді. TRANS: Aldymen öz qūlağyna özı senbei, közı şarasynan şyğa tañdanar edı de, sonşalyq bäseñ, bıraq namysyña tigende temırmen etıñdı tılıp tüskendei ünmen "Skarlett" der edı de, ar-ojdan turaly, adaldyq, şyndyq, tuys-bauyr aldyndağy mındetı turaly aitar edı. TRANSLATION: At first she would hardly believe her own ears and would stare in astonishment with her eyes wide, then say “Scarlett” in a voice so soft yet so cutting it was as if it sliced through your flesh with iron, and then she would speak of conscience, loyalty, truth, and one’s duty to family.
A188: 183 | B188: Honor — Moral code | C188: P4 | D188: Morality, decency, honest behavior | E188: "I shouldn't have expected either truth or honor or fair dealing from you, knowing you as I do. But foolishly, I trusted you." | F188: Scarlett | G188: ascribed | H188: TERM: chestnyy (честный) — honest; honourable [ORD] PASSAGE: Зная вас, мне, конечно, не следовало ожидать, что вы будете правдивы, порядочны и честны со мной. TRANS: Znaya vas, mne, konechno, ne sledovalo ozhidat', chto vy budete pravdivy, poryadochny i chestny so mnoy. TRANSLATION: Knowing you, of course, I should not have expected you to be truthful, decent, and honest with me. | I188: TERM: ADAL (АДАЛ) — honest; faithful; pure; lawful (Arabic ḥalāl) [KED, SZK] PASSAGE: Сізді бұрыннан танып, біле тұра, менімен барынша адал, бүкпесіз ашық болады деп илануымның өзі қателік екенін білемін. TRANS: Sızdı būrynnan tanyp, bıle tūra, menımen barynşa adal, bükpesız aşyq bolady dep ilanuymnyñ özı qatelık ekenın bılemın. TRANSLATION: Knowing you of old, I myself know it was a mistake to believe you would be utterly honest with me, open without concealment.
A189: 184 | B189: Honor — Moral code | C189: P4 | D189: moral honor | E189: "Pride and honor and truth and virtue and kindliness," he enumerated silkily. "You are right, Scarlett. They aren't important when a boat is sinking. But look around you at your friends. Either they are bringing their boats ashore safely with cargoes intact or they are content to go down with all flags flying." | F189: Scarlett | G189: ascribed | H189: TERM: chest' (честь) — honour; honor [ORD] PASSAGE: Гордость, и честь, и правдивость, и целомудрие, и милосердие, — хмуро перечислил он. TRANS: Gordost', i chest', i pravdivost', i tselomudrie, i miloserdie, — khmuro perechislil on. TRANSLATION: Pride, and honor, and truthfulness, and chastity, and mercy, — he listed gloomily. | I189: TERM: AR (АР) — honour; conscience; inalienable inner moral principle [KED, SZK] PASSAGE: Ар, адалдық, шыншылдық, тәкаппарлық, мақсатшылдық, мейірімділік TRANS: Ar, adaldyq, şynşyldyq, täkapparlyq, maqsatşyldyq, meiırımdılık TRANSLATION: Conscience, honesty, truthfulness, dignity, purpose, mercy
A190: 185 | B190: Honor — Moral code | C190: P4 | D190: moral honor | E190: "You can afford to be—but you won't. It's hard to salvage jettisoned cargo and, if it is retrieved, it's usually irreparably damaged. And I fear that when you can afford to fish up the honor and virtue and kindness you've thrown overboard, you'll find they have suffered a sea change and not, I fear, into something rich and strange..." | F190: Scarlett | G190: ascribed | H190: TERM: chest' (честь) — honour; honor [ORD] PASSAGE: И боюсь, что когда вы сочтете возможным втянуть обратно в лодку честь, целомудрие и милосердие, которые вышвырнули за борт, вы обнаружите, что они претерпели в воде существенные изменения, причем отнюдь не к лучшему… TRANS: I boyus', chto kogda vy sochtete vozmozhnym vtyanut' obratno v lodku chest', tselomudrie i miloserdie, kotorye vyshvyrnuli za bort, vy obnaruzhite, chto oni preterpeli v vode sushchestvennye izmeneniya, prichem otnyud' ne k luchshemu… TRANSLATION: And I fear that when you find it possible to pull back into the boat the honor, chastity, and mercy that you tossed overboard, you will discover that they have undergone substantial changes in the water, and not at all for the better... | I190: TERM: AR-ŪİAT (АР-ҰЯТ) — conscience-shame (compound): the active inner moral faculty [KED, SZK] PASSAGE: Сіз ар-ұятыңызды, мейірімділік пен адалдығыңызды қайтадан қажетсініп қайыққа тартып алған кезде де, олардың бұрынғы мәнін жойып, суда қалған кездерінде мүлдем танымастай өзгергенін байқайсыз, және жақсы жағына қарай өзгермес... TRANS: Sız ar-ūiatyñyzdy, meiırımdılık pen adaldyğyñyzdy qaitadan qajetsınıp qaiyqqa tartyp alğan kezde de, olardyñ būrynğy mänın joiyp, suda qalğan kezderınde müldem tanymastai özgergenın baiqaisyz, jäne jaqsy jağyna qarai özgermes... TRANSLATION: When you again come to need your conscience, your mercy, and your honesty and pull them back into the boat, you will discover that they have lost their original substance and changed beyond recognition while in the water — and not for the better...
A191: 186 | B191: Honor — Moral code | C191: P4 | D191: Moral code | E191: "Ashley Wilkes has never taken a cent from me! I couldn't make him take a cent if he were starving! You don't understand him, how honorable, how proud he is! Of course, you can't understand him, being what you are—" | F191: Ashley | G191: ascribed | H191: TERM: blagorodnyy (благородный) — noble; of noble character [ORD] PASSAGE: Вам в жизни не понять, какой он благородный, какой гордый! TRANS: Vam v zhizni ne ponyat', kakoy on blagorodnyy, kakoy gordyy! TRANSLATION: You will never in your life understand how noble he is, how proud! | I191: TERM: ASYL (АСЫЛ) — noble; precious; intrinsically valuable [KED, SZK] PASSAGE: Оның қандай жаны асыл, қандай ар-ұятты биік қоятын адам екенін мәңгі түсінбей өтесіз! TRANS: Onyñ qandai jany asyl, qandai ar-ūiatty biık qoiatyn adam ekenın mäñgı tüsınbei ötesız! TRANSLATION: You will never understand all your life what kind of soul he is — how nobly elevated, how high he holds his conscience!
... A236: 231 | B236: Honor — Undifferentiated honor | C236: P4 | D236: In accordance with honor | E236: "I bare my soul and you are suspicious! No, Scarlett, this is a bona fide honorable declaration. I admit that it's not in the best of taste, coming at this time, but I have a very good excuse for my lack of breeding. I'm going away tomorrow for a long time and I fear that if I wait till I return you'll have married some one else with a little money. So I thought, why not me and my money? Really, Scarlett, I can't go all my life, waiting to catch you between husbands." | F236: Rhett | G236: spoken | H236: TERM: chestnoe predlozhenie. (честное предложение.) = honest declaration PASSAGE: Нет, Скарлетт, это bonа fide честное предложение. TRANS: Net, Skarlett, eto bona fide chestnoe predlozhenie. TRANSLATION: No, Scarlett, this is bona fide an honest proposal. | I236: TERM: ADAL ŪİAT(АДАЛ ҰЯТ) — honest shame/conscience; pure inner uprightness [KED, SZK] (lemma: ұят) PASSAGE: Жоқ, Скарлетт, адал ұятымның шын ұсынысы. TRANS: Joq, Skarlett, adal ūiatymnyñ şyn ūsynysy. TRANSLATION: No, Scarlett, it is the sincere proposal of my honest conscience.

Sheet Summary
A1: Gone with the Wind — moral-emotion corpus: counts
A2: Dual-character tokens (#23, #128, #229) are counted under each of their two characters; token totals count each token once via the Token column.
A4: Tokens by English word (domain)
A5: English word | B5: Tokens
A6: Shame | B6: =SUMIFS('Data (parsed)'!$I$2:$I$235,'Data (parsed)'!$B$2:$B$235,A6) -> 104
A7: Guilt | B7: =SUMIFS('Data (parsed)'!$I$2:$I$235,'Data (parsed)'!$B$2:$B$235,A7) -> 31
A8: Conscience | B8: =SUMIFS('Data (parsed)'!$I$2:$I$235,'Data (parsed)'!$B$2:$B$235,A8) -> 39
A9: Honor | B9: =SUMIFS('Data (parsed)'!$I$2:$I$235,'Data (parsed)'!$B$2:$B$235,A9) -> 57
A10: Total | B10: =SUM(B6:B9) -> 231
A12: Tokens by English word × Part of novel (the arc)
B13: P1 | C13: P2 | D13: P3 | E13: P4 | F13: P5 | G13: Total
A14: Shame | B14: =SUMIFS('Data (parsed)'!$I$2:$I$235,'Data (parsed)'!$B$2:$B$235,$A14,'Data (parsed)'!$D$2:$D$235,B$13) -> 6 | C14: =SUMIFS('Data (parsed)'!$I$2:$I$235,'Data (parsed)'!$B$2:$B$235,$A14,'Data (parsed)'!$D$2:$D$235,C$13) -> 14 | D14: =SUMIFS('Data (parsed)'!$I$2:$I$235,'Data (parsed)'!$B$2:$B$235,$A14,'Data (parsed)'!$D$2:$D$235,D$13) -> 17 | E14: =SUMIFS('Data (parsed)'!$I$2:$I$235,'Data (parsed)'!$B$2:$B$235,$A14,'Data (parsed)'!$D$2:$D$235,E$13) -> 37 | F14: =SUMIFS('Data (parsed)'!$I$2:$I$235,'Data (parsed)'!$B$2:$B$235,$A14,'Data (parsed)'!$D$2:$D$235,F$13) -> 30 | G14: =SUM(B14:F14) -> 104
A15: Guilt | B15: =SUMIFS('Data (parsed)'!$I$2:$I$235,'Data (parsed)'!$B$2:$B$235,$A15,'Data (parsed)'!$D$2:$D$235,B$13) -> 4 | C15: =SUMIFS('Data (parsed)'!$I$2:$I$235,'Data (parsed)'!$B$2:$B$235,$A15,'Data (parsed)'!$D$2:$D$235,C$13) -> 7 | D15: =SUMIFS('Data (parsed)'!$I$2:$I$235,'Data (parsed)'!$B$2:$B$235,$A15,'Data (parsed)'!$D$2:$D$235,D$13) -> 2 | E15: =SUMIFS('Data (parsed)'!$I$2:$I$235,'Data (parsed)'!$B$2:$B$235,$A15,'Data (parsed)'!$D$2:$D$235,E$13) -> 5 | F15: =SUMIFS('Data (parsed)'!$I$2:$I$235,'Data (parsed)'!$B$2:$B$235,$A15,'Data (parsed)'!$D$2:$D$235,F$13) -> 13 | G15: =SUM(B15:F15) -> 31
A16: Conscience | B16: =SUMIFS('Data (parsed)'!$I$2:$I$235,'Data (parsed)'!$B$2:$B$235,$A16,'Data (parsed)'!$D$2:$D$235,B$13) -> 3 | C16: =SUMIFS('Data (parsed)'!$I$2:$I$235,'Data (parsed)'!$B$2:$B$235,$A16,'Data (parsed)'!$D$2:$D$235,C$13) -> 6 | D16: =SUMIFS('Data (parsed)'!$I$2:$I$235,'Data (parsed)'!$B$2:$B$235,$A16,'Data (parsed)'!$D$2:$D$235,D$13) -> 5 | E16: =SUMIFS('Data (parsed)'!$I$2:$I$235,'Data (parsed)'!$B$2:$B$235,$A16,'Data (parsed)'!$D$2:$D$235,E$13) -> 17 | F16: =SUMIFS('Data (parsed)'!$I$2:$I$235,'Data (parsed)'!$B$2:$B$235,$A16,'Data (parsed)'!$D$2:$D$235,F$13) -> 8 | G16: =SUM(B16:F16) -> 39
A17: Honor | B17: =SUMIFS('Data (parsed)'!$I$2:$I$235,'Data (parsed)'!$B$2:$B$235,$A17,'Data (parsed)'!$D$2:$D$235,B$13) -> 6 | C17: =SUMIFS('Data (parsed)'!$I$2:$I$235,'Data (parsed)'!$B$2:$B$235,$A17,'Data (parsed)'!$D$2:$D$235,C$13) -> 5 | D17: =SUMIFS('Data (parsed)'!$I$2:$I$235,'Data (parsed)'!$B$2:$B$235,$A17,'Data (parsed)'!$D$2:$D$235,D$13) -> 2 | E17: =SUMIFS('Data (parsed)'!$I$2:$I$235,'Data (parsed)'!$B$2:$B$235,$A17,'Data (parsed)'!$D$2:$D$235,E$13) -> 31 | F17: =SUMIFS('Data (parsed)'!$I$2:$I$235,'Data (parsed)'!$B$2:$B$235,$A17,'Data (parsed)'!$D$2:$D$235,F$13) -> 13 | G17: =SUM(B17:F17) -> 57
A18: Total | B18: =SUM(B14:B17) -> 19 | C18: =SUM(C14:C17) -> 32 | D18: =SUM(D14:D17) -> 26 | E18: =SUM(E14:E17) -> 90 | F18: =SUM(F14:F17) -> 64 | G18: =SUM(G14:G17) -> 231
A20: Tokens by character × English word (dual tokens counted under each character)
A21: Character | B21: Shame | C21: Guilt | D21: Conscience | E21: Honor | F21: Total
A22: Scarlett | B22: =COUNTIFS('Data (parsed)'!$E$2:$E$235,$A22,'Data (parsed)'!$B$2:$B$235,B$21) -> 48 | C22: =COUNTIFS('Data (parsed)'!$E$2:$E$235,$A22,'Data (parsed)'!$B$2:$B$235,C$21) -> 24 | D22: =COUNTIFS('Data (parsed)'!$E$2:$E$235,$A22,'Data (parsed)'!$B$2:$B$235,D$21) -> 31 | E22: =COUNTIFS('Data (parsed)'!$E$2:$E$235,$A22,'Data (parsed)'!$B$2:$B$235,E$21) -> 9 | F22: =SUM(B22:E22) -> 112
A23: Ashley | B23: =COUNTIFS('Data (parsed)'!$E$2:$E$235,$A23,'Data (parsed)'!$B$2:$B$235,B$21) -> 7 | C23: =COUNTIFS('Data (parsed)'!$E$2:$E$235,$A23,'Data (parsed)'!$B$2:$B$235,C$21) -> 0 | D23: =COUNTIFS('Data (parsed)'!$E$2:$E$235,$A23,'Data (parsed)'!$B$2:$B$235,D$21) -> 0 | E23: =COUNTIFS('Data (parsed)'!$E$2:$E$235,$A23,'Data (parsed)'!$B$2:$B$235,E$21) -> 28 | F23: =SUM(B23:E23) -> 35
A24: Rhett | B24: =COUNTIFS('Data (parsed)'!$E$2:$E$235,$A24,'Data (parsed)'!$B$2:$B$235,B$21) -> 20 | C24: =COUNTIFS('Data (parsed)'!$E$2:$E$235,$A24,'Data (parsed)'!$B$2:$B$235,C$21) -> 0 | D24: =COUNTIFS('Data (parsed)'!$E$2:$E$235,$A24,'Data (parsed)'!$B$2:$B$235,D$21) -> 2 | E24: =COUNTIFS('Data (parsed)'!$E$2:$E$235,$A24,'Data (parsed)'!$B$2:$B$235,E$21) -> 8 | F24: =SUM(B24:E24) -> 30
A25: Melanie | B25: =COUNTIFS('Data (parsed)'!$E$2:$E$235,$A25,'Data (parsed)'!$B$2:$B$235,B$21) -> 8 | C25: =COUNTIFS('Data (parsed)'!$E$2:$E$235,$A25,'Data (parsed)'!$B$2:$B$235,C$21) -> 3 | D25: =COUNTIFS('Data (parsed)'!$E$2:$E$235,$A25,'Data (parsed)'!$B$2:$B$235,D$21) -> 1 | E25: =COUNTIFS('Data (parsed)'!$E$2:$E$235,$A25,'Data (parsed)'!$B$2:$B$235,E$21) -> 1 | F25: =SUM(B25:E25) -> 13
A26: Community / South | B26: =COUNTIFS('Data (parsed)'!$E$2:$E$235,$A26,'Data (parsed)'!$B$2:$B$235,B$21) -> 4 | C26: =COUNTIFS('Data (parsed)'!$E$2:$E$235,$A26,'Data (parsed)'!$B$2:$B$235,C$21) -> 0 | D26: =COUNTIFS('Data (parsed)'!$E$2:$E$235,$A26,'Data (parsed)'!$B$2:$B$235,D$21) -> 0 | E26: =COUNTIFS('Data (parsed)'!$E$2:$E$235,$A26,'Data (parsed)'!$B$2:$B$235,E$21) -> 9 | F26: =SUM(B26:E26) -> 13
A27: Frank Kennedy | B27: =COUNTIFS('Data (parsed)'!$E$2:$E$235,$A27,'Data (parsed)'!$B$2:$B$235,B$21) -> 3 | C27: =COUNTIFS('Data (parsed)'!$E$2:$E$235,$A27,'Data (parsed)'!$B$2:$B$235,C$21) -> 0 | D27: =COUNTIFS('Data (parsed)'!$E$2:$E$235,$A27,'Data (parsed)'!$B$2:$B$235,D$21) -> 2 | E27: =COUNTIFS('Data (parsed)'!$E$2:$E$235,$A27,'Data (parsed)'!$B$2:$B$235,E$21) -> 0 | F27: =SUM(B27:E27) -> 5
A28: Rene Picard | B28: =COUNTIFS('Data (parsed)'!$E$2:$E$235,$A28,'Data (parsed)'!$B$2:$B$235,B$21) -> 3 | C28: =COUNTIFS('Data (parsed)'!$E$2:$E$235,$A28,'Data (parsed)'!$B$2:$B$235,C$21) -> 0 | D28: =COUNTIFS('Data (parsed)'!$E$2:$E$235,$A28,'Data (parsed)'!$B$2:$B$235,D$21) -> 0 | E28: =COUNTIFS('Data (parsed)'!$E$2:$E$235,$A28,'Data (parsed)'!$B$2:$B$235,E$21) -> 0 | F28: =SUM(B28:E28) -> 3
A29: Gerald O’Hara | B29: =COUNTIFS('Data (parsed)'!$E$2:$E$235,$A29,'Data (parsed)'!$B$2:$B$235,B$21) -> 0 | C29: =COUNTIFS('Data (parsed)'!$E$2:$E$235,$A29,'Data (parsed)'!$B$2:$B$235,C$21) -> 2 | D29: =COUNTIFS('Data (parsed)'!$E$2:$E$235,$A29,'Data (parsed)'!$B$2:$B$235,D$21) -> 1 | E29: =COUNTIFS('Data (parsed)'!$E$2:$E$235,$A29,'Data (parsed)'!$B$2:$B$235,E$21) -> 0 | F29: =SUM(B29:E29) -> 3
A30: Uncle Peter | B30: =COUNTIFS('Data (parsed)'!$E$2:$E$235,$A30,'Data (parsed)'!$B$2:$B$235,B$21) -> 2 | C30: =COUNTIFS('Data (parsed)'!$E$2:$E$235,$A30,'Data (parsed)'!$B$2:$B$235,C$21) -> 0 | D30: =COUNTIFS('Data (parsed)'!$E$2:$E$235,$A30,'Data (parsed)'!$B$2:$B$235,D$21) -> 0 | E30: =COUNTIFS('Data (parsed)'!$E$2:$E$235,$A30,'Data (parsed)'!$B$2:$B$235,E$21) -> 0 | F30: =SUM(B30:E30) -> 2
A31: Mammy | B31: =COUNTIFS('Data (parsed)'!$E$2:$E$235,$A31,'Data (parsed)'!$B$2:$B$235,B$21) -> 1 | C31: =COUNTIFS('Data (parsed)'!$E$2:$E$235,$A31,'Data (parsed)'!$B$2:$B$235,C$21) -> 0 | D31: =COUNTIFS('Data (parsed)'!$E$2:$E$235,$A31,'Data (parsed)'!$B$2:$B$235,D$21) -> 1 | E31: =COUNTIFS('Data (parsed)'!$E$2:$E$235,$A31,'Data (parsed)'!$B$2:$B$235,E$21) -> 0 | F31: =SUM(B31:E31) -> 2
A32: Suellen | B32: =COUNTIFS('Data (parsed)'!$E$2:$E$235,$A32,'Data (parsed)'!$B$2:$B$235,B$21) -> 2 | C32: =COUNTIFS('Data (parsed)'!$E$2:$E$235,$A32,'Data (parsed)'!$B$2:$B$235,C$21) -> 0 | D32: =COUNTIFS('Data (parsed)'!$E$2:$E$235,$A32,'Data (parsed)'!$B$2:$B$235,D$21) -> 0 | E32: =COUNTIFS('Data (parsed)'!$E$2:$E$235,$A32,'Data (parsed)'!$B$2:$B$235,E$21) -> 0 | F32: =SUM(B32:E32) -> 2
A33: Prissy | B33: =COUNTIFS('Data (parsed)'!$E$2:$E$235,$A33,'Data (parsed)'!$B$2:$B$235,B$21) -> 1 | C33: =COUNTIFS('Data (parsed)'!$E$2:$E$235,$A33,'Data (parsed)'!$B$2:$B$235,C$21) -> 0 | D33: =COUNTIFS('Data (parsed)'!$E$2:$E$235,$A33,'Data (parsed)'!$B$2:$B$235,D$21) -> 0 | E33: =COUNTIFS('Data (parsed)'!$E$2:$E$235,$A33,'Data (parsed)'!$B$2:$B$235,E$21) -> 0 | F33: =SUM(B33:E33) -> 1
... A46: Rhett’s father | B46: =COUNTIFS('Data (parsed)'!$E$2:$E$235,$A46,'Data (parsed)'!$B$2:$B$235,B$21) -> 0 | C46: =COUNTIFS('Data (parsed)'!$E$2:$E$235,$A46,'Data (parsed)'!$B$2:$B$235,C$21) -> 0 | D46: =COUNTIFS('Data (parsed)'!$E$2:$E$235,$A46,'Data (parsed)'!$B$2:$B$235,D$21) -> 0 | E46: =COUNTIFS('Data (parsed)'!$E$2:$E$235,$A46,'Data (parsed)'!$B$2:$B$235,E$21) -> 1 | F46: =SUM(B46:E46) -> 1

Sheet Principal characters
A1: Principal characters — counts
A2: The four central characters. Dual-character tokens (#23, #128, #229) are counted under each of their two characters, so the four character rows sum to 190; the distinct-token count is 187.
A4: By English word (domain)
A5: Character | B5: Shame | C5: Guilt | D5: Conscience | E5: Honor | F5: Total
A6: Scarlett | B6: =COUNTIFS('Data (parsed)'!$E$2:$E$235,$A6,'Data (parsed)'!$B$2:$B$235,B$5) -> 48 | C6: =COUNTIFS('Data (parsed)'!$E$2:$E$235,$A6,'Data (parsed)'!$B$2:$B$235,C$5) -> 24 | D6: =COUNTIFS('Data (parsed)'!$E$2:$E$235,$A6,'Data (parsed)'!$B$2:$B$235,D$5) -> 31 | E6: =COUNTIFS('Data (parsed)'!$E$2:$E$235,$A6,'Data (parsed)'!$B$2:$B$235,E$5) -> 9 | F6: =SUM(B6:E6) -> 112
A7: Ashley | B7: =COUNTIFS('Data (parsed)'!$E$2:$E$235,$A7,'Data (parsed)'!$B$2:$B$235,B$5) -> 7 | C7: =COUNTIFS('Data (parsed)'!$E$2:$E$235,$A7,'Data (parsed)'!$B$2:$B$235,C$5) -> 0 | D7: =COUNTIFS('Data (parsed)'!$E$2:$E$235,$A7,'Data (parsed)'!$B$2:$B$235,D$5) -> 0 | E7: =COUNTIFS('Data (parsed)'!$E$2:$E$235,$A7,'Data (parsed)'!$B$2:$B$235,E$5) -> 28 | F7: =SUM(B7:E7) -> 35
A8: Rhett | B8: =COUNTIFS('Data (parsed)'!$E$2:$E$235,$A8,'Data (parsed)'!$B$2:$B$235,B$5) -> 20 | C8: =COUNTIFS('Data (parsed)'!$E$2:$E$235,$A8,'Data (parsed)'!$B$2:$B$235,C$5) -> 0 | D8: =COUNTIFS('Data (parsed)'!$E$2:$E$235,$A8,'Data (parsed)'!$B$2:$B$235,D$5) -> 2 | E8: =COUNTIFS('Data (parsed)'!$E$2:$E$235,$A8,'Data (parsed)'!$B$2:$B$235,E$5) -> 8 | F8: =SUM(B8:E8) -> 30
A9: Melanie | B9: =COUNTIFS('Data (parsed)'!$E$2:$E$235,$A9,'Data (parsed)'!$B$2:$B$235,B$5) -> 8 | C9: =COUNTIFS('Data (parsed)'!$E$2:$E$235,$A9,'Data (parsed)'!$B$2:$B$235,C$5) -> 3 | D9: =COUNTIFS('Data (parsed)'!$E$2:$E$235,$A9,'Data (parsed)'!$B$2:$B$235,D$5) -> 1 | E9: =COUNTIFS('Data (parsed)'!$E$2:$E$235,$A9,'Data (parsed)'!$B$2:$B$235,E$5) -> 1 | F9: =SUM(B9:E9) -> 13
A10: Distinct tokens | B10: =SUMIFS('Data (parsed)'!$I$2:$I$235,'Data (parsed)'!$J$2:$J$235,1,'Data (parsed)'!$B$2:$B$235,B$5) -> 82 | C10: =SUMIFS('Data (parsed)'!$I$2:$I$235,'Data (parsed)'!$J$2:$J$235,1,'Data (parsed)'!$B$2:$B$235,C$5) -> 26 | D10: =SUMIFS('Data (parsed)'!$I$2:$I$235,'Data (parsed)'!$J$2:$J$235,1,'Data (parsed)'!$B$2:$B$235,D$5) -> 34 | E10: =SUMIFS('Data (parsed)'!$I$2:$I$235,'Data (parsed)'!$J$2:$J$235,1,'Data (parsed)'!$B$2:$B$235,E$5) -> 45 | F10: =SUM(B10:E10) -> 187
A12: By Part of the novel (the arc)
A13: Character | B13: P1 | C13: P2 | D13: P3 | E13: P4 | F13: P5 | G13: Total
A14: Scarlett | B14: =COUNTIFS('Data (parsed)'!$E$2:$E$235,$A14,'Data (parsed)'!$D$2:$D$235,B$13) -> 8 | C14: =COUNTIFS('Data (parsed)'!$E$2:$E$235,$A14,'Data (parsed)'!$D$2:$D$235,C$13) -> 16 | D14: =COUNTIFS('Data (parsed)'!$E$2:$E$235,$A14,'Data (parsed)'!$D$2:$D$235,D$13) -> 14 | E14: =COUNTIFS('Data (parsed)'!$E$2:$E$235,$A14,'Data (parsed)'!$D$2:$D$235,E$13) -> 42 | F14: =COUNTIFS('Data (parsed)'!$E$2:$E$235,$A14,'Data (parsed)'!$D$2:$D$235,F$13) -> 32 | G14: =SUM(B14:F14) -> 112
A15: Ashley | B15: =COUNTIFS('Data (parsed)'!$E$2:$E$235,$A15,'Data (parsed)'!$D$2:$D$235,B$13) -> 0 | C15: =COUNTIFS('Data (parsed)'!$E$2:$E$235,$A15,'Data (parsed)'!$D$2:$D$235,C$13) -> 3 | D15: =COUNTIFS('Data (parsed)'!$E$2:$E$235,$A15,'Data (parsed)'!$D$2:$D$235,D$13) -> 1 | E15: =COUNTIFS('Data (parsed)'!$E$2:$E$235,$A15,'Data (parsed)'!$D$2:$D$235,E$13) -> 17 | F15: =COUNTIFS('Data (parsed)'!$E$2:$E$235,$A15,'Data (parsed)'!$D$2:$D$235,F$13) -> 14 | G15: =SUM(B15:F15) -> 35
A16: Rhett | B16: =COUNTIFS('Data (parsed)'!$E$2:$E$235,$A16,'Data (parsed)'!$D$2:$D$235,B$13) -> 0 | C16: =COUNTIFS('Data (parsed)'!$E$2:$E$235,$A16,'Data (parsed)'!$D$2:$D$235,C$13) -> 2 | D16: =COUNTIFS('Data (parsed)'!$E$2:$E$235,$A16,'Data (parsed)'!$D$2:$D$235,D$13) -> 3 | E16: =COUNTIFS('Data (parsed)'!$E$2:$E$235,$A16,'Data (parsed)'!$D$2:$D$235,E$13) -> 14 | F16: =COUNTIFS('Data (parsed)'!$E$2:$E$235,$A16,'Data (parsed)'!$D$2:$D$235,F$13) -> 11 | G16: =SUM(B16:F16) -> 30
A17: Melanie | B17: =COUNTIFS('Data (parsed)'!$E$2:$E$235,$A17,'Data (parsed)'!$D$2:$D$235,B$13) -> 0 | C17: =COUNTIFS('Data (parsed)'!$E$2:$E$235,$A17,'Data (parsed)'!$D$2:$D$235,C$13) -> 4 | D17: =COUNTIFS('Data (parsed)'!$E$2:$E$235,$A17,'Data (parsed)'!$D$2:$D$235,D$13) -> 3 | E17: =COUNTIFS('Data (parsed)'!$E$2:$E$235,$A17,'Data (parsed)'!$D$2:$D$235,E$13) -> 1 | F17: =COUNTIFS('Data (parsed)'!$E$2:$E$235,$A17,'Data (parsed)'!$D$2:$D$235,F$13) -> 5 | G17: =SUM(B17:F17) -> 13

Sheet Shame
A1: SHAME — 104 tokens
A3: Shame: subtype × part of novel (arc)
A4: Subtype | B4: P1 | C4: P2 | D4: P3 | E4: P4 | F4: P5 | G4: Total
A5: Moral shame | B5: =SUMIFS('Data (parsed)'!$I$2:$I$235,'Data (parsed)'!$B$2:$B$235,"Shame",'Data (parsed)'!$C$2:$C$235,$A5,'Data (parsed)'!$D$2:$D$235,B$4) -> 2 | C5: =SUMIFS('Data (parsed)'!$I$2:$I$235,'Data (parsed)'!$B$2:$B$235,"Shame",'Data (parsed)'!$C$2:$C$235,$A5,'Data (parsed)'!$D$2:$D$235,C$4) -> 1 | D5: =SUMIFS('Data (parsed)'!$I$2:$I$235,'Data (parsed)'!$B$2:$B$235,"Shame",'Data (parsed)'!$C$2:$C$235,$A5,'Data (parsed)'!$D$2:$D$235,D$4) -> 6 | E5: =SUMIFS('Data (parsed)'!$I$2:$I$235,'Data (parsed)'!$B$2:$B$235,"Shame",'Data (parsed)'!$C$2:$C$235,$A5,'Data (parsed)'!$D$2:$D$235,E$4) -> 9 | F5: =SUMIFS('Data (parsed)'!$I$2:$I$235,'Data (parsed)'!$B$2:$B$235,"Shame",'Data (parsed)'!$C$2:$C$235,$A5,'Data (parsed)'!$D$2:$D$235,F$4) -> 7 | G5: =SUM(B5:F5) -> 25
A6: Social shame | B6: =SUMIFS('Data (parsed)'!$I$2:$I$235,'Data (parsed)'!$B$2:$B$235,"Shame",'Data (parsed)'!$C$2:$C$235,$A6,'Data (parsed)'!$D$2:$D$235,B$4) -> 2 | C6: =SUMIFS('Data (parsed)'!$I$2:$I$235,'Data (parsed)'!$B$2:$B$235,"Shame",'Data (parsed)'!$C$2:$C$235,$A6,'Data (parsed)'!$D$2:$D$235,C$4) -> 4 | D6: =SUMIFS('Data (parsed)'!$I$2:$I$235,'Data (parsed)'!$B$2:$B$235,"Shame",'Data (parsed)'!$C$2:$C$235,$A6,'Data (parsed)'!$D$2:$D$235,D$4) -> 1 | E6: =SUMIFS('Data (parsed)'!$I$2:$I$235,'Data (parsed)'!$B$2:$B$235,"Shame",'Data (parsed)'!$C$2:$C$235,$A6,'Data (parsed)'!$D$2:$D$235,E$4) -> 6 | F6: =SUMIFS('Data (parsed)'!$I$2:$I$235,'Data (parsed)'!$B$2:$B$235,"Shame",'Data (parsed)'!$C$2:$C$235,$A6,'Data (parsed)'!$D$2:$D$235,F$4) -> 6 | G6: =SUM(B6:F6) -> 19
A7: Illocutionary shame (shaming) | B7: =SUMIFS('Data (parsed)'!$I$2:$I$235,'Data (parsed)'!$B$2:$B$235,"Shame",'Data (parsed)'!$C$2:$C$235,$A7,'Data (parsed)'!$D$2:$D$235,B$4) -> 0 | C7: =SUMIFS('Data (parsed)'!$I$2:$I$235,'Data (parsed)'!$B$2:$B$235,"Shame",'Data (parsed)'!$C$2:$C$235,$A7,'Data (parsed)'!$D$2:$D$235,C$4) -> 3 | D7: =SUMIFS('Data (parsed)'!$I$2:$I$235,'Data (parsed)'!$B$2:$B$235,"Shame",'Data (parsed)'!$C$2:$C$235,$A7,'Data (parsed)'!$D$2:$D$235,D$4) -> 3 | E7: =SUMIFS('Data (parsed)'!$I$2:$I$235,'Data (parsed)'!$B$2:$B$235,"Shame",'Data (parsed)'!$C$2:$C$235,$A7,'Data (parsed)'!$D$2:$D$235,E$4) -> 6 | F7: =SUMIFS('Data (parsed)'!$I$2:$I$235,'Data (parsed)'!$B$2:$B$235,"Shame",'Data (parsed)'!$C$2:$C$235,$A7,'Data (parsed)'!$D$2:$D$235,F$4) -> 5 | G7: =SUM(B7:F7) -> 17
A8: Absent shame | B8: =SUMIFS('Data (parsed)'!$I$2:$I$235,'Data (parsed)'!$B$2:$B$235,"Shame",'Data (parsed)'!$C$2:$C$235,$A8,'Data (parsed)'!$D$2:$D$235,B$4) -> 0 | C8: =SUMIFS('Data (parsed)'!$I$2:$I$235,'Data (parsed)'!$B$2:$B$235,"Shame",'Data (parsed)'!$C$2:$C$235,$A8,'Data (parsed)'!$D$2:$D$235,C$4) -> 4 | D8: =SUMIFS('Data (parsed)'!$I$2:$I$235,'Data (parsed)'!$B$2:$B$235,"Shame",'Data (parsed)'!$C$2:$C$235,$A8,'Data (parsed)'!$D$2:$D$235,D$4) -> 1 | E8: =SUMIFS('Data (parsed)'!$I$2:$I$235,'Data (parsed)'!$B$2:$B$235,"Shame",'Data (parsed)'!$C$2:$C$235,$A8,'Data (parsed)'!$D$2:$D$235,E$4) -> 2 | F8: =SUMIFS('Data (parsed)'!$I$2:$I$235,'Data (parsed)'!$B$2:$B$235,"Shame",'Data (parsed)'!$C$2:$C$235,$A8,'Data (parsed)'!$D$2:$D$235,F$4) -> 5 | G8: =SUM(B8:F8) -> 12
A9: Performed / ironic shame | B9: =SUMIFS('Data (parsed)'!$I$2:$I$235,'Data (parsed)'!$B$2:$B$235,"Shame",'Data (parsed)'!$C$2:$C$235,$A9,'Data (parsed)'!$D$2:$D$235,B$4) -> 0 | C9: =SUMIFS('Data (parsed)'!$I$2:$I$235,'Data (parsed)'!$B$2:$B$235,"Shame",'Data (parsed)'!$C$2:$C$235,$A9,'Data (parsed)'!$D$2:$D$235,C$4) -> 0 | D9: =SUMIFS('Data (parsed)'!$I$2:$I$235,'Data (parsed)'!$B$2:$B$235,"Shame",'Data (parsed)'!$C$2:$C$235,$A9,'Data (parsed)'!$D$2:$D$235,D$4) -> 1 | E9: =SUMIFS('Data (parsed)'!$I$2:$I$235,'Data (parsed)'!$B$2:$B$235,"Shame",'Data (parsed)'!$C$2:$C$235,$A9,'Data (parsed)'!$D$2:$D$235,E$4) -> 3 | F9: =SUMIFS('Data (parsed)'!$I$2:$I$235,'Data (parsed)'!$B$2:$B$235,"Shame",'Data (parsed)'!$C$2:$C$235,$A9,'Data (parsed)'!$D$2:$D$235,F$4) -> 5 | G9: =SUM(B9:F9) -> 9
A10: Absent social shame | B10: =SUMIFS('Data (parsed)'!$I$2:$I$235,'Data (parsed)'!$B$2:$B$235,"Shame",'Data (parsed)'!$C$2:$C$235,$A10,'Data (parsed)'!$D$2:$D$235,B$4) -> 0 | C10: =SUMIFS('Data (parsed)'!$I$2:$I$235,'Data (parsed)'!$B$2:$B$235,"Shame",'Data (parsed)'!$C$2:$C$235,$A10,'Data (parsed)'!$D$2:$D$235,C$4) -> 0 | D10: =SUMIFS('Data (parsed)'!$I$2:$I$235,'Data (parsed)'!$B$2:$B$235,"Shame",'Data (parsed)'!$C$2:$C$235,$A10,'Data (parsed)'!$D$2:$D$235,D$4) -> 3 | E10: =SUMIFS('Data (parsed)'!$I$2:$I$235,'Data (parsed)'!$B$2:$B$235,"Shame",'Data (parsed)'!$C$2:$C$235,$A10,'Data (parsed)'!$D$2:$D$235,E$4) -> 3 | F10: =SUMIFS('Data (parsed)'!$I$2:$I$235,'Data (parsed)'!$B$2:$B$235,"Shame",'Data (parsed)'!$C$2:$C$235,$A10,'Data (parsed)'!$D$2:$D$235,F$4) -> 1 | G10: =SUM(B10:F10) -> 7
A11: Social shame (somatic expression) | B11: =SUMIFS('Data (parsed)'!$I$2:$I$235,'Data (parsed)'!$B$2:$B$235,"Shame",'Data (parsed)'!$C$2:$C$235,$A11,'Data (parsed)'!$D$2:$D$235,B$4) -> 0 | C11: =SUMIFS('Data (parsed)'!$I$2:$I$235,'Data (parsed)'!$B$2:$B$235,"Shame",'Data (parsed)'!$C$2:$C$235,$A11,'Data (parsed)'!$D$2:$D$235,C$4) -> 1 | D11: =SUMIFS('Data (parsed)'!$I$2:$I$235,'Data (parsed)'!$B$2:$B$235,"Shame",'Data (parsed)'!$C$2:$C$235,$A11,'Data (parsed)'!$D$2:$D$235,D$4) -> 1 | E11: =SUMIFS('Data (parsed)'!$I$2:$I$235,'Data (parsed)'!$B$2:$B$235,"Shame",'Data (parsed)'!$C$2:$C$235,$A11,'Data (parsed)'!$D$2:$D$235,E$4) -> 2 | F11: =SUMIFS('Data (parsed)'!$I$2:$I$235,'Data (parsed)'!$B$2:$B$235,"Shame",'Data (parsed)'!$C$2:$C$235,$A11,'Data (parsed)'!$D$2:$D$235,F$4) -> 0 | G11: =SUM(B11:F11) -> 4
A12: Social shame (about the body) | B12: =SUMIFS('Data (parsed)'!$I$2:$I$235,'Data (parsed)'!$B$2:$B$235,"Shame",'Data (parsed)'!$C$2:$C$235,$A12,'Data (parsed)'!$D$2:$D$235,B$4) -> 0 | C12: =SUMIFS('Data (parsed)'!$I$2:$I$235,'Data (parsed)'!$B$2:$B$235,"Shame",'Data (parsed)'!$C$2:$C$235,$A12,'Data (parsed)'!$D$2:$D$235,C$4) -> 0 | D12: =SUMIFS('Data (parsed)'!$I$2:$I$235,'Data (parsed)'!$B$2:$B$235,"Shame",'Data (parsed)'!$C$2:$C$235,$A12,'Data (parsed)'!$D$2:$D$235,D$4) -> 1 | E12: =SUMIFS('Data (parsed)'!$I$2:$I$235,'Data (parsed)'!$B$2:$B$235,"Shame",'Data (parsed)'!$C$2:$C$235,$A12,'Data (parsed)'!$D$2:$D$235,E$4) -> 3 | F12: =SUMIFS('Data (parsed)'!$I$2:$I$235,'Data (parsed)'!$B$2:$B$235,"Shame",'Data (parsed)'!$C$2:$C$235,$A12,'Data (parsed)'!$D$2:$D$235,F$4) -> 0 | G12: =SUM(B12:F12) -> 4
A13: Absent moral shame | B13: =SUMIFS('Data (parsed)'!$I$2:$I$235,'Data (parsed)'!$B$2:$B$235,"Shame",'Data (parsed)'!$C$2:$C$235,$A13,'Data (parsed)'!$D$2:$D$235,B$4) -> 0 | C13: =SUMIFS('Data (parsed)'!$I$2:$I$235,'Data (parsed)'!$B$2:$B$235,"Shame",'Data (parsed)'!$C$2:$C$235,$A13,'Data (parsed)'!$D$2:$D$235,C$4) -> 1 | D13: =SUMIFS('Data (parsed)'!$I$2:$I$235,'Data (parsed)'!$B$2:$B$235,"Shame",'Data (parsed)'!$C$2:$C$235,$A13,'Data (parsed)'!$D$2:$D$235,D$4) -> 0 | E13: =SUMIFS('Data (parsed)'!$I$2:$I$235,'Data (parsed)'!$B$2:$B$235,"Shame",'Data (parsed)'!$C$2:$C$235,$A13,'Data (parsed)'!$D$2:$D$235,E$4) -> 1 | F13: =SUMIFS('Data (parsed)'!$I$2:$I$235,'Data (parsed)'!$B$2:$B$235,"Shame",'Data (parsed)'!$C$2:$C$235,$A13,'Data (parsed)'!$D$2:$D$235,F$4) -> 1 | G13: =SUM(B13:F13) -> 3
A14: Absent social shame (about the body) | B14: =SUMIFS('Data (parsed)'!$I$2:$I$235,'Data (parsed)'!$B$2:$B$235,"Shame",'Data (parsed)'!$C$2:$C$235,$A14,'Data (parsed)'!$D$2:$D$235,B$4) -> 2 | C14: =SUMIFS('Data (parsed)'!$I$2:$I$235,'Data (parsed)'!$B$2:$B$235,"Shame",'Data (parsed)'!$C$2:$C$235,$A14,'Data (parsed)'!$D$2:$D$235,C$4) -> 0 | D14: =SUMIFS('Data (parsed)'!$I$2:$I$235,'Data (parsed)'!$B$2:$B$235,"Shame",'Data (parsed)'!$C$2:$C$235,$A14,'Data (parsed)'!$D$2:$D$235,D$4) -> 0 | E14: =SUMIFS('Data (parsed)'!$I$2:$I$235,'Data (parsed)'!$B$2:$B$235,"Shame",'Data (parsed)'!$C$2:$C$235,$A14,'Data (parsed)'!$D$2:$D$235,E$4) -> 0 | F14: =SUMIFS('Data (parsed)'!$I$2:$I$235,'Data (parsed)'!$B$2:$B$235,"Shame",'Data (parsed)'!$C$2:$C$235,$A14,'Data (parsed)'!$D$2:$D$235,F$4) -> 0 | G14: =SUM(B14:F14) -> 2
A15: Shame as verdict | B15: =SUMIFS('Data (parsed)'!$I$2:$I$235,'Data (parsed)'!$B$2:$B$235,"Shame",'Data (parsed)'!$C$2:$C$235,$A15,'Data (parsed)'!$D$2:$D$235,B$4) -> 0 | C15: =SUMIFS('Data (parsed)'!$I$2:$I$235,'Data (parsed)'!$B$2:$B$235,"Shame",'Data (parsed)'!$C$2:$C$235,$A15,'Data (parsed)'!$D$2:$D$235,C$4) -> 0 | D15: =SUMIFS('Data (parsed)'!$I$2:$I$235,'Data (parsed)'!$B$2:$B$235,"Shame",'Data (parsed)'!$C$2:$C$235,$A15,'Data (parsed)'!$D$2:$D$235,D$4) -> 0 | E15: =SUMIFS('Data (parsed)'!$I$2:$I$235,'Data (parsed)'!$B$2:$B$235,"Shame",'Data (parsed)'!$C$2:$C$235,$A15,'Data (parsed)'!$D$2:$D$235,E$4) -> 2 | F15: =SUMIFS('Data (parsed)'!$I$2:$I$235,'Data (parsed)'!$B$2:$B$235,"Shame",'Data (parsed)'!$C$2:$C$235,$A15,'Data (parsed)'!$D$2:$D$235,F$4) -> 0 | G15: =SUM(B15:F15) -> 2
A16: Total | B16: =SUM(B5:B15) -> 6 | C16: =SUM(C5:C15) -> 14 | D16: =SUM(D5:D15) -> 17 | E16: =SUM(E5:E15) -> 37 | F16: =SUM(F5:F15) -> 30 | G16: =SUM(G5:G15) -> 104
A18: Shame: subtype × character (dual tokens counted under each principal; Tokens = distinct count)
A19: Subtype | B19: Scarlett | C19: Ashley | D19: Rhett | E19: Melanie | F19: Other | G19: Tokens
A20: Moral shame | B20: =COUNTIFS('Data (parsed)'!$E$2:$E$235,B$19,'Data (parsed)'!$B$2:$B$235,"Shame",'Data (parsed)'!$C$2:$C$235,$A20) -> 18 | C20: =COUNTIFS('Data (parsed)'!$E$2:$E$235,C$19,'Data (parsed)'!$B$2:$B$235,"Shame",'Data (parsed)'!$C$2:$C$235,$A20) -> 4 | D20: =COUNTIFS('Data (parsed)'!$E$2:$E$235,D$19,'Data (parsed)'!$B$2:$B$235,"Shame",'Data (parsed)'!$C$2:$C$235,$A20) -> 1 | E20: =COUNTIFS('Data (parsed)'!$E$2:$E$235,E$19,'Data (parsed)'!$B$2:$B$235,"Shame",'Data (parsed)'!$C$2:$C$235,$A20) -> 1 | F20: =SUMIFS('Data (parsed)'!$I$2:$I$235,'Data (parsed)'!$B$2:$B$235,"Shame",'Data (parsed)'!$C$2:$C$235,$A20,'Data (parsed)'!$J$2:$J$235,0) -> 2 | G20: =SUMIFS('Data (parsed)'!$I$2:$I$235,'Data (parsed)'!$B$2:$B$235,"Shame",'Data (parsed)'!$C$2:$C$235,$A20) -> 25
A21: Social shame | B21: =COUNTIFS('Data (parsed)'!$E$2:$E$235,B$19,'Data (parsed)'!$B$2:$B$235,"Shame",'Data (parsed)'!$C$2:$C$235,$A21) -> 9 | C21: =COUNTIFS('Data (parsed)'!$E$2:$E$235,C$19,'Data (parsed)'!$B$2:$B$235,"Shame",'Data (parsed)'!$C$2:$C$235,$A21) -> 2 | D21: =COUNTIFS('Data (parsed)'!$E$2:$E$235,D$19,'Data (parsed)'!$B$2:$B$235,"Shame",'Data (parsed)'!$C$2:$C$235,$A21) -> 0 | E21: =COUNTIFS('Data (parsed)'!$E$2:$E$235,E$19,'Data (parsed)'!$B$2:$B$235,"Shame",'Data (parsed)'!$C$2:$C$235,$A21) -> 0 | F21: =SUMIFS('Data (parsed)'!$I$2:$I$235,'Data (parsed)'!$B$2:$B$235,"Shame",'Data (parsed)'!$C$2:$C$235,$A21,'Data (parsed)'!$J$2:$J$235,0) -> 8 | G21: =SUMIFS('Data (parsed)'!$I$2:$I$235,'Data (parsed)'!$B$2:$B$235,"Shame",'Data (parsed)'!$C$2:$C$235,$A21) -> 19
A22: Illocutionary shame (shaming) | B22: =COUNTIFS('Data (parsed)'!$E$2:$E$235,B$19,'Data (parsed)'!$B$2:$B$235,"Shame",'Data (parsed)'!$C$2:$C$235,$A22) -> 6 | C22: =COUNTIFS('Data (parsed)'!$E$2:$E$235,C$19,'Data (parsed)'!$B$2:$B$235,"Shame",'Data (parsed)'!$C$2:$C$235,$A22) -> 1 | D22: =COUNTIFS('Data (parsed)'!$E$2:$E$235,D$19,'Data (parsed)'!$B$2:$B$235,"Shame",'Data (parsed)'!$C$2:$C$235,$A22) -> 1 | E22: =COUNTIFS('Data (parsed)'!$E$2:$E$235,E$19,'Data (parsed)'!$B$2:$B$235,"Shame",'Data (parsed)'!$C$2:$C$235,$A22) -> 2 | F22: =SUMIFS('Data (parsed)'!$I$2:$I$235,'Data (parsed)'!$B$2:$B$235,"Shame",'Data (parsed)'!$C$2:$C$235,$A22,'Data (parsed)'!$J$2:$J$235,0) -> 7 | G22: =SUMIFS('Data (parsed)'!$I$2:$I$235,'Data (parsed)'!$B$2:$B$235,"Shame",'Data (parsed)'!$C$2:$C$235,$A22) -> 17
A23: Absent shame | B23: =COUNTIFS('Data (parsed)'!$E$2:$E$235,B$19,'Data (parsed)'!$B$2:$B$235,"Shame",'Data (parsed)'!$C$2:$C$235,$A23) -> 1 | C23: =COUNTIFS('Data (parsed)'!$E$2:$E$235,C$19,'Data (parsed)'!$B$2:$B$235,"Shame",'Data (parsed)'!$C$2:$C$235,$A23) -> 0 | D23: =COUNTIFS('Data (parsed)'!$E$2:$E$235,D$19,'Data (parsed)'!$B$2:$B$235,"Shame",'Data (parsed)'!$C$2:$C$235,$A23) -> 9 | E23: =COUNTIFS('Data (parsed)'!$E$2:$E$235,E$19,'Data (parsed)'!$B$2:$B$235,"Shame",'Data (parsed)'!$C$2:$C$235,$A23) -> 2 | F23: =SUMIFS('Data (parsed)'!$I$2:$I$235,'Data (parsed)'!$B$2:$B$235,"Shame",'Data (parsed)'!$C$2:$C$235,$A23,'Data (parsed)'!$J$2:$J$235,0) -> 0 | G23: =SUMIFS('Data (parsed)'!$I$2:$I$235,'Data (parsed)'!$B$2:$B$235,"Shame",'Data (parsed)'!$C$2:$C$235,$A23) -> 12
A24: Performed / ironic shame | B24: =COUNTIFS('Data (parsed)'!$E$2:$E$235,B$19,'Data (parsed)'!$B$2:$B$235,"Shame",'Data (parsed)'!$C$2:$C$235,$A24) -> 0 | C24: =COUNTIFS('Data (parsed)'!$E$2:$E$235,C$19,'Data (parsed)'!$B$2:$B$235,"Shame",'Data (parsed)'!$C$2:$C$235,$A24) -> 0 | D24: =COUNTIFS('Data (parsed)'!$E$2:$E$235,D$19,'Data (parsed)'!$B$2:$B$235,"Shame",'Data (parsed)'!$C$2:$C$235,$A24) -> 9 | E24: =COUNTIFS('Data (parsed)'!$E$2:$E$235,E$19,'Data (parsed)'!$B$2:$B$235,"Shame",'Data (parsed)'!$C$2:$C$235,$A24) -> 0 | F24: =SUMIFS('Data (parsed)'!$I$2:$I$235,'Data (parsed)'!$B$2:$B$235,"Shame",'Data (parsed)'!$C$2:$C$235,$A24,'Data (parsed)'!$J$2:$J$235,0) -> 0 | G24: =SUMIFS('Data (parsed)'!$I$2:$I$235,'Data (parsed)'!$B$2:$B$235,"Shame",'Data (parsed)'!$C$2:$C$235,$A24) -> 9
A25: Absent social shame | B25: =COUNTIFS('Data (parsed)'!$E$2:$E$235,B$19,'Data (parsed)'!$B$2:$B$235,"Shame",'Data (parsed)'!$C$2:$C$235,$A25) -> 2 | C25: =COUNTIFS('Data (parsed)'!$E$2:$E$235,C$19,'Data (parsed)'!$B$2:$B$235,"Shame",'Data (parsed)'!$C$2:$C$235,$A25) -> 0 | D25: =COUNTIFS('Data (parsed)'!$E$2:$E$235,D$19,'Data (parsed)'!$B$2:$B$235,"Shame",'Data (parsed)'!$C$2:$C$235,$A25) -> 0 | E25: =COUNTIFS('Data (parsed)'!$E$2:$E$235,E$19,'Data (parsed)'!$B$2:$B$235,"Shame",'Data (parsed)'!$C$2:$C$235,$A25) -> 2 | F25: =SUMIFS('Data (parsed)'!$I$2:$I$235,'Data (parsed)'!$B$2:$B$235,"Shame",'Data (parsed)'!$C$2:$C$235,$A25,'Data (parsed)'!$J$2:$J$235,0) -> 3 | G25: =SUMIFS('Data (parsed)'!$I$2:$I$235,'Data (parsed)'!$B$2:$B$235,"Shame",'Data (parsed)'!$C$2:$C$235,$A25) -> 7
A26: Social shame (somatic expression) | B26: =COUNTIFS('Data (parsed)'!$E$2:$E$235,B$19,'Data (parsed)'!$B$2:$B$235,"Shame",'Data (parsed)'!$C$2:$C$235,$A26) -> 4 | C26: =COUNTIFS('Data (parsed)'!$E$2:$E$235,C$19,'Data (parsed)'!$B$2:$B$235,"Shame",'Data (parsed)'!$C$2:$C$235,$A26) -> 0 | D26: =COUNTIFS('Data (parsed)'!$E$2:$E$235,D$19,'Data (parsed)'!$B$2:$B$235,"Shame",'Data (parsed)'!$C$2:$C$235,$A26) -> 0 | E26: =COUNTIFS('Data (parsed)'!$E$2:$E$235,E$19,'Data (parsed)'!$B$2:$B$235,"Shame",'Data (parsed)'!$C$2:$C$235,$A26) -> 0 | F26: =SUMIFS('Data (parsed)'!$I$2:$I$235,'Data (parsed)'!$B$2:$B$235,"Shame",'Data (parsed)'!$C$2:$C$235,$A26,'Data (parsed)'!$J$2:$J$235,0) -> 0 | G26: =SUMIFS('Data (parsed)'!$I$2:$I$235,'Data (parsed)'!$B$2:$B$235,"Shame",'Data (parsed)'!$C$2:$C$235,$A26) -> 4
A27: Social shame (about the body) | B27: =COUNTIFS('Data (parsed)'!$E$2:$E$235,B$19,'Data (parsed)'!$B$2:$B$235,"Shame",'Data (parsed)'!$C$2:$C$235,$A27) -> 3 | C27: =COUNTIFS('Data (parsed)'!$E$2:$E$235,C$19,'Data (parsed)'!$B$2:$B$235,"Shame",'Data (parsed)'!$C$2:$C$235,$A27) -> 0 | D27: =COUNTIFS('Data (parsed)'!$E$2:$E$235,D$19,'Data (parsed)'!$B$2:$B$235,"Shame",'Data (parsed)'!$C$2:$C$235,$A27) -> 0 | E27: =COUNTIFS('Data (parsed)'!$E$2:$E$235,E$19,'Data (parsed)'!$B$2:$B$235,"Shame",'Data (parsed)'!$C$2:$C$235,$A27) -> 1 | F27: =SUMIFS('Data (parsed)'!$I$2:$I$235,'Data (parsed)'!$B$2:$B$235,"Shame",'Data (parsed)'!$C$2:$C$235,$A27,'Data (parsed)'!$J$2:$J$235,0) -> 0 | G27: =SUMIFS('Data (parsed)'!$I$2:$I$235,'Data (parsed)'!$B$2:$B$235,"Shame",'Data (parsed)'!$C$2:$C$235,$A27) -> 4
A28: Absent moral shame | B28: =COUNTIFS('Data (parsed)'!$E$2:$E$235,B$19,'Data (parsed)'!$B$2:$B$235,"Shame",'Data (parsed)'!$C$2:$C$235,$A28) -> 3 | C28: =COUNTIFS('Data (parsed)'!$E$2:$E$235,C$19,'Data (parsed)'!$B$2:$B$235,"Shame",'Data (parsed)'!$C$2:$C$235,$A28) -> 0 | D28: =COUNTIFS('Data (parsed)'!$E$2:$E$235,D$19,'Data (parsed)'!$B$2:$B$235,"Shame",'Data (parsed)'!$C$2:$C$235,$A28) -> 0 | E28: =COUNTIFS('Data (parsed)'!$E$2:$E$235,E$19,'Data (parsed)'!$B$2:$B$235,"Shame",'Data (parsed)'!$C$2:$C$235,$A28) -> 0 | F28: =SUMIFS('Data (parsed)'!$I$2:$I$235,'Data (parsed)'!$B$2:$B$235,"Shame",'Data (parsed)'!$C$2:$C$235,$A28,'Data (parsed)'!$J$2:$J$235,0) -> 0 | G28: =SUMIFS('Data (parsed)'!$I$2:$I$235,'Data (parsed)'!$B$2:$B$235,"Shame",'Data (parsed)'!$C$2:$C$235,$A28) -> 3
A29: Absent social shame (about the body) | B29: =COUNTIFS('Data (parsed)'!$E$2:$E$235,B$19,'Data (parsed)'!$B$2:$B$235,"Shame",'Data (parsed)'!$C$2:$C$235,$A29) -> 2 | C29: =COUNTIFS('Data (parsed)'!$E$2:$E$235,C$19,'Data (parsed)'!$B$2:$B$235,"Shame",'Data (parsed)'!$C$2:$C$235,$A29) -> 0 | D29: =COUNTIFS('Data (parsed)'!$E$2:$E$235,D$19,'Data (parsed)'!$B$2:$B$235,"Shame",'Data (parsed)'!$C$2:$C$235,$A29) -> 0 | E29: =COUNTIFS('Data (parsed)'!$E$2:$E$235,E$19,'Data (parsed)'!$B$2:$B$235,"Shame",'Data (parsed)'!$C$2:$C$235,$A29) -> 0 | F29: =SUMIFS('Data (parsed)'!$I$2:$I$235,'Data (parsed)'!$B$2:$B$235,"Shame",'Data (parsed)'!$C$2:$C$235,$A29,'Data (parsed)'!$J$2:$J$235,0) -> 0 | G29: =SUMIFS('Data (parsed)'!$I$2:$I$235,'Data (parsed)'!$B$2:$B$235,"Shame",'Data (parsed)'!$C$2:$C$235,$A29) -> 2
A30: Shame as verdict | B30: =COUNTIFS('Data (parsed)'!$E$2:$E$235,B$19,'Data (parsed)'!$B$2:$B$235,"Shame",'Data (parsed)'!$C$2:$C$235,$A30) -> 0 | C30: =COUNTIFS('Data (parsed)'!$E$2:$E$235,C$19,'Data (parsed)'!$B$2:$B$235,"Shame",'Data (parsed)'!$C$2:$C$235,$A30) -> 0 | D30: =COUNTIFS('Data (parsed)'!$E$2:$E$235,D$19,'Data (parsed)'!$B$2:$B$235,"Shame",'Data (parsed)'!$C$2:$C$235,$A30) -> 0 | E30: =COUNTIFS('Data (parsed)'!$E$2:$E$235,E$19,'Data (parsed)'!$B$2:$B$235,"Shame",'Data (parsed)'!$C$2:$C$235,$A30) -> 0 | F30: =SUMIFS('Data (parsed)'!$I$2:$I$235,'Data (parsed)'!$B$2:$B$235,"Shame",'Data (parsed)'!$C$2:$C$235,$A30,'Data (parsed)'!$J$2:$J$235,0) -> 2 | G30: =SUMIFS('Data (parsed)'!$I$2:$I$235,'Data (parsed)'!$B$2:$B$235,"Shame",'Data (parsed)'!$C$2:$C$235,$A30) -> 2
A31: Total | B31: =SUM(B20:B30) -> 48 | C31: =SUM(C20:C30) -> 7 | D31: =SUM(D20:D30) -> 20 | E31: =SUM(E20:E30) -> 8 | F31: =SUM(F20:F30) -> 22 | G31: =SUM(G20:G30) -> 104

Sheet Guilt
A1: GUILT — 31 tokens
A3: Guilt: subtype × part of novel (arc)
A4: Subtype | B4: P1 | C4: P2 | D4: P3 | E4: P4 | F4: P5 | G4: Total
A5: Felt guilt | B5: =SUMIFS('Data (parsed)'!$I$2:$I$235,'Data (parsed)'!$B$2:$B$235,"Guilt",'Data (parsed)'!$C$2:$C$235,$A5,'Data (parsed)'!$D$2:$D$235,B$4) -> 2 | C5: =SUMIFS('Data (parsed)'!$I$2:$I$235,'Data (parsed)'!$B$2:$B$235,"Guilt",'Data (parsed)'!$C$2:$C$235,$A5,'Data (parsed)'!$D$2:$D$235,C$4) -> 3 | D5: =SUMIFS('Data (parsed)'!$I$2:$I$235,'Data (parsed)'!$B$2:$B$235,"Guilt",'Data (parsed)'!$C$2:$C$235,$A5,'Data (parsed)'!$D$2:$D$235,D$4) -> 2 | E5: =SUMIFS('Data (parsed)'!$I$2:$I$235,'Data (parsed)'!$B$2:$B$235,"Guilt",'Data (parsed)'!$C$2:$C$235,$A5,'Data (parsed)'!$D$2:$D$235,E$4) -> 3 | F5: =SUMIFS('Data (parsed)'!$I$2:$I$235,'Data (parsed)'!$B$2:$B$235,"Guilt",'Data (parsed)'!$C$2:$C$235,$A5,'Data (parsed)'!$D$2:$D$235,F$4) -> 7 | G5: =SUM(B5:F5) -> 17
A6: Guilt as deed | B6: =SUMIFS('Data (parsed)'!$I$2:$I$235,'Data (parsed)'!$B$2:$B$235,"Guilt",'Data (parsed)'!$C$2:$C$235,$A6,'Data (parsed)'!$D$2:$D$235,B$4) -> 0 | C6: =SUMIFS('Data (parsed)'!$I$2:$I$235,'Data (parsed)'!$B$2:$B$235,"Guilt",'Data (parsed)'!$C$2:$C$235,$A6,'Data (parsed)'!$D$2:$D$235,C$4) -> 1 | D6: =SUMIFS('Data (parsed)'!$I$2:$I$235,'Data (parsed)'!$B$2:$B$235,"Guilt",'Data (parsed)'!$C$2:$C$235,$A6,'Data (parsed)'!$D$2:$D$235,D$4) -> 0 | E6: =SUMIFS('Data (parsed)'!$I$2:$I$235,'Data (parsed)'!$B$2:$B$235,"Guilt",'Data (parsed)'!$C$2:$C$235,$A6,'Data (parsed)'!$D$2:$D$235,E$4) -> 0 | F6: =SUMIFS('Data (parsed)'!$I$2:$I$235,'Data (parsed)'!$B$2:$B$235,"Guilt",'Data (parsed)'!$C$2:$C$235,$A6,'Data (parsed)'!$D$2:$D$235,F$4) -> 4 | G6: =SUM(B6:F6) -> 5
A7: Felt guilt (guilty pleasure) | B7: =SUMIFS('Data (parsed)'!$I$2:$I$235,'Data (parsed)'!$B$2:$B$235,"Guilt",'Data (parsed)'!$C$2:$C$235,$A7,'Data (parsed)'!$D$2:$D$235,B$4) -> 2 | C7: =SUMIFS('Data (parsed)'!$I$2:$I$235,'Data (parsed)'!$B$2:$B$235,"Guilt",'Data (parsed)'!$C$2:$C$235,$A7,'Data (parsed)'!$D$2:$D$235,C$4) -> 0 | D7: =SUMIFS('Data (parsed)'!$I$2:$I$235,'Data (parsed)'!$B$2:$B$235,"Guilt",'Data (parsed)'!$C$2:$C$235,$A7,'Data (parsed)'!$D$2:$D$235,D$4) -> 0 | E7: =SUMIFS('Data (parsed)'!$I$2:$I$235,'Data (parsed)'!$B$2:$B$235,"Guilt",'Data (parsed)'!$C$2:$C$235,$A7,'Data (parsed)'!$D$2:$D$235,E$4) -> 1 | F7: =SUMIFS('Data (parsed)'!$I$2:$I$235,'Data (parsed)'!$B$2:$B$235,"Guilt",'Data (parsed)'!$C$2:$C$235,$A7,'Data (parsed)'!$D$2:$D$235,F$4) -> 0 | G7: =SUM(B7:F7) -> 3
A8: Felt guilt (guilty conscience) | B8: =SUMIFS('Data (parsed)'!$I$2:$I$235,'Data (parsed)'!$B$2:$B$235,"Guilt",'Data (parsed)'!$C$2:$C$235,$A8,'Data (parsed)'!$D$2:$D$235,B$4) -> 0 | C8: =SUMIFS('Data (parsed)'!$I$2:$I$235,'Data (parsed)'!$B$2:$B$235,"Guilt",'Data (parsed)'!$C$2:$C$235,$A8,'Data (parsed)'!$D$2:$D$235,C$4) -> 1 | D8: =SUMIFS('Data (parsed)'!$I$2:$I$235,'Data (parsed)'!$B$2:$B$235,"Guilt",'Data (parsed)'!$C$2:$C$235,$A8,'Data (parsed)'!$D$2:$D$235,D$4) -> 0 | E8: =SUMIFS('Data (parsed)'!$I$2:$I$235,'Data (parsed)'!$B$2:$B$235,"Guilt",'Data (parsed)'!$C$2:$C$235,$A8,'Data (parsed)'!$D$2:$D$235,E$4) -> 0 | F8: =SUMIFS('Data (parsed)'!$I$2:$I$235,'Data (parsed)'!$B$2:$B$235,"Guilt",'Data (parsed)'!$C$2:$C$235,$A8,'Data (parsed)'!$D$2:$D$235,F$4) -> 2 | G8: =SUM(B8:F8) -> 3
A9: Guilt as tormentor | B9: =SUMIFS('Data (parsed)'!$I$2:$I$235,'Data (parsed)'!$B$2:$B$235,"Guilt",'Data (parsed)'!$C$2:$C$235,$A9,'Data (parsed)'!$D$2:$D$235,B$4) -> 0 | C9: =SUMIFS('Data (parsed)'!$I$2:$I$235,'Data (parsed)'!$B$2:$B$235,"Guilt",'Data (parsed)'!$C$2:$C$235,$A9,'Data (parsed)'!$D$2:$D$235,C$4) -> 2 | D9: =SUMIFS('Data (parsed)'!$I$2:$I$235,'Data (parsed)'!$B$2:$B$235,"Guilt",'Data (parsed)'!$C$2:$C$235,$A9,'Data (parsed)'!$D$2:$D$235,D$4) -> 0 | E9: =SUMIFS('Data (parsed)'!$I$2:$I$235,'Data (parsed)'!$B$2:$B$235,"Guilt",'Data (parsed)'!$C$2:$C$235,$A9,'Data (parsed)'!$D$2:$D$235,E$4) -> 0 | F9: =SUMIFS('Data (parsed)'!$I$2:$I$235,'Data (parsed)'!$B$2:$B$235,"Guilt",'Data (parsed)'!$C$2:$C$235,$A9,'Data (parsed)'!$D$2:$D$235,F$4) -> 0 | G9: =SUM(B9:F9) -> 2
A10: Guilt as weight | B10: =SUMIFS('Data (parsed)'!$I$2:$I$235,'Data (parsed)'!$B$2:$B$235,"Guilt",'Data (parsed)'!$C$2:$C$235,$A10,'Data (parsed)'!$D$2:$D$235,B$4) -> 0 | C10: =SUMIFS('Data (parsed)'!$I$2:$I$235,'Data (parsed)'!$B$2:$B$235,"Guilt",'Data (parsed)'!$C$2:$C$235,$A10,'Data (parsed)'!$D$2:$D$235,C$4) -> 0 | D10: =SUMIFS('Data (parsed)'!$I$2:$I$235,'Data (parsed)'!$B$2:$B$235,"Guilt",'Data (parsed)'!$C$2:$C$235,$A10,'Data (parsed)'!$D$2:$D$235,D$4) -> 0 | E10: =SUMIFS('Data (parsed)'!$I$2:$I$235,'Data (parsed)'!$B$2:$B$235,"Guilt",'Data (parsed)'!$C$2:$C$235,$A10,'Data (parsed)'!$D$2:$D$235,E$4) -> 1 | F10: =SUMIFS('Data (parsed)'!$I$2:$I$235,'Data (parsed)'!$B$2:$B$235,"Guilt",'Data (parsed)'!$C$2:$C$235,$A10,'Data (parsed)'!$D$2:$D$235,F$4) -> 0 | G10: =SUM(B10:F10) -> 1
A11: Total | B11: =SUM(B5:B10) -> 4 | C11: =SUM(C5:C10) -> 7 | D11: =SUM(D5:D10) -> 2 | E11: =SUM(E5:E10) -> 5 | F11: =SUM(F5:F10) -> 13 | G11: =SUM(G5:G10) -> 31
A13: Guilt: subtype × character (dual tokens counted under each principal; Tokens = distinct count)
A14: Subtype | B14: Scarlett | C14: Ashley | D14: Rhett | E14: Melanie | F14: Other | G14: Tokens
A15: Felt guilt | B15: =COUNTIFS('Data (parsed)'!$E$2:$E$235,B$14,'Data (parsed)'!$B$2:$B$235,"Guilt",'Data (parsed)'!$C$2:$C$235,$A15) -> 12 | C15: =COUNTIFS('Data (parsed)'!$E$2:$E$235,C$14,'Data (parsed)'!$B$2:$B$235,"Guilt",'Data (parsed)'!$C$2:$C$235,$A15) -> 0 | D15: =COUNTIFS('Data (parsed)'!$E$2:$E$235,D$14,'Data (parsed)'!$B$2:$B$235,"Guilt",'Data (parsed)'!$C$2:$C$235,$A15) -> 0 | E15: =COUNTIFS('Data (parsed)'!$E$2:$E$235,E$14,'Data (parsed)'!$B$2:$B$235,"Guilt",'Data (parsed)'!$C$2:$C$235,$A15) -> 2 | F15: =SUMIFS('Data (parsed)'!$I$2:$I$235,'Data (parsed)'!$B$2:$B$235,"Guilt",'Data (parsed)'!$C$2:$C$235,$A15,'Data (parsed)'!$J$2:$J$235,0) -> 4 | G15: =SUMIFS('Data (parsed)'!$I$2:$I$235,'Data (parsed)'!$B$2:$B$235,"Guilt",'Data (parsed)'!$C$2:$C$235,$A15) -> 17
A16: Guilt as deed | B16: =COUNTIFS('Data (parsed)'!$E$2:$E$235,B$14,'Data (parsed)'!$B$2:$B$235,"Guilt",'Data (parsed)'!$C$2:$C$235,$A16) -> 4 | C16: =COUNTIFS('Data (parsed)'!$E$2:$E$235,C$14,'Data (parsed)'!$B$2:$B$235,"Guilt",'Data (parsed)'!$C$2:$C$235,$A16) -> 0 | D16: =COUNTIFS('Data (parsed)'!$E$2:$E$235,D$14,'Data (parsed)'!$B$2:$B$235,"Guilt",'Data (parsed)'!$C$2:$C$235,$A16) -> 0 | E16: =COUNTIFS('Data (parsed)'!$E$2:$E$235,E$14,'Data (parsed)'!$B$2:$B$235,"Guilt",'Data (parsed)'!$C$2:$C$235,$A16) -> 1 | F16: =SUMIFS('Data (parsed)'!$I$2:$I$235,'Data (parsed)'!$B$2:$B$235,"Guilt",'Data (parsed)'!$C$2:$C$235,$A16,'Data (parsed)'!$J$2:$J$235,0) -> 0 | G16: =SUMIFS('Data (parsed)'!$I$2:$I$235,'Data (parsed)'!$B$2:$B$235,"Guilt",'Data (parsed)'!$C$2:$C$235,$A16) -> 5
A17: Felt guilt (guilty pleasure) | B17: =COUNTIFS('Data (parsed)'!$E$2:$E$235,B$14,'Data (parsed)'!$B$2:$B$235,"Guilt",'Data (parsed)'!$C$2:$C$235,$A17) -> 2 | C17: =COUNTIFS('Data (parsed)'!$E$2:$E$235,C$14,'Data (parsed)'!$B$2:$B$235,"Guilt",'Data (parsed)'!$C$2:$C$235,$A17) -> 0 | D17: =COUNTIFS('Data (parsed)'!$E$2:$E$235,D$14,'Data (parsed)'!$B$2:$B$235,"Guilt",'Data (parsed)'!$C$2:$C$235,$A17) -> 0 | E17: =COUNTIFS('Data (parsed)'!$E$2:$E$235,E$14,'Data (parsed)'!$B$2:$B$235,"Guilt",'Data (parsed)'!$C$2:$C$235,$A17) -> 0 | F17: =SUMIFS('Data (parsed)'!$I$2:$I$235,'Data (parsed)'!$B$2:$B$235,"Guilt",'Data (parsed)'!$C$2:$C$235,$A17,'Data (parsed)'!$J$2:$J$235,0) -> 1 | G17: =SUMIFS('Data (parsed)'!$I$2:$I$235,'Data (parsed)'!$B$2:$B$235,"Guilt",'Data (parsed)'!$C$2:$C$235,$A17) -> 3
A18: Felt guilt (guilty conscience) | B18: =COUNTIFS('Data (parsed)'!$E$2:$E$235,B$14,'Data (parsed)'!$B$2:$B$235,"Guilt",'Data (parsed)'!$C$2:$C$235,$A18) -> 3 | C18: =COUNTIFS('Data (parsed)'!$E$2:$E$235,C$14,'Data (parsed)'!$B$2:$B$235,"Guilt",'Data (parsed)'!$C$2:$C$235,$A18) -> 0 | D18: =COUNTIFS('Data (parsed)'!$E$2:$E$235,D$14,'Data (parsed)'!$B$2:$B$235,"Guilt",'Data (parsed)'!$C$2:$C$235,$A18) -> 0 | E18: =COUNTIFS('Data (parsed)'!$E$2:$E$235,E$14,'Data (parsed)'!$B$2:$B$235,"Guilt",'Data (parsed)'!$C$2:$C$235,$A18) -> 0 | F18: =SUMIFS('Data (parsed)'!$I$2:$I$235,'Data (parsed)'!$B$2:$B$235,"Guilt",'Data (parsed)'!$C$2:$C$235,$A18,'Data (parsed)'!$J$2:$J$235,0) -> 0 | G18: =SUMIFS('Data (parsed)'!$I$2:$I$235,'Data (parsed)'!$B$2:$B$235,"Guilt",'Data (parsed)'!$C$2:$C$235,$A18) -> 3
A19: Guilt as tormentor | B19: =COUNTIFS('Data (parsed)'!$E$2:$E$235,B$14,'Data (parsed)'!$B$2:$B$235,"Guilt",'Data (parsed)'!$C$2:$C$235,$A19) -> 2 | C19: =COUNTIFS('Data (parsed)'!$E$2:$E$235,C$14,'Data (parsed)'!$B$2:$B$235,"Guilt",'Data (parsed)'!$C$2:$C$235,$A19) -> 0 | D19: =COUNTIFS('Data (parsed)'!$E$2:$E$235,D$14,'Data (parsed)'!$B$2:$B$235,"Guilt",'Data (parsed)'!$C$2:$C$235,$A19) -> 0 | E19: =COUNTIFS('Data (parsed)'!$E$2:$E$235,E$14,'Data (parsed)'!$B$2:$B$235,"Guilt",'Data (parsed)'!$C$2:$C$235,$A19) -> 0 | F19: =SUMIFS('Data (parsed)'!$I$2:$I$235,'Data (parsed)'!$B$2:$B$235,"Guilt",'Data (parsed)'!$C$2:$C$235,$A19,'Data (parsed)'!$J$2:$J$235,0) -> 0 | G19: =SUMIFS('Data (parsed)'!$I$2:$I$235,'Data (parsed)'!$B$2:$B$235,"Guilt",'Data (parsed)'!$C$2:$C$235,$A19) -> 2
A20: Guilt as weight | B20: =COUNTIFS('Data (parsed)'!$E$2:$E$235,B$14,'Data (parsed)'!$B$2:$B$235,"Guilt",'Data (parsed)'!$C$2:$C$235,$A20) -> 1 | C20: =COUNTIFS('Data (parsed)'!$E$2:$E$235,C$14,'Data (parsed)'!$B$2:$B$235,"Guilt",'Data (parsed)'!$C$2:$C$235,$A20) -> 0 | D20: =COUNTIFS('Data (parsed)'!$E$2:$E$235,D$14,'Data (parsed)'!$B$2:$B$235,"Guilt",'Data (parsed)'!$C$2:$C$235,$A20) -> 0 | E20: =COUNTIFS('Data (parsed)'!$E$2:$E$235,E$14,'Data (parsed)'!$B$2:$B$235,"Guilt",'Data (parsed)'!$C$2:$C$235,$A20) -> 0 | F20: =SUMIFS('Data (parsed)'!$I$2:$I$235,'Data (parsed)'!$B$2:$B$235,"Guilt",'Data (parsed)'!$C$2:$C$235,$A20,'Data (parsed)'!$J$2:$J$235,0) -> 0 | G20: =SUMIFS('Data (parsed)'!$I$2:$I$235,'Data (parsed)'!$B$2:$B$235,"Guilt",'Data (parsed)'!$C$2:$C$235,$A20) -> 1
A21: Total | B21: =SUM(B15:B20) -> 24 | C21: =SUM(C15:C20) -> 0 | D21: =SUM(D15:D20) -> 0 | E21: =SUM(E15:E20) -> 3 | F21: =SUM(F15:F20) -> 5 | G21: =SUM(G15:G20) -> 31

Sheet Conscience
A1: CONSCIENCE — 39 tokens
A3: Conscience: subtype × part of novel (arc)
A4: Subtype | B4: P1 | C4: P2 | D4: P3 | E4: P4 | F4: P5 | G4: Total
A5: Internal authority (advisor / opponent) | B5: =SUMIFS('Data (parsed)'!$I$2:$I$235,'Data (parsed)'!$B$2:$B$235,"Conscience",'Data (parsed)'!$C$2:$C$235,$A5,'Data (parsed)'!$D$2:$D$235,B$4) -> 1 | C5: =SUMIFS('Data (parsed)'!$I$2:$I$235,'Data (parsed)'!$B$2:$B$235,"Conscience",'Data (parsed)'!$C$2:$C$235,$A5,'Data (parsed)'!$D$2:$D$235,C$4) -> 2 | D5: =SUMIFS('Data (parsed)'!$I$2:$I$235,'Data (parsed)'!$B$2:$B$235,"Conscience",'Data (parsed)'!$C$2:$C$235,$A5,'Data (parsed)'!$D$2:$D$235,D$4) -> 0 | E5: =SUMIFS('Data (parsed)'!$I$2:$I$235,'Data (parsed)'!$B$2:$B$235,"Conscience",'Data (parsed)'!$C$2:$C$235,$A5,'Data (parsed)'!$D$2:$D$235,E$4) -> 4 | F5: =SUMIFS('Data (parsed)'!$I$2:$I$235,'Data (parsed)'!$B$2:$B$235,"Conscience",'Data (parsed)'!$C$2:$C$235,$A5,'Data (parsed)'!$D$2:$D$235,F$4) -> 2 | G5: =SUM(B5:F5) -> 9
A6: Absent reaction | B6: =SUMIFS('Data (parsed)'!$I$2:$I$235,'Data (parsed)'!$B$2:$B$235,"Conscience",'Data (parsed)'!$C$2:$C$235,$A6,'Data (parsed)'!$D$2:$D$235,B$4) -> 0 | C6: =SUMIFS('Data (parsed)'!$I$2:$I$235,'Data (parsed)'!$B$2:$B$235,"Conscience",'Data (parsed)'!$C$2:$C$235,$A6,'Data (parsed)'!$D$2:$D$235,C$4) -> 0 | D6: =SUMIFS('Data (parsed)'!$I$2:$I$235,'Data (parsed)'!$B$2:$B$235,"Conscience",'Data (parsed)'!$C$2:$C$235,$A6,'Data (parsed)'!$D$2:$D$235,D$4) -> 1 | E6: =SUMIFS('Data (parsed)'!$I$2:$I$235,'Data (parsed)'!$B$2:$B$235,"Conscience",'Data (parsed)'!$C$2:$C$235,$A6,'Data (parsed)'!$D$2:$D$235,E$4) -> 6 | F6: =SUMIFS('Data (parsed)'!$I$2:$I$235,'Data (parsed)'!$B$2:$B$235,"Conscience",'Data (parsed)'!$C$2:$C$235,$A6,'Data (parsed)'!$D$2:$D$235,F$4) -> 1 | G6: =SUM(B6:F6) -> 8
A7: Tormentor / punisher | B7: =SUMIFS('Data (parsed)'!$I$2:$I$235,'Data (parsed)'!$B$2:$B$235,"Conscience",'Data (parsed)'!$C$2:$C$235,$A7,'Data (parsed)'!$D$2:$D$235,B$4) -> 0 | C7: =SUMIFS('Data (parsed)'!$I$2:$I$235,'Data (parsed)'!$B$2:$B$235,"Conscience",'Data (parsed)'!$C$2:$C$235,$A7,'Data (parsed)'!$D$2:$D$235,C$4) -> 2 | D7: =SUMIFS('Data (parsed)'!$I$2:$I$235,'Data (parsed)'!$B$2:$B$235,"Conscience",'Data (parsed)'!$C$2:$C$235,$A7,'Data (parsed)'!$D$2:$D$235,D$4) -> 2 | E7: =SUMIFS('Data (parsed)'!$I$2:$I$235,'Data (parsed)'!$B$2:$B$235,"Conscience",'Data (parsed)'!$C$2:$C$235,$A7,'Data (parsed)'!$D$2:$D$235,E$4) -> 0 | F7: =SUMIFS('Data (parsed)'!$I$2:$I$235,'Data (parsed)'!$B$2:$B$235,"Conscience",'Data (parsed)'!$C$2:$C$235,$A7,'Data (parsed)'!$D$2:$D$235,F$4) -> 3 | G7: =SUM(B7:F7) -> 7
A8: Weight | B8: =SUMIFS('Data (parsed)'!$I$2:$I$235,'Data (parsed)'!$B$2:$B$235,"Conscience",'Data (parsed)'!$C$2:$C$235,$A8,'Data (parsed)'!$D$2:$D$235,B$4) -> 0 | C8: =SUMIFS('Data (parsed)'!$I$2:$I$235,'Data (parsed)'!$B$2:$B$235,"Conscience",'Data (parsed)'!$C$2:$C$235,$A8,'Data (parsed)'!$D$2:$D$235,C$4) -> 0 | D8: =SUMIFS('Data (parsed)'!$I$2:$I$235,'Data (parsed)'!$B$2:$B$235,"Conscience",'Data (parsed)'!$C$2:$C$235,$A8,'Data (parsed)'!$D$2:$D$235,D$4) -> 0 | E8: =SUMIFS('Data (parsed)'!$I$2:$I$235,'Data (parsed)'!$B$2:$B$235,"Conscience",'Data (parsed)'!$C$2:$C$235,$A8,'Data (parsed)'!$D$2:$D$235,E$4) -> 3 | F8: =SUMIFS('Data (parsed)'!$I$2:$I$235,'Data (parsed)'!$B$2:$B$235,"Conscience",'Data (parsed)'!$C$2:$C$235,$A8,'Data (parsed)'!$D$2:$D$235,F$4) -> 1 | G8: =SUM(B8:F8) -> 4
A9: Dormant / waking creature | B9: =SUMIFS('Data (parsed)'!$I$2:$I$235,'Data (parsed)'!$B$2:$B$235,"Conscience",'Data (parsed)'!$C$2:$C$235,$A9,'Data (parsed)'!$D$2:$D$235,B$4) -> 0 | C9: =SUMIFS('Data (parsed)'!$I$2:$I$235,'Data (parsed)'!$B$2:$B$235,"Conscience",'Data (parsed)'!$C$2:$C$235,$A9,'Data (parsed)'!$D$2:$D$235,C$4) -> 1 | D9: =SUMIFS('Data (parsed)'!$I$2:$I$235,'Data (parsed)'!$B$2:$B$235,"Conscience",'Data (parsed)'!$C$2:$C$235,$A9,'Data (parsed)'!$D$2:$D$235,D$4) -> 0 | E9: =SUMIFS('Data (parsed)'!$I$2:$I$235,'Data (parsed)'!$B$2:$B$235,"Conscience",'Data (parsed)'!$C$2:$C$235,$A9,'Data (parsed)'!$D$2:$D$235,E$4) -> 1 | F9: =SUMIFS('Data (parsed)'!$I$2:$I$235,'Data (parsed)'!$B$2:$B$235,"Conscience",'Data (parsed)'!$C$2:$C$235,$A9,'Data (parsed)'!$D$2:$D$235,F$4) -> 1 | G9: =SUM(B9:F9) -> 3
A10: General faculty | B10: =SUMIFS('Data (parsed)'!$I$2:$I$235,'Data (parsed)'!$B$2:$B$235,"Conscience",'Data (parsed)'!$C$2:$C$235,$A10,'Data (parsed)'!$D$2:$D$235,B$4) -> 0 | C10: =SUMIFS('Data (parsed)'!$I$2:$I$235,'Data (parsed)'!$B$2:$B$235,"Conscience",'Data (parsed)'!$C$2:$C$235,$A10,'Data (parsed)'!$D$2:$D$235,C$4) -> 0 | D10: =SUMIFS('Data (parsed)'!$I$2:$I$235,'Data (parsed)'!$B$2:$B$235,"Conscience",'Data (parsed)'!$C$2:$C$235,$A10,'Data (parsed)'!$D$2:$D$235,D$4) -> 0 | E10: =SUMIFS('Data (parsed)'!$I$2:$I$235,'Data (parsed)'!$B$2:$B$235,"Conscience",'Data (parsed)'!$C$2:$C$235,$A10,'Data (parsed)'!$D$2:$D$235,E$4) -> 2 | F10: =SUMIFS('Data (parsed)'!$I$2:$I$235,'Data (parsed)'!$B$2:$B$235,"Conscience",'Data (parsed)'!$C$2:$C$235,$A10,'Data (parsed)'!$D$2:$D$235,F$4) -> 0 | G10: =SUM(B10:F10) -> 2
A11: Pained body part | B11: =SUMIFS('Data (parsed)'!$I$2:$I$235,'Data (parsed)'!$B$2:$B$235,"Conscience",'Data (parsed)'!$C$2:$C$235,$A11,'Data (parsed)'!$D$2:$D$235,B$4) -> 1 | C11: =SUMIFS('Data (parsed)'!$I$2:$I$235,'Data (parsed)'!$B$2:$B$235,"Conscience",'Data (parsed)'!$C$2:$C$235,$A11,'Data (parsed)'!$D$2:$D$235,C$4) -> 1 | D11: =SUMIFS('Data (parsed)'!$I$2:$I$235,'Data (parsed)'!$B$2:$B$235,"Conscience",'Data (parsed)'!$C$2:$C$235,$A11,'Data (parsed)'!$D$2:$D$235,D$4) -> 0 | E11: =SUMIFS('Data (parsed)'!$I$2:$I$235,'Data (parsed)'!$B$2:$B$235,"Conscience",'Data (parsed)'!$C$2:$C$235,$A11,'Data (parsed)'!$D$2:$D$235,E$4) -> 0 | F11: =SUMIFS('Data (parsed)'!$I$2:$I$235,'Data (parsed)'!$B$2:$B$235,"Conscience",'Data (parsed)'!$C$2:$C$235,$A11,'Data (parsed)'!$D$2:$D$235,F$4) -> 0 | G11: =SUM(B11:F11) -> 2
A12: Object (stretchable) | B12: =SUMIFS('Data (parsed)'!$I$2:$I$235,'Data (parsed)'!$B$2:$B$235,"Conscience",'Data (parsed)'!$C$2:$C$235,$A12,'Data (parsed)'!$D$2:$D$235,B$4) -> 0 | C12: =SUMIFS('Data (parsed)'!$I$2:$I$235,'Data (parsed)'!$B$2:$B$235,"Conscience",'Data (parsed)'!$C$2:$C$235,$A12,'Data (parsed)'!$D$2:$D$235,C$4) -> 0 | D12: =SUMIFS('Data (parsed)'!$I$2:$I$235,'Data (parsed)'!$B$2:$B$235,"Conscience",'Data (parsed)'!$C$2:$C$235,$A12,'Data (parsed)'!$D$2:$D$235,D$4) -> 1 | E12: =SUMIFS('Data (parsed)'!$I$2:$I$235,'Data (parsed)'!$B$2:$B$235,"Conscience",'Data (parsed)'!$C$2:$C$235,$A12,'Data (parsed)'!$D$2:$D$235,E$4) -> 0 | F12: =SUMIFS('Data (parsed)'!$I$2:$I$235,'Data (parsed)'!$B$2:$B$235,"Conscience",'Data (parsed)'!$C$2:$C$235,$A12,'Data (parsed)'!$D$2:$D$235,F$4) -> 0 | G12: =SUM(B12:F12) -> 1
A13: Resource | B13: =SUMIFS('Data (parsed)'!$I$2:$I$235,'Data (parsed)'!$B$2:$B$235,"Conscience",'Data (parsed)'!$C$2:$C$235,$A13,'Data (parsed)'!$D$2:$D$235,B$4) -> 0 | C13: =SUMIFS('Data (parsed)'!$I$2:$I$235,'Data (parsed)'!$B$2:$B$235,"Conscience",'Data (parsed)'!$C$2:$C$235,$A13,'Data (parsed)'!$D$2:$D$235,C$4) -> 0 | D13: =SUMIFS('Data (parsed)'!$I$2:$I$235,'Data (parsed)'!$B$2:$B$235,"Conscience",'Data (parsed)'!$C$2:$C$235,$A13,'Data (parsed)'!$D$2:$D$235,D$4) -> 0 | E13: =SUMIFS('Data (parsed)'!$I$2:$I$235,'Data (parsed)'!$B$2:$B$235,"Conscience",'Data (parsed)'!$C$2:$C$235,$A13,'Data (parsed)'!$D$2:$D$235,E$4) -> 1 | F13: =SUMIFS('Data (parsed)'!$I$2:$I$235,'Data (parsed)'!$B$2:$B$235,"Conscience",'Data (parsed)'!$C$2:$C$235,$A13,'Data (parsed)'!$D$2:$D$235,F$4) -> 0 | G13: =SUM(B13:F13) -> 1
A14: Object (clean / unclean) | B14: =SUMIFS('Data (parsed)'!$I$2:$I$235,'Data (parsed)'!$B$2:$B$235,"Conscience",'Data (parsed)'!$C$2:$C$235,$A14,'Data (parsed)'!$D$2:$D$235,B$4) -> 1 | C14: =SUMIFS('Data (parsed)'!$I$2:$I$235,'Data (parsed)'!$B$2:$B$235,"Conscience",'Data (parsed)'!$C$2:$C$235,$A14,'Data (parsed)'!$D$2:$D$235,C$4) -> 0 | D14: =SUMIFS('Data (parsed)'!$I$2:$I$235,'Data (parsed)'!$B$2:$B$235,"Conscience",'Data (parsed)'!$C$2:$C$235,$A14,'Data (parsed)'!$D$2:$D$235,D$4) -> 0 | E14: =SUMIFS('Data (parsed)'!$I$2:$I$235,'Data (parsed)'!$B$2:$B$235,"Conscience",'Data (parsed)'!$C$2:$C$235,$A14,'Data (parsed)'!$D$2:$D$235,E$4) -> 0 | F14: =SUMIFS('Data (parsed)'!$I$2:$I$235,'Data (parsed)'!$B$2:$B$235,"Conscience",'Data (parsed)'!$C$2:$C$235,$A14,'Data (parsed)'!$D$2:$D$235,F$4) -> 0 | G14: =SUM(B14:F14) -> 1
A15: Internal authority (judge) | B15: =SUMIFS('Data (parsed)'!$I$2:$I$235,'Data (parsed)'!$B$2:$B$235,"Conscience",'Data (parsed)'!$C$2:$C$235,$A15,'Data (parsed)'!$D$2:$D$235,B$4) -> 0 | C15: =SUMIFS('Data (parsed)'!$I$2:$I$235,'Data (parsed)'!$B$2:$B$235,"Conscience",'Data (parsed)'!$C$2:$C$235,$A15,'Data (parsed)'!$D$2:$D$235,C$4) -> 0 | D15: =SUMIFS('Data (parsed)'!$I$2:$I$235,'Data (parsed)'!$B$2:$B$235,"Conscience",'Data (parsed)'!$C$2:$C$235,$A15,'Data (parsed)'!$D$2:$D$235,D$4) -> 1 | E15: =SUMIFS('Data (parsed)'!$I$2:$I$235,'Data (parsed)'!$B$2:$B$235,"Conscience",'Data (parsed)'!$C$2:$C$235,$A15,'Data (parsed)'!$D$2:$D$235,E$4) -> 0 | F15: =SUMIFS('Data (parsed)'!$I$2:$I$235,'Data (parsed)'!$B$2:$B$235,"Conscience",'Data (parsed)'!$C$2:$C$235,$A15,'Data (parsed)'!$D$2:$D$235,F$4) -> 0 | G15: =SUM(B15:F15) -> 1
A16: Total | B16: =SUM(B5:B15) -> 3 | C16: =SUM(C5:C15) -> 6 | D16: =SUM(D5:D15) -> 5 | E16: =SUM(E5:E15) -> 17 | F16: =SUM(F5:F15) -> 8 | G16: =SUM(G5:G15) -> 39
A18: Conscience: subtype × character (dual tokens counted under each principal; Tokens = distinct count)
A19: Subtype | B19: Scarlett | C19: Ashley | D19: Rhett | E19: Melanie | F19: Other | G19: Tokens
A20: Internal authority (advisor / opponent) | B20: =COUNTIFS('Data (parsed)'!$E$2:$E$235,B$19,'Data (parsed)'!$B$2:$B$235,"Conscience",'Data (parsed)'!$C$2:$C$235,$A20) -> 6 | C20: =COUNTIFS('Data (parsed)'!$E$2:$E$235,C$19,'Data (parsed)'!$B$2:$B$235,"Conscience",'Data (parsed)'!$C$2:$C$235,$A20) -> 0 | D20: =COUNTIFS('Data (parsed)'!$E$2:$E$235,D$19,'Data (parsed)'!$B$2:$B$235,"Conscience",'Data (parsed)'!$C$2:$C$235,$A20) -> 0 | E20: =COUNTIFS('Data (parsed)'!$E$2:$E$235,E$19,'Data (parsed)'!$B$2:$B$235,"Conscience",'Data (parsed)'!$C$2:$C$235,$A20) -> 0 | F20: =SUMIFS('Data (parsed)'!$I$2:$I$235,'Data (parsed)'!$B$2:$B$235,"Conscience",'Data (parsed)'!$C$2:$C$235,$A20,'Data (parsed)'!$J$2:$J$235,0) -> 3 | G20: =SUMIFS('Data (parsed)'!$I$2:$I$235,'Data (parsed)'!$B$2:$B$235,"Conscience",'Data (parsed)'!$C$2:$C$235,$A20) -> 9
A21: Absent reaction | B21: =COUNTIFS('Data (parsed)'!$E$2:$E$235,B$19,'Data (parsed)'!$B$2:$B$235,"Conscience",'Data (parsed)'!$C$2:$C$235,$A21) -> 5 | C21: =COUNTIFS('Data (parsed)'!$E$2:$E$235,C$19,'Data (parsed)'!$B$2:$B$235,"Conscience",'Data (parsed)'!$C$2:$C$235,$A21) -> 0 | D21: =COUNTIFS('Data (parsed)'!$E$2:$E$235,D$19,'Data (parsed)'!$B$2:$B$235,"Conscience",'Data (parsed)'!$C$2:$C$235,$A21) -> 2 | E21: =COUNTIFS('Data (parsed)'!$E$2:$E$235,E$19,'Data (parsed)'!$B$2:$B$235,"Conscience",'Data (parsed)'!$C$2:$C$235,$A21) -> 0 | F21: =SUMIFS('Data (parsed)'!$I$2:$I$235,'Data (parsed)'!$B$2:$B$235,"Conscience",'Data (parsed)'!$C$2:$C$235,$A21,'Data (parsed)'!$J$2:$J$235,0) -> 1 | G21: =SUMIFS('Data (parsed)'!$I$2:$I$235,'Data (parsed)'!$B$2:$B$235,"Conscience",'Data (parsed)'!$C$2:$C$235,$A21) -> 8
A22: Tormentor / punisher | B22: =COUNTIFS('Data (parsed)'!$E$2:$E$235,B$19,'Data (parsed)'!$B$2:$B$235,"Conscience",'Data (parsed)'!$C$2:$C$235,$A22) -> 6 | C22: =COUNTIFS('Data (parsed)'!$E$2:$E$235,C$19,'Data (parsed)'!$B$2:$B$235,"Conscience",'Data (parsed)'!$C$2:$C$235,$A22) -> 0 | D22: =COUNTIFS('Data (parsed)'!$E$2:$E$235,D$19,'Data (parsed)'!$B$2:$B$235,"Conscience",'Data (parsed)'!$C$2:$C$235,$A22) -> 0 | E22: =COUNTIFS('Data (parsed)'!$E$2:$E$235,E$19,'Data (parsed)'!$B$2:$B$235,"Conscience",'Data (parsed)'!$C$2:$C$235,$A22) -> 1 | F22: =SUMIFS('Data (parsed)'!$I$2:$I$235,'Data (parsed)'!$B$2:$B$235,"Conscience",'Data (parsed)'!$C$2:$C$235,$A22,'Data (parsed)'!$J$2:$J$235,0) -> 0 | G22: =SUMIFS('Data (parsed)'!$I$2:$I$235,'Data (parsed)'!$B$2:$B$235,"Conscience",'Data (parsed)'!$C$2:$C$235,$A22) -> 7
A23: Weight | B23: =COUNTIFS('Data (parsed)'!$E$2:$E$235,B$19,'Data (parsed)'!$B$2:$B$235,"Conscience",'Data (parsed)'!$C$2:$C$235,$A23) -> 3 | C23: =COUNTIFS('Data (parsed)'!$E$2:$E$235,C$19,'Data (parsed)'!$B$2:$B$235,"Conscience",'Data (parsed)'!$C$2:$C$235,$A23) -> 0 | D23: =COUNTIFS('Data (parsed)'!$E$2:$E$235,D$19,'Data (parsed)'!$B$2:$B$235,"Conscience",'Data (parsed)'!$C$2:$C$235,$A23) -> 0 | E23: =COUNTIFS('Data (parsed)'!$E$2:$E$235,E$19,'Data (parsed)'!$B$2:$B$235,"Conscience",'Data (parsed)'!$C$2:$C$235,$A23) -> 0 | F23: =SUMIFS('Data (parsed)'!$I$2:$I$235,'Data (parsed)'!$B$2:$B$235,"Conscience",'Data (parsed)'!$C$2:$C$235,$A23,'Data (parsed)'!$J$2:$J$235,0) -> 1 | G23: =SUMIFS('Data (parsed)'!$I$2:$I$235,'Data (parsed)'!$B$2:$B$235,"Conscience",'Data (parsed)'!$C$2:$C$235,$A23) -> 4
A24: Dormant / waking creature | B24: =COUNTIFS('Data (parsed)'!$E$2:$E$235,B$19,'Data (parsed)'!$B$2:$B$235,"Conscience",'Data (parsed)'!$C$2:$C$235,$A24) -> 3 | C24: =COUNTIFS('Data (parsed)'!$E$2:$E$235,C$19,'Data (parsed)'!$B$2:$B$235,"Conscience",'Data (parsed)'!$C$2:$C$235,$A24) -> 0 | D24: =COUNTIFS('Data (parsed)'!$E$2:$E$235,D$19,'Data (parsed)'!$B$2:$B$235,"Conscience",'Data (parsed)'!$C$2:$C$235,$A24) -> 0 | E24: =COUNTIFS('Data (parsed)'!$E$2:$E$235,E$19,'Data (parsed)'!$B$2:$B$235,"Conscience",'Data (parsed)'!$C$2:$C$235,$A24) -> 0 | F24: =SUMIFS('Data (parsed)'!$I$2:$I$235,'Data (parsed)'!$B$2:$B$235,"Conscience",'Data (parsed)'!$C$2:$C$235,$A24,'Data (parsed)'!$J$2:$J$235,0) -> 0 | G24: =SUMIFS('Data (parsed)'!$I$2:$I$235,'Data (parsed)'!$B$2:$B$235,"Conscience",'Data (parsed)'!$C$2:$C$235,$A24) -> 3
A25: General faculty | B25: =COUNTIFS('Data (parsed)'!$E$2:$E$235,B$19,'Data (parsed)'!$B$2:$B$235,"Conscience",'Data (parsed)'!$C$2:$C$235,$A25) -> 2 | C25: =COUNTIFS('Data (parsed)'!$E$2:$E$235,C$19,'Data (parsed)'!$B$2:$B$235,"Conscience",'Data (parsed)'!$C$2:$C$235,$A25) -> 0 | D25: =COUNTIFS('Data (parsed)'!$E$2:$E$235,D$19,'Data (parsed)'!$B$2:$B$235,"Conscience",'Data (parsed)'!$C$2:$C$235,$A25) -> 0 | E25: =COUNTIFS('Data (parsed)'!$E$2:$E$235,E$19,'Data (parsed)'!$B$2:$B$235,"Conscience",'Data (parsed)'!$C$2:$C$235,$A25) -> 0 | F25: =SUMIFS('Data (parsed)'!$I$2:$I$235,'Data (parsed)'!$B$2:$B$235,"Conscience",'Data (parsed)'!$C$2:$C$235,$A25,'Data (parsed)'!$J$2:$J$235,0) -> 0 | G25: =SUMIFS('Data (parsed)'!$I$2:$I$235,'Data (parsed)'!$B$2:$B$235,"Conscience",'Data (parsed)'!$C$2:$C$235,$A25) -> 2
A26: Pained body part | B26: =COUNTIFS('Data (parsed)'!$E$2:$E$235,B$19,'Data (parsed)'!$B$2:$B$235,"Conscience",'Data (parsed)'!$C$2:$C$235,$A26) -> 2 | C26: =COUNTIFS('Data (parsed)'!$E$2:$E$235,C$19,'Data (parsed)'!$B$2:$B$235,"Conscience",'Data (parsed)'!$C$2:$C$235,$A26) -> 0 | D26: =COUNTIFS('Data (parsed)'!$E$2:$E$235,D$19,'Data (parsed)'!$B$2:$B$235,"Conscience",'Data (parsed)'!$C$2:$C$235,$A26) -> 0 | E26: =COUNTIFS('Data (parsed)'!$E$2:$E$235,E$19,'Data (parsed)'!$B$2:$B$235,"Conscience",'Data (parsed)'!$C$2:$C$235,$A26) -> 0 | F26: =SUMIFS('Data (parsed)'!$I$2:$I$235,'Data (parsed)'!$B$2:$B$235,"Conscience",'Data (parsed)'!$C$2:$C$235,$A26,'Data (parsed)'!$J$2:$J$235,0) -> 0 | G26: =SUMIFS('Data (parsed)'!$I$2:$I$235,'Data (parsed)'!$B$2:$B$235,"Conscience",'Data (parsed)'!$C$2:$C$235,$A26) -> 2
A27: Object (stretchable) | B27: =COUNTIFS('Data (parsed)'!$E$2:$E$235,B$19,'Data (parsed)'!$B$2:$B$235,"Conscience",'Data (parsed)'!$C$2:$C$235,$A27) -> 1 | C27: =COUNTIFS('Data (parsed)'!$E$2:$E$235,C$19,'Data (parsed)'!$B$2:$B$235,"Conscience",'Data (parsed)'!$C$2:$C$235,$A27) -> 0 | D27: =COUNTIFS('Data (parsed)'!$E$2:$E$235,D$19,'Data (parsed)'!$B$2:$B$235,"Conscience",'Data (parsed)'!$C$2:$C$235,$A27) -> 0 | E27: =COUNTIFS('Data (parsed)'!$E$2:$E$235,E$19,'Data (parsed)'!$B$2:$B$235,"Conscience",'Data (parsed)'!$C$2:$C$235,$A27) -> 0 | F27: =SUMIFS('Data (parsed)'!$I$2:$I$235,'Data (parsed)'!$B$2:$B$235,"Conscience",'Data (parsed)'!$C$2:$C$235,$A27,'Data (parsed)'!$J$2:$J$235,0) -> 0 | G27: =SUMIFS('Data (parsed)'!$I$2:$I$235,'Data (parsed)'!$B$2:$B$235,"Conscience",'Data (parsed)'!$C$2:$C$235,$A27) -> 1
A28: Resource | B28: =COUNTIFS('Data (parsed)'!$E$2:$E$235,B$19,'Data (parsed)'!$B$2:$B$235,"Conscience",'Data (parsed)'!$C$2:$C$235,$A28) -> 1 | C28: =COUNTIFS('Data (parsed)'!$E$2:$E$235,C$19,'Data (parsed)'!$B$2:$B$235,"Conscience",'Data (parsed)'!$C$2:$C$235,$A28) -> 0 | D28: =COUNTIFS('Data (parsed)'!$E$2:$E$235,D$19,'Data (parsed)'!$B$2:$B$235,"Conscience",'Data (parsed)'!$C$2:$C$235,$A28) -> 0 | E28: =COUNTIFS('Data (parsed)'!$E$2:$E$235,E$19,'Data (parsed)'!$B$2:$B$235,"Conscience",'Data (parsed)'!$C$2:$C$235,$A28) -> 0 | F28: =SUMIFS('Data (parsed)'!$I$2:$I$235,'Data (parsed)'!$B$2:$B$235,"Conscience",'Data (parsed)'!$C$2:$C$235,$A28,'Data (parsed)'!$J$2:$J$235,0) -> 0 | G28: =SUMIFS('Data (parsed)'!$I$2:$I$235,'Data (parsed)'!$B$2:$B$235,"Conscience",'Data (parsed)'!$C$2:$C$235,$A28) -> 1
A29: Object (clean / unclean) | B29: =COUNTIFS('Data (parsed)'!$E$2:$E$235,B$19,'Data (parsed)'!$B$2:$B$235,"Conscience",'Data (parsed)'!$C$2:$C$235,$A29) -> 1 | C29: =COUNTIFS('Data (parsed)'!$E$2:$E$235,C$19,'Data (parsed)'!$B$2:$B$235,"Conscience",'Data (parsed)'!$C$2:$C$235,$A29) -> 0 | D29: =COUNTIFS('Data (parsed)'!$E$2:$E$235,D$19,'Data (parsed)'!$B$2:$B$235,"Conscience",'Data (parsed)'!$C$2:$C$235,$A29) -> 0 | E29: =COUNTIFS('Data (parsed)'!$E$2:$E$235,E$19,'Data (parsed)'!$B$2:$B$235,"Conscience",'Data (parsed)'!$C$2:$C$235,$A29) -> 0 | F29: =SUMIFS('Data (parsed)'!$I$2:$I$235,'Data (parsed)'!$B$2:$B$235,"Conscience",'Data (parsed)'!$C$2:$C$235,$A29,'Data (parsed)'!$J$2:$J$235,0) -> 0 | G29: =SUMIFS('Data (parsed)'!$I$2:$I$235,'Data (parsed)'!$B$2:$B$235,"Conscience",'Data (parsed)'!$C$2:$C$235,$A29) -> 1
A30: Internal authority (judge) | B30: =COUNTIFS('Data (parsed)'!$E$2:$E$235,B$19,'Data (parsed)'!$B$2:$B$235,"Conscience",'Data (parsed)'!$C$2:$C$235,$A30) -> 1 | C30: =COUNTIFS('Data (parsed)'!$E$2:$E$235,C$19,'Data (parsed)'!$B$2:$B$235,"Conscience",'Data (parsed)'!$C$2:$C$235,$A30) -> 0 | D30: =COUNTIFS('Data (parsed)'!$E$2:$E$235,D$19,'Data (parsed)'!$B$2:$B$235,"Conscience",'Data (parsed)'!$C$2:$C$235,$A30) -> 0 | E30: =COUNTIFS('Data (parsed)'!$E$2:$E$235,E$19,'Data (parsed)'!$B$2:$B$235,"Conscience",'Data (parsed)'!$C$2:$C$235,$A30) -> 0 | F30: =SUMIFS('Data (parsed)'!$I$2:$I$235,'Data (parsed)'!$B$2:$B$235,"Conscience",'Data (parsed)'!$C$2:$C$235,$A30,'Data (parsed)'!$J$2:$J$235,0) -> 0 | G30: =SUMIFS('Data (parsed)'!$I$2:$I$235,'Data (parsed)'!$B$2:$B$235,"Conscience",'Data (parsed)'!$C$2:$C$235,$A30) -> 1
A31: Total | B31: =SUM(B20:B30) -> 31 | C31: =SUM(C20:C30) -> 0 | D31: =SUM(D20:D30) -> 2 | E31: =SUM(E20:E30) -> 1 | F31: =SUM(F20:F30) -> 5 | G31: =SUM(G20:G30) -> 39

Sheet Honor
A1: HONOR — 57 tokens
A3: Honor: subtype × part of novel (arc)
A4: Subtype | B4: P1 | C4: P2 | D4: P3 | E4: P4 | F4: P5 | G4: Total
A5: Moral code | B5: =SUMIFS('Data (parsed)'!$I$2:$I$235,'Data (parsed)'!$B$2:$B$235,"Honor",'Data (parsed)'!$C$2:$C$235,$A5,'Data (parsed)'!$D$2:$D$235,B$4) -> 0 | C5: =SUMIFS('Data (parsed)'!$I$2:$I$235,'Data (parsed)'!$B$2:$B$235,"Honor",'Data (parsed)'!$C$2:$C$235,$A5,'Data (parsed)'!$D$2:$D$235,C$4) -> 1 | D5: =SUMIFS('Data (parsed)'!$I$2:$I$235,'Data (parsed)'!$B$2:$B$235,"Honor",'Data (parsed)'!$C$2:$C$235,$A5,'Data (parsed)'!$D$2:$D$235,D$4) -> 2 | E5: =SUMIFS('Data (parsed)'!$I$2:$I$235,'Data (parsed)'!$B$2:$B$235,"Honor",'Data (parsed)'!$C$2:$C$235,$A5,'Data (parsed)'!$D$2:$D$235,E$4) -> 17 | F5: =SUMIFS('Data (parsed)'!$I$2:$I$235,'Data (parsed)'!$B$2:$B$235,"Honor",'Data (parsed)'!$C$2:$C$235,$A5,'Data (parsed)'!$D$2:$D$235,F$4) -> 7 | G5: =SUM(B5:F5) -> 27
A6: Reputation / standing | B6: =SUMIFS('Data (parsed)'!$I$2:$I$235,'Data (parsed)'!$B$2:$B$235,"Honor",'Data (parsed)'!$C$2:$C$235,$A6,'Data (parsed)'!$D$2:$D$235,B$4) -> 2 | C6: =SUMIFS('Data (parsed)'!$I$2:$I$235,'Data (parsed)'!$B$2:$B$235,"Honor",'Data (parsed)'!$C$2:$C$235,$A6,'Data (parsed)'!$D$2:$D$235,C$4) -> 1 | D6: =SUMIFS('Data (parsed)'!$I$2:$I$235,'Data (parsed)'!$B$2:$B$235,"Honor",'Data (parsed)'!$C$2:$C$235,$A6,'Data (parsed)'!$D$2:$D$235,D$4) -> 0 | E6: =SUMIFS('Data (parsed)'!$I$2:$I$235,'Data (parsed)'!$B$2:$B$235,"Honor",'Data (parsed)'!$C$2:$C$235,$A6,'Data (parsed)'!$D$2:$D$235,E$4) -> 5 | F6: =SUMIFS('Data (parsed)'!$I$2:$I$235,'Data (parsed)'!$B$2:$B$235,"Honor",'Data (parsed)'!$C$2:$C$235,$A6,'Data (parsed)'!$D$2:$D$235,F$4) -> 3 | G6: =SUM(B6:F6) -> 11
A7: Tribute / glory | B7: =SUMIFS('Data (parsed)'!$I$2:$I$235,'Data (parsed)'!$B$2:$B$235,"Honor",'Data (parsed)'!$C$2:$C$235,$A7,'Data (parsed)'!$D$2:$D$235,B$4) -> 3 | C7: =SUMIFS('Data (parsed)'!$I$2:$I$235,'Data (parsed)'!$B$2:$B$235,"Honor",'Data (parsed)'!$C$2:$C$235,$A7,'Data (parsed)'!$D$2:$D$235,C$4) -> 2 | D7: =SUMIFS('Data (parsed)'!$I$2:$I$235,'Data (parsed)'!$B$2:$B$235,"Honor",'Data (parsed)'!$C$2:$C$235,$A7,'Data (parsed)'!$D$2:$D$235,D$4) -> 0 | E7: =SUMIFS('Data (parsed)'!$I$2:$I$235,'Data (parsed)'!$B$2:$B$235,"Honor",'Data (parsed)'!$C$2:$C$235,$A7,'Data (parsed)'!$D$2:$D$235,E$4) -> 1 | F7: =SUMIFS('Data (parsed)'!$I$2:$I$235,'Data (parsed)'!$B$2:$B$235,"Honor",'Data (parsed)'!$C$2:$C$235,$A7,'Data (parsed)'!$D$2:$D$235,F$4) -> 0 | G7: =SUM(B7:F7) -> 6
A8: Ironic / mocked | B8: =SUMIFS('Data (parsed)'!$I$2:$I$235,'Data (parsed)'!$B$2:$B$235,"Honor",'Data (parsed)'!$C$2:$C$235,$A8,'Data (parsed)'!$D$2:$D$235,B$4) -> 0 | C8: =SUMIFS('Data (parsed)'!$I$2:$I$235,'Data (parsed)'!$B$2:$B$235,"Honor",'Data (parsed)'!$C$2:$C$235,$A8,'Data (parsed)'!$D$2:$D$235,C$4) -> 1 | D8: =SUMIFS('Data (parsed)'!$I$2:$I$235,'Data (parsed)'!$B$2:$B$235,"Honor",'Data (parsed)'!$C$2:$C$235,$A8,'Data (parsed)'!$D$2:$D$235,D$4) -> 0 | E8: =SUMIFS('Data (parsed)'!$I$2:$I$235,'Data (parsed)'!$B$2:$B$235,"Honor",'Data (parsed)'!$C$2:$C$235,$A8,'Data (parsed)'!$D$2:$D$235,E$4) -> 4 | F8: =SUMIFS('Data (parsed)'!$I$2:$I$235,'Data (parsed)'!$B$2:$B$235,"Honor",'Data (parsed)'!$C$2:$C$235,$A8,'Data (parsed)'!$D$2:$D$235,F$4) -> 0 | G8: =SUM(B8:F8) -> 5
A9: Absent / dishonor | B9: =SUMIFS('Data (parsed)'!$I$2:$I$235,'Data (parsed)'!$B$2:$B$235,"Honor",'Data (parsed)'!$C$2:$C$235,$A9,'Data (parsed)'!$D$2:$D$235,B$4) -> 1 | C9: =SUMIFS('Data (parsed)'!$I$2:$I$235,'Data (parsed)'!$B$2:$B$235,"Honor",'Data (parsed)'!$C$2:$C$235,$A9,'Data (parsed)'!$D$2:$D$235,C$4) -> 0 | D9: =SUMIFS('Data (parsed)'!$I$2:$I$235,'Data (parsed)'!$B$2:$B$235,"Honor",'Data (parsed)'!$C$2:$C$235,$A9,'Data (parsed)'!$D$2:$D$235,D$4) -> 0 | E9: =SUMIFS('Data (parsed)'!$I$2:$I$235,'Data (parsed)'!$B$2:$B$235,"Honor",'Data (parsed)'!$C$2:$C$235,$A9,'Data (parsed)'!$D$2:$D$235,E$4) -> 2 | F9: =SUMIFS('Data (parsed)'!$I$2:$I$235,'Data (parsed)'!$B$2:$B$235,"Honor",'Data (parsed)'!$C$2:$C$235,$A9,'Data (parsed)'!$D$2:$D$235,F$4) -> 2 | G9: =SUM(B9:F9) -> 5
A10: Undifferentiated honor | B10: =SUMIFS('Data (parsed)'!$I$2:$I$235,'Data (parsed)'!$B$2:$B$235,"Honor",'Data (parsed)'!$C$2:$C$235,$A10,'Data (parsed)'!$D$2:$D$235,B$4) -> 0 | C10: =SUMIFS('Data (parsed)'!$I$2:$I$235,'Data (parsed)'!$B$2:$B$235,"Honor",'Data (parsed)'!$C$2:$C$235,$A10,'Data (parsed)'!$D$2:$D$235,C$4) -> 0 | D10: =SUMIFS('Data (parsed)'!$I$2:$I$235,'Data (parsed)'!$B$2:$B$235,"Honor",'Data (parsed)'!$C$2:$C$235,$A10,'Data (parsed)'!$D$2:$D$235,D$4) -> 0 | E10: =SUMIFS('Data (parsed)'!$I$2:$I$235,'Data (parsed)'!$B$2:$B$235,"Honor",'Data (parsed)'!$C$2:$C$235,$A10,'Data (parsed)'!$D$2:$D$235,E$4) -> 2 | F10: =SUMIFS('Data (parsed)'!$I$2:$I$235,'Data (parsed)'!$B$2:$B$235,"Honor",'Data (parsed)'!$C$2:$C$235,$A10,'Data (parsed)'!$D$2:$D$235,F$4) -> 0 | G10: =SUM(B10:F10) -> 2
A11: Nobility of character | B11: =SUMIFS('Data (parsed)'!$I$2:$I$235,'Data (parsed)'!$B$2:$B$235,"Honor",'Data (parsed)'!$C$2:$C$235,$A11,'Data (parsed)'!$D$2:$D$235,B$4) -> 0 | C11: =SUMIFS('Data (parsed)'!$I$2:$I$235,'Data (parsed)'!$B$2:$B$235,"Honor",'Data (parsed)'!$C$2:$C$235,$A11,'Data (parsed)'!$D$2:$D$235,C$4) -> 0 | D11: =SUMIFS('Data (parsed)'!$I$2:$I$235,'Data (parsed)'!$B$2:$B$235,"Honor",'Data (parsed)'!$C$2:$C$235,$A11,'Data (parsed)'!$D$2:$D$235,D$4) -> 0 | E11: =SUMIFS('Data (parsed)'!$I$2:$I$235,'Data (parsed)'!$B$2:$B$235,"Honor",'Data (parsed)'!$C$2:$C$235,$A11,'Data (parsed)'!$D$2:$D$235,E$4) -> 0 | F11: =SUMIFS('Data (parsed)'!$I$2:$I$235,'Data (parsed)'!$B$2:$B$235,"Honor",'Data (parsed)'!$C$2:$C$235,$A11,'Data (parsed)'!$D$2:$D$235,F$4) -> 1 | G11: =SUM(B11:F11) -> 1
A12: Total | B12: =SUM(B5:B11) -> 6 | C12: =SUM(C5:C11) -> 5 | D12: =SUM(D5:D11) -> 2 | E12: =SUM(E5:E11) -> 31 | F12: =SUM(F5:F11) -> 13 | G12: =SUM(G5:G11) -> 57
A14: Honor: subtype × character (dual tokens counted under each principal; Tokens = distinct count)
A15: Subtype | B15: Scarlett | C15: Ashley | D15: Rhett | E15: Melanie | F15: Other | G15: Tokens
A16: Moral code | B16: =COUNTIFS('Data (parsed)'!$E$2:$E$235,B$15,'Data (parsed)'!$B$2:$B$235,"Honor",'Data (parsed)'!$C$2:$C$235,$A16) -> 6 | C16: =COUNTIFS('Data (parsed)'!$E$2:$E$235,C$15,'Data (parsed)'!$B$2:$B$235,"Honor",'Data (parsed)'!$C$2:$C$235,$A16) -> 18 | D16: =COUNTIFS('Data (parsed)'!$E$2:$E$235,D$15,'Data (parsed)'!$B$2:$B$235,"Honor",'Data (parsed)'!$C$2:$C$235,$A16) -> 2 | E16: =COUNTIFS('Data (parsed)'!$E$2:$E$235,E$15,'Data (parsed)'!$B$2:$B$235,"Honor",'Data (parsed)'!$C$2:$C$235,$A16) -> 0 | F16: =SUMIFS('Data (parsed)'!$I$2:$I$235,'Data (parsed)'!$B$2:$B$235,"Honor",'Data (parsed)'!$C$2:$C$235,$A16,'Data (parsed)'!$J$2:$J$235,0) -> 1 | G16: =SUMIFS('Data (parsed)'!$I$2:$I$235,'Data (parsed)'!$B$2:$B$235,"Honor",'Data (parsed)'!$C$2:$C$235,$A16) -> 27
A17: Reputation / standing | B17: =COUNTIFS('Data (parsed)'!$E$2:$E$235,B$15,'Data (parsed)'!$B$2:$B$235,"Honor",'Data (parsed)'!$C$2:$C$235,$A17) -> 2 | C17: =COUNTIFS('Data (parsed)'!$E$2:$E$235,C$15,'Data (parsed)'!$B$2:$B$235,"Honor",'Data (parsed)'!$C$2:$C$235,$A17) -> 3 | D17: =COUNTIFS('Data (parsed)'!$E$2:$E$235,D$15,'Data (parsed)'!$B$2:$B$235,"Honor",'Data (parsed)'!$C$2:$C$235,$A17) -> 1 | E17: =COUNTIFS('Data (parsed)'!$E$2:$E$235,E$15,'Data (parsed)'!$B$2:$B$235,"Honor",'Data (parsed)'!$C$2:$C$235,$A17) -> 0 | F17: =SUMIFS('Data (parsed)'!$I$2:$I$235,'Data (parsed)'!$B$2:$B$235,"Honor",'Data (parsed)'!$C$2:$C$235,$A17,'Data (parsed)'!$J$2:$J$235,0) -> 5 | G17: =SUMIFS('Data (parsed)'!$I$2:$I$235,'Data (parsed)'!$B$2:$B$235,"Honor",'Data (parsed)'!$C$2:$C$235,$A17) -> 11
A18: Tribute / glory | B18: =COUNTIFS('Data (parsed)'!$E$2:$E$235,B$15,'Data (parsed)'!$B$2:$B$235,"Honor",'Data (parsed)'!$C$2:$C$235,$A18) -> 0 | C18: =COUNTIFS('Data (parsed)'!$E$2:$E$235,C$15,'Data (parsed)'!$B$2:$B$235,"Honor",'Data (parsed)'!$C$2:$C$235,$A18) -> 1 | D18: =COUNTIFS('Data (parsed)'!$E$2:$E$235,D$15,'Data (parsed)'!$B$2:$B$235,"Honor",'Data (parsed)'!$C$2:$C$235,$A18) -> 1 | E18: =COUNTIFS('Data (parsed)'!$E$2:$E$235,E$15,'Data (parsed)'!$B$2:$B$235,"Honor",'Data (parsed)'!$C$2:$C$235,$A18) -> 0 | F18: =SUMIFS('Data (parsed)'!$I$2:$I$235,'Data (parsed)'!$B$2:$B$235,"Honor",'Data (parsed)'!$C$2:$C$235,$A18,'Data (parsed)'!$J$2:$J$235,0) -> 4 | G18: =SUMIFS('Data (parsed)'!$I$2:$I$235,'Data (parsed)'!$B$2:$B$235,"Honor",'Data (parsed)'!$C$2:$C$235,$A18) -> 6
A19: Ironic / mocked | B19: =COUNTIFS('Data (parsed)'!$E$2:$E$235,B$15,'Data (parsed)'!$B$2:$B$235,"Honor",'Data (parsed)'!$C$2:$C$235,$A19) -> 0 | C19: =COUNTIFS('Data (parsed)'!$E$2:$E$235,C$15,'Data (parsed)'!$B$2:$B$235,"Honor",'Data (parsed)'!$C$2:$C$235,$A19) -> 3 | D19: =COUNTIFS('Data (parsed)'!$E$2:$E$235,D$15,'Data (parsed)'!$B$2:$B$235,"Honor",'Data (parsed)'!$C$2:$C$235,$A19) -> 1 | E19: =COUNTIFS('Data (parsed)'!$E$2:$E$235,E$15,'Data (parsed)'!$B$2:$B$235,"Honor",'Data (parsed)'!$C$2:$C$235,$A19) -> 0 | F19: =SUMIFS('Data (parsed)'!$I$2:$I$235,'Data (parsed)'!$B$2:$B$235,"Honor",'Data (parsed)'!$C$2:$C$235,$A19,'Data (parsed)'!$J$2:$J$235,0) -> 1 | G19: =SUMIFS('Data (parsed)'!$I$2:$I$235,'Data (parsed)'!$B$2:$B$235,"Honor",'Data (parsed)'!$C$2:$C$235,$A19) -> 5
A20: Absent / dishonor | B20: =COUNTIFS('Data (parsed)'!$E$2:$E$235,B$15,'Data (parsed)'!$B$2:$B$235,"Honor",'Data (parsed)'!$C$2:$C$235,$A20) -> 1 | C20: =COUNTIFS('Data (parsed)'!$E$2:$E$235,C$15,'Data (parsed)'!$B$2:$B$235,"Honor",'Data (parsed)'!$C$2:$C$235,$A20) -> 2 | D20: =COUNTIFS('Data (parsed)'!$E$2:$E$235,D$15,'Data (parsed)'!$B$2:$B$235,"Honor",'Data (parsed)'!$C$2:$C$235,$A20) -> 2 | E20: =COUNTIFS('Data (parsed)'!$E$2:$E$235,E$15,'Data (parsed)'!$B$2:$B$235,"Honor",'Data (parsed)'!$C$2:$C$235,$A20) -> 0 | F20: =SUMIFS('Data (parsed)'!$I$2:$I$235,'Data (parsed)'!$B$2:$B$235,"Honor",'Data (parsed)'!$C$2:$C$235,$A20,'Data (parsed)'!$J$2:$J$235,0) -> 1 | G20: =SUMIFS('Data (parsed)'!$I$2:$I$235,'Data (parsed)'!$B$2:$B$235,"Honor",'Data (parsed)'!$C$2:$C$235,$A20) -> 5
A21: Undifferentiated honor | B21: =COUNTIFS('Data (parsed)'!$E$2:$E$235,B$15,'Data (parsed)'!$B$2:$B$235,"Honor",'Data (parsed)'!$C$2:$C$235,$A21) -> 0 | C21: =COUNTIFS('Data (parsed)'!$E$2:$E$235,C$15,'Data (parsed)'!$B$2:$B$235,"Honor",'Data (parsed)'!$C$2:$C$235,$A21) -> 1 | D21: =COUNTIFS('Data (parsed)'!$E$2:$E$235,D$15,'Data (parsed)'!$B$2:$B$235,"Honor",'Data (parsed)'!$C$2:$C$235,$A21) -> 1 | E21: =COUNTIFS('Data (parsed)'!$E$2:$E$235,E$15,'Data (parsed)'!$B$2:$B$235,"Honor",'Data (parsed)'!$C$2:$C$235,$A21) -> 0 | F21: =SUMIFS('Data (parsed)'!$I$2:$I$235,'Data (parsed)'!$B$2:$B$235,"Honor",'Data (parsed)'!$C$2:$C$235,$A21,'Data (parsed)'!$J$2:$J$235,0) -> 0 | G21: =SUMIFS('Data (parsed)'!$I$2:$I$235,'Data (parsed)'!$B$2:$B$235,"Honor",'Data (parsed)'!$C$2:$C$235,$A21) -> 2
A22: Nobility of character | B22: =COUNTIFS('Data (parsed)'!$E$2:$E$235,B$15,'Data (parsed)'!$B$2:$B$235,"Honor",'Data (parsed)'!$C$2:$C$235,$A22) -> 0 | C22: =COUNTIFS('Data (parsed)'!$E$2:$E$235,C$15,'Data (parsed)'!$B$2:$B$235,"Honor",'Data (parsed)'!$C$2:$C$235,$A22) -> 0 | D22: =COUNTIFS('Data (parsed)'!$E$2:$E$235,D$15,'Data (parsed)'!$B$2:$B$235,"Honor",'Data (parsed)'!$C$2:$C$235,$A22) -> 0 | E22: =COUNTIFS('Data (parsed)'!$E$2:$E$235,E$15,'Data (parsed)'!$B$2:$B$235,"Honor",'Data (parsed)'!$C$2:$C$235,$A22) -> 1 | F22: =SUMIFS('Data (parsed)'!$I$2:$I$235,'Data (parsed)'!$B$2:$B$235,"Honor",'Data (parsed)'!$C$2:$C$235,$A22,'Data (parsed)'!$J$2:$J$235,0) -> 0 | G22: =SUMIFS('Data (parsed)'!$I$2:$I$235,'Data (parsed)'!$B$2:$B$235,"Honor",'Data (parsed)'!$C$2:$C$235,$A22) -> 1
A23: Total | B23: =SUM(B16:B22) -> 9 | C23: =SUM(C16:C22) -> 28 | D23: =SUM(D16:D22) -> 8 | E23: =SUM(E16:E22) -> 1 | F23: =SUM(F16:F22) -> 12 | G23: =SUM(G16:G22) -> 57

Sheet Russian renderings
A1: Russian renderings: how each subtype (frame) is rendered, with counts
A3: English word | B3: Subtype | C3: Rendering (lemma / form; bracketed = paraphrase/omission) | D3: Count
A4: Shame | B4: Absent moral shame | C4: стеснение | D4: =SUMIFS('Data (parsed)'!$I$2:$I$235,'Data (parsed)'!$B$2:$B$235,$A4,'Data (parsed)'!$C$2:$C$235,$B4,'Data (parsed)'!$G$2:$G$235,$C4) -> 1
A5: Shame | B5: Absent moral shame | C5: стыд | D5: =SUMIFS('Data (parsed)'!$I$2:$I$235,'Data (parsed)'!$B$2:$B$235,$A5,'Data (parsed)'!$C$2:$C$235,$B5,'Data (parsed)'!$G$2:$G$235,$C5) -> 1
A6: Shame | B6: Absent moral shame | C6: угрызение | D6: =SUMIFS('Data (parsed)'!$I$2:$I$235,'Data (parsed)'!$B$2:$B$235,$A6,'Data (parsed)'!$C$2:$C$235,$B6,'Data (parsed)'!$G$2:$G$235,$C6) -> 1
A7: Shame | B7: Absent shame | C7: стыдиться | D7: =SUMIFS('Data (parsed)'!$I$2:$I$235,'Data (parsed)'!$B$2:$B$235,$A7,'Data (parsed)'!$C$2:$C$235,$B7,'Data (parsed)'!$G$2:$G$235,$C7) -> 3
A8: Shame | B8: Absent shame | C8: [paraphrase / no single-word equivalent] | D8: =SUMIFS('Data (parsed)'!$I$2:$I$235,'Data (parsed)'!$B$2:$B$235,$A8,'Data (parsed)'!$C$2:$C$235,$B8,'Data (parsed)'!$G$2:$G$235,$C8) -> 1
A9: Shame | B9: Absent shame | C9: Смутить | D9: =SUMIFS('Data (parsed)'!$I$2:$I$235,'Data (parsed)'!$B$2:$B$235,$A9,'Data (parsed)'!$C$2:$C$235,$B9,'Data (parsed)'!$G$2:$G$235,$C9) -> 1
A10: Shame | B10: Absent shame | C10: бесстыдно | D10: =SUMIFS('Data (parsed)'!$I$2:$I$235,'Data (parsed)'!$B$2:$B$235,$A10,'Data (parsed)'!$C$2:$C$235,$B10,'Data (parsed)'!$G$2:$G$235,$C10) -> 1
A11: Shame | B11: Absent shame | C11: бесстыдство | D11: =SUMIFS('Data (parsed)'!$I$2:$I$235,'Data (parsed)'!$B$2:$B$235,$A11,'Data (parsed)'!$C$2:$C$235,$B11,'Data (parsed)'!$G$2:$G$235,$C11) -> 1
A12: Shame | B12: Absent shame | C12: зазрение | D12: =SUMIFS('Data (parsed)'!$I$2:$I$235,'Data (parsed)'!$B$2:$B$235,$A12,'Data (parsed)'!$C$2:$C$235,$B12,'Data (parsed)'!$G$2:$G$235,$C12) -> 1
A13: Shame | B13: Absent shame | C13: осуждать | D13: =SUMIFS('Data (parsed)'!$I$2:$I$235,'Data (parsed)'!$B$2:$B$235,$A13,'Data (parsed)'!$C$2:$C$235,$B13,'Data (parsed)'!$G$2:$G$235,$C13) -> 1
A14: Shame | B14: Absent shame | C14: пристыдить | D14: =SUMIFS('Data (parsed)'!$I$2:$I$235,'Data (parsed)'!$B$2:$B$235,$A14,'Data (parsed)'!$C$2:$C$235,$B14,'Data (parsed)'!$G$2:$G$235,$C14) -> 1
A15: Shame | B15: Absent shame | C15: стесняться | D15: =SUMIFS('Data (parsed)'!$I$2:$I$235,'Data (parsed)'!$B$2:$B$235,$A15,'Data (parsed)'!$C$2:$C$235,$B15,'Data (parsed)'!$G$2:$G$235,$C15) -> 1
... A140: Honor | B140: Undifferentiated honor | C140: честное предложение. | D140: =SUMIFS('Data (parsed)'!$I$2:$I$235,'Data (parsed)'!$B$2:$B$235,$A140,'Data (parsed)'!$C$2:$C$235,$B140,'Data (parsed)'!$G$2:$G$235,$C140) -> 1

Sheet Kazakh renderings
A1: Kazakh renderings: how each subtype (frame) is rendered, with counts
A3: English word | B3: Subtype | C3: Rendering (lemma / form; bracketed = paraphrase/omission) | D3: Count
A4: Shame | B4: Absent moral shame | C4: QYMSYNU | D4: =SUMIFS('Data (parsed)'!$I$2:$I$235,'Data (parsed)'!$B$2:$B$235,$A4,'Data (parsed)'!$C$2:$C$235,$B4,'Data (parsed)'!$H$2:$H$235,$C4) -> 1
A5: Shame | B5: Absent moral shame | C5: [paraphrase / no single-word equivalent] | D5: =SUMIFS('Data (parsed)'!$I$2:$I$235,'Data (parsed)'!$B$2:$B$235,$A5,'Data (parsed)'!$C$2:$C$235,$B5,'Data (parsed)'!$H$2:$H$235,$C5) -> 1
A6: Shame | B6: Absent moral shame | C6: ŪİAT | D6: =SUMIFS('Data (parsed)'!$I$2:$I$235,'Data (parsed)'!$B$2:$B$235,$A6,'Data (parsed)'!$C$2:$C$235,$B6,'Data (parsed)'!$H$2:$H$235,$C6) -> 1
A7: Shame | B7: Absent shame | C7: ŪİALU | D7: =SUMIFS('Data (parsed)'!$I$2:$I$235,'Data (parsed)'!$B$2:$B$235,$A7,'Data (parsed)'!$C$2:$C$235,$B7,'Data (parsed)'!$H$2:$H$235,$C7) -> 6
A8: Shame | B8: Absent shame | C8: QYSYLU | D8: =SUMIFS('Data (parsed)'!$I$2:$I$235,'Data (parsed)'!$B$2:$B$235,$A8,'Data (parsed)'!$C$2:$C$235,$B8,'Data (parsed)'!$H$2:$H$235,$C8) -> 2
A9: Shame | B9: Absent shame | C9: KINÄLAU | D9: =SUMIFS('Data (parsed)'!$I$2:$I$235,'Data (parsed)'!$B$2:$B$235,$A9,'Data (parsed)'!$C$2:$C$235,$B9,'Data (parsed)'!$H$2:$H$235,$C9) -> 1
A10: Shame | B10: Absent shame | C10: QYMSYNU | D10: =SUMIFS('Data (parsed)'!$I$2:$I$235,'Data (parsed)'!$B$2:$B$235,$A10,'Data (parsed)'!$C$2:$C$235,$B10,'Data (parsed)'!$H$2:$H$235,$C10) -> 1
A11: Shame | B11: Absent shame | C11: ŪİALTU | D11: =SUMIFS('Data (parsed)'!$I$2:$I$235,'Data (parsed)'!$B$2:$B$235,$A11,'Data (parsed)'!$C$2:$C$235,$B11,'Data (parsed)'!$H$2:$H$235,$C11) -> 1
A12: Shame | B12: Absent shame | C12: ŪİATSYZDYQ | D12: =SUMIFS('Data (parsed)'!$I$2:$I$235,'Data (parsed)'!$B$2:$B$235,$A12,'Data (parsed)'!$C$2:$C$235,$B12,'Data (parsed)'!$H$2:$H$235,$C12) -> 1
A13: Shame | B13: Absent social shame | C13: ŪİALU | D13: =SUMIFS('Data (parsed)'!$I$2:$I$235,'Data (parsed)'!$B$2:$B$235,$A13,'Data (parsed)'!$C$2:$C$235,$B13,'Data (parsed)'!$H$2:$H$235,$C13) -> 3
A14: Shame | B14: Absent social shame | C14: ŪİAT | D14: =SUMIFS('Data (parsed)'!$I$2:$I$235,'Data (parsed)'!$B$2:$B$235,$A14,'Data (parsed)'!$C$2:$C$235,$B14,'Data (parsed)'!$H$2:$H$235,$C14) -> 2
A15: Shame | B15: Absent social shame | C15: QYSYLU | D15: =SUMIFS('Data (parsed)'!$I$2:$I$235,'Data (parsed)'!$B$2:$B$235,$A15,'Data (parsed)'!$C$2:$C$235,$B15,'Data (parsed)'!$H$2:$H$235,$C15) -> 1
... A147: Honor | B147: Undifferentiated honor | C147: ADAL ŪİAT | D147: =SUMIFS('Data (parsed)'!$I$2:$I$235,'Data (parsed)'!$B$2:$B$235,$A147,'Data (parsed)'!$C$2:$C$235,$B147,'Data (parsed)'!$H$2:$H$235,$C147) -> 1

Sheet Data (parsed)
A1: # | B1: Domain | C1: Subtype | D1: Part | E1: Character | F1: Mode | G1: Russian rendering | H1: Kazakh rendering | I1: Token | J1: IsPrincipal
A2: 1 | B2: Shame | C2: Moral shame | D2: P1 | E2: Scarlett | F2: felt | G2: пристыдить | H2: ŪİALTU | I2: 1 | J2: 1
A3: 2 | B3: Shame | C3: Moral shame | D3: P1 | E3: Scarlett | F3: felt | G3: устыдиться | H3: ŪİALU | I3: 1 | J3: 1
A4: 3 | B4: Shame | C4: Moral shame | D4: P3 | E4: Scarlett | F4: felt | G4: стыдно | H4: ŪİALU | I4: 1 | J4: 1
A5: 4 | B5: Shame | C5: Moral shame | D5: P3 | E5: Scarlett | F5: felt | G5: устыдиться | H5: ŪİALU | I5: 1 | J5: 1
A6: 5 | B6: Shame | C6: Moral shame | D6: P3 | E6: Scarlett | F6: felt | G6: стыдно | H6: ŪİALU | I6: 1 | J6: 1
A7: 6 | B7: Shame | C7: Moral shame | D7: P3 | E7: Scarlett | F7: felt | G7: стыдно | H7: [paraphrase / no single-word equivalent] | I7: 1 | J7: 1
A8: 7 | B8: Shame | C8: Moral shame | D8: P4 | E8: Scarlett | F8: ascribed | G8: стыдно | H8: ŪİAT | I8: 1 | J8: 1
A9: 8 | B9: Shame | C9: Moral shame | D9: P4 | E9: Scarlett | F9: felt | G9: пристыженный | H9: QOLAİSYZ | I9: 1 | J9: 1
A10: 9 | B10: Shame | C10: Moral shame | D10: P4 | E10: Scarlett | F10: ascribed | G10: стыдно | H10: ŪİALU | I10: 1 | J10: 1
A11: 10 | B11: Shame | C11: Moral shame | D11: P4 | E11: Scarlett | F11: felt | G11: слеза | H11: [paraphrase / no single-word equivalent] | I11: 1 | J11: 1
A12: 11 | B12: Shame | C12: Moral shame | D12: P4 | E12: Scarlett | F12: felt | G12: стыд | H12: ŪİAT | I12: 1 | J12: 1
A13: 12 | B13: Shame | C13: Moral shame | D13: P4 | E13: Scarlett | F13: felt | G13: стыд | H13: ŪİAT | I13: 1 | J13: 1
... A235: 231 | B235: Honor | C235: Undifferentiated honor | D235: P4 | E235: Rhett | F235: spoken | G235: честное предложение. | H235: ADAL ŪİAT | I235: 1 | J235: 1
